Workbook

Sheet As Values
N2: Mister Kiosk Stickers (KSS) | T2: Gen 2 Peg KSS | AB2: Gen 1 Peg KSS | AE2: DRB KSS | AN2: Awareness Flyers | BG2: Handheld Menus | BZ2: 28x44 Windscreens | CG2: Roadside Banners | CN2: Scancards | CP2: V | CQ2: V | CT2: Collateral Guide | DB2: Box Sticker
A3: NEW BUILD BLITZ WAVE 4 August 2026 | E3: Last updated | F3: 46244 | M3: Filename | N3: NB Blitz 4-UWC-KSS-Mister-V4-10F-101-Print.pdf | O3: NB Blitz 4-UWC-KSS-Mister-V4-8F-304-Print.pdf | P3: NB Blitz 4-UWC-KSS-Mister-V4-A-01-Print.pdf | Q3: NB Blitz 4-UWC-KSS-Mister-V4-B-06-Print.pdf | R3: NB Blitz 4-UWC-KSS-Mister-V4-D-01-Print.pdf | S3: NB Blitz 4-UWC-KSS-Mister-V4-E-01-Print.pdf | T3: 2026 09 Promo-NB Blitz 4-UWC-KSS-Peg2-A-01-Print.pdf | U3: 2026 09 Promo-NB Blitz 4-UWC-KSS-Peg2-B-01-Print.pdf | V3: 2026 09 Promo-NB Blitz 4-UWC-KSS-Peg2-C-01-Print.pdf | W3: 2026 09 Promo-NB Blitz 4-UWC-KSS-Peg2-D-01-Print.pdf | X3: 2026 09 Promo-NB Blitz 4-UWC-KSS-Peg2 8D-04-Print.pdf | Y3: 2026 09 Promo-NB Blitz 4-UWC-KSS-Peg2-E-01-Print.pdf | Z3: 2026 09 Promo-NB Blitz 4-UWC-KSS-Peg2-8F-304-Print.pdf | AA3: 2026 09 Promo-NB Blitz 4-UWC-KSS-Peg2-10F-101-Print.pdf | AB3: 2026 09 Promo-NB Blitz 4-UWC-KSS-Peg1 10F-201-Print.pdf | AC3: 2026 09 Promo-NB Blitz 4-UWC-KSS-Peg1-D-01-Print.pdf | AD3: 2026 09 Promo-NB Blitz 4-UWC-KSS-Peg1-B-01-Print.pdf | AE3: 2026 09 Promo-NB Blitz 4-UWC-KSS-DRB XPT 2012-A-01-Print.pdf | AF3: 2026 09 Promo-NB Blitz 4-UWC-KSS-DRB XPT 2012-B-01-Print.pdf | AG3: 2026 09 Promo-NB Blitz 4-UWC-KSS-DRB XPT 2012-C-01-Print.pdf | AH3: 2026 09 Promo-NB Blitz 4-UWC-KSS-DRB XPT 2012-D-01-Print.pdf | AI3: 2026 09 Promo-NB Blitz 4-UWC-KSS-DRB XPT 2012 8D-05-Print.pdf | AJ3: 2026 09 Promo-NB Blitz 4-UWC-KSS-DRB XPT 2012-E-01-Print.pdf | AK3: 2026 09 Promo-NB Blitz 4-UWC-KSS-DRB XPT 2012-8F-304-Print.pdf | AL3: 2026 09 Promo-NB Blitz 4-UWC-KSS-DRB XPT 2012-10F-101-Print.pdf | AM3: 2026 09 Promo-NB Blitz 4-UWC-KSS-DRB XPT 2012-E-01-Print.pdf | AN3: 2026 09 Promo-NB Blitz 4-POR-1mo-UWC-Awareness-10-10F-101-Print.pdf | AO3: 2026 09 Promo-NB Blitz 4-POR-1mo-UWC-Awareness-10-10F-104-Print.pdf | AP3: 2026 09 Promo-NB Blitz 4-POR-1mo-UWC-Awareness-10-10F-201-Print.pdf | AQ3: 2026 09 Promo-NB Blitz 4-999-1mo-UWC-Awareness-8D-04-Print.pdf | AR3: 2026 09 Promo-NB Blitz 4-999-1mo-UWC-Awareness-8D-05-Print.pdf | AS3: 2026 09 Promo-NB Blitz 4-POR-1mo-UWC-Awareness-8-8F-304-Print.pdf | AT3: 2026 09 Promo-NB Blitz 4-10-3mos-UWC-Awareness-A-01-Print.pdf | AU3: 2026 09 Promo-NB Blitz 4-15 off-1mo-UWC-Awareness-B-01-Print.pdf | AV3: 2026 09 Promo-NB Blitz 4-15 off-1mo-UWC-Awareness-B-05-Print.pdf | AW3: 2026 09 Promo-NB Blitz 4-15 off-1mo-UWC-Awareness-B-06-Print.pdf | AX3: 2026 09 Promo-NB Blitz 4-5 10 15-1mo-UWC-Awareness-V2-C-01-Print.pdf | AY3: 2026 09 Promo-NB Blitz 4-5 10 15-1mo-UWC-Awareness-V2-C-04-Print.pdf | AZ3: 2026 09 Promo-NB Blitz 4-999-1mo-UWC-Awareness-D-01-Print.pdf | BA3: 2026 09 Promo-NB Blitz 4-999-1mo-UWC-Awareness-D-02-Print.pdf | BB3: 2026 09 Promo-NB Blitz 4-999-1mo-UWC-Awareness-D-03-Print.pdf | BC3: 2026 09 Promo-NB Blitz 4-999-1mo-UWC-Awareness-D-06-Print.pdf | BD3: 2026 09 Promo-NB Blitz 4-50 off-1mo-UWC-Awareness-E-01-Print.pdf | BE3: 2026 09 Promo-NB Blitz 4-50 off-1mo-UWC-Awareness-E-03-Print.pdf | BF3: 2026 09 Promo-NB Blitz 4-50 off-1mo-UWC-Awareness-E-07-Print.pdf | BG3: 2026 09 Promo-NB Blitz 4-POR-1mo-HandheldMenu-10-10F-101-Print.pdf | BH3: 2026 09 Promo-NB Blitz 4-POR-1mo-HandheldMenu-10-10F-104-Print.pdf | BI3: 2026 09 Promo-NB Blitz 4-POR-1mo-HandheldMenu-10-10F-201-Print.pdf | BJ3: 2026 09 Promo-NB Blitz 4-999-1mo-HandheldMenu-8D-04-Print.pdf | BK3: 2026 09 Promo-NB Blitz 4-999-1mo-HandheldMenu-8D-05-Print.pdf | BL3: 2026 09 Promo-NB Blitz 4-POR-1mo-HandheldMenu-8-8F-304-Print.pdf | BM3: 2026 09 Promo-NB Blitz 4-10-3mos-HandheldMenu-A-01-Print.pdf | BN3: 2026 09 Promo-NB Blitz 4-15 off-1mo-HandheldMenu-B-01-Print.pdf | BO3: 2026 09 Promo-NB Blitz 4-15 off-1mo-HandheldMenu-B-05-Print.pdf | BP3: 2026 09 Promo-NB Blitz 4-15 off-1mo-HandheldMenu-B-06-Print.pdf | BQ3: 2026 09 Promo-NB Blitz 4-5 10 15-1mo-HandheldMenu-V2-C-01-Print.pdf | BR3: 2026 09 Promo-NB Blitz 4-5 10 15-1mo-HandheldMenu-V2-C-04-Print.pdf | BS3: 2026 09 Promo-NB Blitz 4-999-1mo-HandheldMenu-D-01-Print.pdf | BT3: 2026 09 Promo-NB Blitz 4-999-1mo-HandheldMenu-D-02-Print.pdf | BU3: 2026 09 Promo-NB Blitz 4-999-1mo-HandheldMenu-D-03-Print.pdf | BV3: 2026 09 Promo-NB Blitz 4-999-1mo-HandheldMenu-D-06-Print.pdf | BW3: 2026 09 Promo-NB Blitz 4-50 off-1mo-HandheldMenu-E-01-Print.pdf | BX3: 2026 09 Promo-NB Blitz 4-50 off-1mo-HandheldMenu-E-03-Print.pdf | BY3: 2026 09 Promo-NB Blitz 4-50 off-1mo-HandheldMenu-E-07-Print.pdf | BZ3: 2026 09 Promo-NB Blitz 4-UWC-WS-28x44-A-Print.pdf | CA3: 2026 09 Promo-NB Blitz 4-UWC-WS-28x44-B-Print.pdf | CB3: 2026 09 Promo-NB Blitz 4-UWC-WS-28x44-D-Print.pdf | CC3: 2026 09 Promo-NB Blitz 4-UWC-WS-28x44-8D-Print.pdf | CD3: 2026 09 Promo-NB Blitz 4-UWC-WS-28x44-E-Print.pdf | CE3: 2026 09 Promo-NB Blitz 4-UWC-WS-28x44-8F-Print.pdf | CF3: 2026 09 Promo-NB Blitz 4-UWC-WS-28x44-10F-Print.pdf | CG3: 2026 09 Promo-UWC-96x36 Banner-V4-A-Print.pdf | CH3: 2026 09 Promo-UWC-96x36 Banner-V4-B-Print.pdf | CI3: 2026 09 Promo-UWC-96x36 Banner-V4-C-Print.pdf | CJ3: 2026 09 Promo-UWC-96x36 Banner-V4-D-Print.pdf | CK3: 2026 09 Promo-UWC-96x36 Banner-V4-E-Print.pdf | CL3: 2026 09 Promo-UWC-96x36 Banner-V4-8F-Print.pdf | CM3: 2026 09 Promo-UWC-96x36 Banner-V4-10F-Print.pdf | CN3: 2026 09 Promo 10off 3mos Scan Cards-V2-Print | CO3: 2026 09 Promo-15 Off-1mo-ScanCard-Print | CP3: 2026 09 Promo-5-10-15-1mo-ScanCardSet-Print | CQ3: 2026 09 Promo-999-1mo-ScanCardSet-Print.pdf | CR3: 2026 09 Promo-50off-1mo-ScanCard-Print.pdf | CS3: 2026 09 All Plans PoR 1mo Scan Cards-V2-Print.pdf | CT3: 2026 09 Promo-NB Blitz 4-Collateral Guides-A-Print.pdf | CU3: 2026 09 Promo-NB Blitz 4-Collateral Guides-B-Print.pdf | CV3: 2026 09 Promo-NB Blitz 4-Collateral Guides-C-Print.pdf | CW3: 2026 09 Promo-NB Blitz 4-Collateral Guides-8D-Print.pdf | CX3: 2026 09 Promo-NB Blitz 4-Collateral Guides-D-Print.pdf | CY3: 2026 09 Promo-NB Blitz 4-Collateral Guides-E-Print.pdf | CZ3: 2026 09 Promo-NB Blitz 4-Collateral Guides-8F-Print.pdf | DA3: 2026 09 Promo-NB Blitz 4-Collateral Guides-10F-Print.pdf | DB3: Box Sticker
A4: Region | B4: CC | C4: Store # | D4: Vlookup Store # | E4: Location Name | F4: General Manager | G4: Address | H4: City | I4: State | J4: Zip Code | K4: Phone Number | L4: Promo | M4: Art Code | N4: 10F | O4: 8F | P4: A | Q4: B | R4: D | S4: E | T4: A | U4: B | V4: C | W4: D | X4: 8D | Y4: E | Z4: 8F | AA4: 10F | AB4: 10F | AC4: D | AD4: B | AE4: A | AF4: B | AG4: C | AH4: D | AI4: 8D | AJ4: E | AK4: 8F | AL4: 10F | AM4: E | AN4: 10F-101 | AO4: 10F-104 | AP4: 10F-201 | AQ4: 8D-04 | AR4: 8D-05 | AS4: 8F-304 | AT4: A01 | AU4: B01 | AV4: B05 | AW4: B06 | AX4: C01 | AY4: C04 | AZ4: D01 | BA4: D02 | BB4: D03 | BC4: D06 | BD4: E01 | BE4: E03 | BF4: E07 | BG4: 10F-101 | BH4: 10F-104 | BI4: 10F-201 | BJ4: 8D-04 | BK4: 8D-05 | BL4: 8F-304 | BM4: A01 | BN4: B01 | BO4: B05 | BP4: B06 | BQ4: C01 | BR4: C04 | BS4: D01 | BT4: D02 | BU4: D03 | BV4: D06 | BW4: E01 | BX4: E03 | BY4: E07 | BZ4: A | CA4: B | CB4: D | CC4: 8D | CD4: E | CE4: 8F | CF4: 10F | CG4: A | CH4: B | CI4: C | CJ4: D | CK4: E | CL4: 8F | CM4: 10F | CN4: A5 | CO4: B7 | CP4: C8 | CQ4: D9 | CR4: E12 | CS4: F | CT4: A | CU4: B | CV4: C | CW4: 8D | CX4: D | CY4: E | CZ4: 8F | DA4: 10F
A5: AL-Huntsville | B5: 813 | C5: 0041 | D5: 41 | E5: Hartselle | F5: MaryGrace Gilley | G5: 1206 HIGHWAY 31 NW | H5: HARTSELLE | I5: AL | J5: 35640-4421 | K5: (256) 773-7737 | L5: 50% off all plan 1 mo. | M5: E01 | AJ5: 1 | BD5: 1500 | BW5: 10 | CK5: 2 | CR5: 10 | CX5: 1 | DB5: 1
A6: AL-Huntsville | B6: 813 | C6: 0042 | D6: 42 | E6: Limestone | F6: Jamie Garrie | G6: 1321 US HIGHWAY 72 E | H6: ATHENS | I6: AL | J6: 35611-4405 | K6: (256) 233-2290 | L6: 50% off all plan 1 mo. | M6: E01 | AJ6: 1 | BD6: 1500 | BW6: 10 | CK6: 2 | CR6: 10 | CX6: 1 | DB6: 1
A7: AL-Huntsville | B7: 813 | C7: 0043 | D7: 43 | E7: Madison | F7: Klaryssa Melendrez | G7: 5509 PROMENADE POINT PKWY | H7: MADISON | I7: AL | J7: 35758-6701 | K7: (256) 895-2693 | L7: 50% off all plan 1 mo. | M7: E01 | AJ7: 1 | BD7: 1500 | BW7: 10 | CK7: 2 | CR7: 10 | CX7: 1 | DB7: 1
A8: AL-Huntsville | B8: 813 | C8: 0044 | D8: 44 | E8: Setter | F8: Stevie Wagner | G8: 627 BELTLINE RD SW | H8: DECATUR | I8: AL | J8: 35601 | K8: (256) 867-0108 | L8: 50% off all plan 1 mo. | M8: E01 | AJ8: 1 | BD8: 1500 | BW8: 10 | CK8: 2 | CR8: 10 | CX8: 1 | DB8: 1
A9: AL-Huntsville | B9: 813 | C9: 0045 | D9: 45 | E9: 9th Street | F9: Christian Rider | G9: 2240 BELTLINE RD SW | H9: DECATUR | I9: AL | J9: 35601-7001 | K9: (256) 822-2939 | L9: 50% off all plan 1 mo. | M9: E01 | AJ9: 1 | BD9: 1500 | BW9: 10 | CK9: 2 | CR9: 10 | CX9: 1 | DB9: 1
A10: AL-Huntsville | B10: 813 | C10: 0046 | D10: 46 | E10: Bassett Ave | F10: Josh Lamey | G10: 721 14TH ST SE | H10: DECATUR | I10: AL | J10: 35601-5911 | K10: (256) 822-2029 | L10: 50% off all plan 1 mo. | M10: E01 | AJ10: 1 | BD10: 1500 | BW10: 10 | CK10: 2 | CR10: 10 | CX10: 1 | DB10: 1
A11: AL-Huntsville | B11: 813 | C11: 0047 | D11: 47 | E11: Grace | F11: Justin Williams | G11: 403 US HIGHWAY 72 W | H11: ATHENS | I11: AL | J11: 35611-4207 | K11: (256) 998-5312 | L11: 50% off all plan 1 mo. | M11: E01 | AJ11: 1 | BD11: 1500 | BW11: 10 | CK11: 2 | CR11: 10 | CX11: 1 | DB11: 1
A12: AL-Huntsville | B12: 813 | C12: 0051 | D12: 51 | E12: Azalea | F12: Colby Gray | G12: 271 AZALEA DR | H12: FLORENCE | I12: AL | J12: 35630-1733 | K12: (256) 766-2726 | L12: 50% off all plan 1 mo. | M12: E01 | AJ12: 1 | BD12: 1500 | BW12: 10 | CK12: 2 | CR12: 10 | CX12: 1 | DB12: 1
A13: AL-Huntsville | B13: 813 | C13: 0052 | D13: 52 | E13: Muscle Shoals | F13: Olivia Thomsen | G13: 702 AVALON AVE | H13: MUSCLE SHOALS | I13: AL | J13: 35661-2304 | K13: (256) 389-3890 | L13: 50% off all plan 1 mo. | M13: E01 | BD13: 1500 | BW13: 10 | CD13: 1 | CK13: 2 | CR13: 10 | CX13: 1 | DB13: 1
A14: AL-Huntsville | B14: 813 | C14: 0053 | D14: 53 | E14: Cloverdale | F14: Katherine Huddleston | G14: 2914 CLOVERDALE RD | H14: FLORENCE | I14: AL | J14: 35633 | K14: (256) 712-0183 | L14: 50% off all plan 1 mo. | M14: E01 | AJ14: 1 | BD14: 1500 | BW14: 10 | CK14: 2 | CR14: 10 | CX14: 1 | DB14: 1
A15: AZ-Tucson | B15: 806 | C15: 0326 | D15: 326 | E15: Swan | F15: Sierrah Bainter | G15: 4600 E BROADWAY BLVD | H15: TUCSON | I15: AZ | J15: 85711-3512 | K15: (520) 428-0256 | L15: $9.99 all plans 1 mo. | M15: D01 | AZ15: 1500 | BS15: 10 | CB15: 1 | CJ15: 2 | CQ15: 10 | CX15: 1 | DB15: 1
A16: AZ-Tucson | B16: 806 | C16: 0327 | D16: 327 | E16: South Kolb | F16: Evelyn Conger | G16: 2409 S KOLB RD | H16: TUCSON | I16: AZ | J16: 85710 | K16: (520) 721-9290 | L16: $9.99 all plans 1 mo. | M16: D01 | AZ16: 1500 | BS16: 10 | CB16: 1 | CJ16: 2 | CQ16: 10 | CX16: 1 | DB16: 1
A17: AZ-Tucson | B17: 806 | C17: 0328 | D17: 328 | E17: Euclid | F17: Stefanie Osuna | G17: 730 E BROADWAY BLVD | H17: TUCSON | I17: AZ | J17: 85719 | K17: (520) 623-2923 | L17: $9.99 all plans 1 mo. | M17: D01 | AZ17: 1500 | BS17: 10 | CB17: 1 | CJ17: 2 | CQ17: 10 | CX17: 1 | DB17: 1
A18: AZ-Tucson | B18: 806 | C18: 0335 | D18: 335 | E18: E Grant | F18: 0 | G18: 3150 E GRANT RD | H18: TUCSON | I18: AZ | J18: 85716 | K18: (520) 881-1486 | L18: $9.99 all plans 1 mo. | M18: D01 | AZ18: 1500 | BS18: 10 | CB18: 1 | CJ18: 2 | CQ18: 10 | CX18: 1 | DB18: 1
A19: AZ-Tucson | B19: 806 | C19: 1329 | D19: 1329 | E19: Craycroft | F19: Chandrani Das | G19: 5515 E GRANT RD | H19: TUCSON | I19: AZ | J19: 85712 | K19: (520) 497-1922 | L19: $9.99 all plans 1 mo. | M19: D01 | R19: 2 | AZ19: 1500 | BS19: 10 | CJ19: 2 | CQ19: 10 | CX19: 1 | DB19: 1
A20: AZ-Tucson | B20: 806 | C20: 1331 | D20: 1331 | E20: Twin Peaks | F20: Vanna Valdez | G20: 6520 W MARANA CENTER BL | H20: TUCSON | I20: AZ | J20: 85742 | K20: (520) 335-8707 | L20: $9.99 all plans 1 mo. | M20: D01 | R20: 1 | AZ20: 1500 | BS20: 10 | CJ20: 2 | CQ20: 10 | CX20: 1 | DB20: 1
A21: AZ-Tucson | B21: 806 | C21: 2552 | D21: 2552 | E21: Tucson Mall | F21: Natalie Vazquez Martinez | G21: 4646 N ORACLE | H21: TUCSON | I21: AZ | J21: 85705 | K21: (520) 485-2620 | L21: $9.99 all plans 1 mo. | M21: D01 | R21: 1 | AZ21: 1500 | BS21: 10 | CJ21: 2 | CQ21: 10 | CX21: 1 | DB21: 1
A22: AZ-Tucson | B22: 806 | C22: 2557 | D22: 2557 | E22: Cardinal | F22: Martin Soto | G22: 2850 W VALENCIA ROAD | H22: TUCSON | I22: AZ | J22: 85746 | K22: (520) 497-1992 | L22: $9.99 all plans 1 mo. | M22: D01 | R22: 1 | AZ22: 1500 | BS22: 10 | CJ22: 2 | CQ22: 10 | CX22: 1 | DB22: 1
A23: CA-Bakersfield | B23: 830 | C23: 1016 | D23: 1016 | E23: Rosedale Hwy | F23: Adrian Vargas | G23: 11921 ROSEDALE HIGHWAY | H23: BAKERSFIELD | I23: CA | J23: 93312 | K23: (661) 230-5335 | L23: $9.99 all plans 1 mo. | M23: D01 | W23: 2 | AZ23: 1500 | BS23: 10 | CJ23: 2 | CQ23: 10 | CX23: 1 | DB23: 1
A24: CA-Bakersfield | B24: 830 | C24: 1034 | D24: 1034 | E24: Carmen | F24: Edgar Barron | G24: 1925 S BROADWAY | H24: SANTA MARIA | I24: CA | J24: 93454 | K24: (805) 621-6835 | L24: $9.99 all plans 1 mo. | M24: D01 | R24: 2 | AZ24: 1500 | BS24: 10 | CJ24: 2 | CQ24: 10 | CX24: 1 | DB24: 1
A25: CA-Bakersfield | B25: 830 | C25: 1035 | D25: 1035 | E25: Hosking | F25: Susana Ledina | G25: 1601 HOSKING AVE | H25: BAKERSFIELD | I25: CA | J25: 93307 | K25: (661) 336-9952 | L25: $9.99 all plans 1 mo. | M25: D01 | R25: 1 | AZ25: 1500 | BS25: 10 | CJ25: 2 | CQ25: 10 | CX25: 1 | DB25: 1
A26: CA-Bakersfield | B26: 830 | C26: 1038 | D26: 1038 | E26: Heath | F26: Hailey Divina | G26: 16214 STOCKDALE HWY | H26: BAKERSFIELD | I26: CA | J26: 93314 | K26: (661) 336-9403 | L26: $9.99 all plans 1 mo. | M26: D01 | R26: 2 | AZ26: 1500 | BS26: 10 | CJ26: 2 | CQ26: 10 | CX26: 1 | DB26: 1
A27: CA-Bakersfield | B27: 830 | C27: 1058 | D27: 1058 | E27: Stockdale | F27: Jorge Escobar | G27: 11417 STOCKDALE HWY | H27: BAKERSFIELD | I27: CA | J27: 93311 | K27: (661) 636-6520 | L27: $9.99 all plans 1 mo. | M27: D01 | R27: 2 | AZ27: 1500 | BS27: 10 | CJ27: 2 | CQ27: 10 | CX27: 1 | DB27: 1
A28: CA-Los Angeles | B28: 830 | C28: 1013 | D28: 1013 | E28: Hwy 138 | F28: Kayla Lopez | G28: 1822 E PALMDALE BLVD | H28: PALMDALE | I28: CA | J28: 93550 | K28: (661) 268-6424 | L28: $9.99 all plans 1 mo. | M28: D01 | W28: 2 | AZ28: 1500 | BS28: 10 | CJ28: 2 | CQ28: 10 | CX28: 1 | DB28: 1
A29: CA-Los Angeles | B29: 830 | C29: 1018 | D29: 1018 | E29: Rialto | F29: Olivia Rodriguez | G29: 127 WEST VALLEY BLVD | H29: RIALTO | I29: CA | J29: 92376 | K29: (909) 237-8099 | L29: $9.99 all plans 1 mo. | M29: D01 | R29: 2 | AZ29: 1500 | BS29: 10 | CJ29: 2 | CQ29: 10 | CX29: 1 | DB29: 1
A30: CA-Los Angeles | B30: 830 | C30: 1027 | D30: 1027 | E30: Stoneridge | F30: Zachary Ojeda | G30: 27240 EUCALYPTUS AVE | H30: MORENO VALLEY | I30: CA | J30: 92555 | K30: (951) 221-3009 | L30: $9.99 all plans 1 mo. | M30: D01 | R30: 2 | AZ30: 1500 | BS30: 10 | CJ30: 2 | CQ30: 10 | CX30: 1 | DB30: 1
A31: CA-Los Angeles | B31: 830 | C31: 1037 | D31: 1037 | E31: Varsity | F31: Anthony Fickewirth | G31: 4212 N VARSITY AVE | H31: SAN BERNARDINO | I31: CA | J31: 92407 | K31: (909) 277-6601 | L31: $9.99 all plans 1 mo. | M31: D01 | R31: 2 | AZ31: 1500 | BS31: 10 | CJ31: 2 | CQ31: 10 | CX31: 1 | DB31: 1
A32: CA-Modesto | B32: 831 | C32: 0915 | D32: 915 | E32: Merced | F32: Manuel Toro Garcia | G32: 1800 WEST OLIVE AVE | H32: MERCED | I32: CA | J32: 95348 | K32: (209) 388-9274 | L32: $9.99 all plans 1 mo. | M32: D01 | W32: 1 | AZ32: 1500 | BS32: 10 | CJ32: 2 | CQ32: 10 | CX32: 1 | DB32: 1
A33: CA-Modesto | B33: 830 | C33: 1076 | D33: 1076 | E33: Tuolumne | F33: Elicia Solis | G33: 2530 COUNTRYSIDE DR | H33: TURLOCK | I33: CA | J33: 95380 | K33: (350) 203-2119 | L33: $9.99 all plans 1 mo. | M33: D01 | R33: 2 | AZ33: 1500 | BS33: 10 | CJ33: 2 | CQ33: 10 | CX33: 1 | DB33: 1
A34: CA-San Joaquin Valley | B34: 830 | C34: 1039 | D34: 1039 | E34: Mooney Blvd | F34: Maurice Lacy | G34: 1920 S MOONEY BLVD | H34: VISALIA | I34: CA | J34: 93277 | K34: (559) 372-0454 | L34: All Plans PoR 1 mo. | M34: 10F-101 | N34: 2 | AN34: 1500 | BG34: 10 | CM34: 2 | CS34: 10 | DA34: 1 | DB34: 1
A35: CA-San Joaquin Valley | B35: 830 | C35: 1072 | D35: 1072 | E35: Reedley | F35: Francisco Villatoro | G35: 1595 W MANNING AVE | H35: REEDLEY | I35: CA | J35: 93654 | K35: (559) 554-1641 | L35: All Plans PoR 1 mo. | M35: 10F-101 | N35: 2 | AN35: 1500 | BG35: 10 | CM35: 2 | CS35: 10 | DA35: 1 | DB35: 1
A36: CA-Victor Valley | B36: 830 | C36: 1019 | D36: 1019 | E36: Happy Trails Hwy | F36: Salvador Ramirez | G36: 20440 OUTER HWY 18 | H36: APPLE VALLEY | I36: CA | J36: 92307 | K36: (760) 503-0311 | L36: $9.99 all plans 1 mo. | M36: D01 | R36: 1 | AZ36: 1500 | BS36: 10 | CJ36: 2 | CQ36: 10 | CX36: 1 | DB36: 1
A37: CA-Victor Valley | B37: 830 | C37: 1031 | D37: 1031 | E37: Jellico Ave | F37: Kenyon Mcwhorter | G37: 17112 MAIN STREET | H37: HESPERIA | I37: CA | J37: 92345 | K37: (442) 267-6146 | L37: $9.99 all plans 1 mo. | M37: D01 | R37: 2 | AZ37: 1500 | BS37: 10 | CJ37: 2 | CQ37: 10 | CX37: 1 | DB37: 1
A38: CA-Victor Valley | B38: 830 | C38: 1064 | D38: 1064 | E38: Bear Valley | F38: Natalie Craven | G38: 19389 BEAR VALLEY RD | H38: APPLE VALLEY | I38: CA | J38: 92308 | K38: (442) 855-7229 | L38: $9.99 all plans 1 mo. | M38: D01 | R38: 1 | AZ38: 1500 | BS38: 10 | CJ38: 2 | CQ38: 10 | CX38: 1 | DB38: 1
A39: CO-Colorado Springs/Pueblo/Denver | B39: 810 | C39: 0341 | D39: 341 | E39: Prospect Ave | F39: Davante Jordan | G39: 24273 E PROSPECT AVE | H39: AURORA | I39: CO | J39: 80016 | K39: (303) 928-7520 | L39: $15 off all plans 1 mo. | M39: B06 | AW39: 1500 | BP39: 10 | CA39: 1 | CH39: 2 | CO39: 10 | CU39: 1 | DB39: 1
A40: CO-Colorado Springs/Pueblo/Denver | B40: 810 | C40: 0343 | D40: 343 | E40: Woodmen | F40: Marvin Willis | G40: 5366 NEW CAR DR | H40: COLORADO SPRINGS | I40: CO | J40: 80923-8854 | K40: (719) 266-0169 | L40: $15 off all plans 1 mo. | M40: B05 | Q40: 2 | AV40: 1500 | BO40: 10 | CH40: 2 | CO40: 10 | CU40: 1 | DB40: 1
A41: CO-Colorado Springs/Pueblo/Denver | B41: 810 | C41: 0344 | D41: 344 | E41: Bradley | F41: Michael Dye | G41: 1822 MAIN ST | H41: COLORADO SPRINGS | I41: CO | J41: 80911-1152 | K41: (719) 392-2250 | L41: $15 off all plans 1 mo. | M41: B05 | Q41: 1 | AV41: 1500 | BO41: 10 | CH41: 2 | CO41: 10 | CU41: 1 | DB41: 1
A42: CO-Colorado Springs/Pueblo/Denver | B42: 810 | C42: 0347 | D42: 347 | E42: Fountain | F42: Joshua Benforado | G42: 7980 FOUNTAIN MESA RD | H42: FOUNTAIN | I42: CO | J42: 80817 | K42: (719) 280-0458 | L42: $15 off all plans 1 mo. | M42: B05 | U42: 2 | AV42: 1500 | BO42: 10 | CH42: 2 | CO42: 10 | CU42: 1 | DB42: 1
A43: CO-Colorado Springs/Pueblo/Denver | B43: 810 | C43: 0348 | D43: 348 | E43: Old Ranch Rd | F43: Brandon Sirmans | G43: 3581 BLUE HORIZON VIEW | H43: COLORADO SPRINGS | I43: CO | J43: 80924 | K43: (719) 203-2707 | L43: $15 off all plans 1 mo. | M43: B05 | U43: 1 | AV43: 1500 | BO43: 10 | CH43: 2 | CO43: 10 | CU43: 1 | DB43: 1
A44: CO-Colorado Springs/Pueblo/Denver | B44: 810 | C44: 1341 | D44: 1341 | E44: Academy Blvd | F44: April Jaramillo | G44: 4275 N ACADEMY BLVD | H44: COLORADO SPRINGS | I44: CO | J44: 80918 | K44: (719) 208-4919 | L44: $15 off all plans 1 mo. | M44: B05 | Q44: 2 | AV44: 1500 | BO44: 10 | CH44: 2 | CO44: 10 | CU44: 1 | DB44: 1
A45: CO-Colorado Springs/Pueblo/Denver | B45: 810 | C45: 1343 | D45: 1343 | E45: Monument | F45: Conor Symons | G45: 980 W BAPTIST RD | H45: MONUMENT | I45: CO | J45: 80132 | K45: (719) 203-1873 | L45: $15 off all plans 1 mo. | M45: B05 | Q45: 2 | AV45: 1500 | BO45: 10 | CH45: 2 | CO45: 10 | CU45: 1 | DB45: 1
A46: CO-Colorado Springs/Pueblo/Denver | B46: 810 | C46: 1344 | D46: 1344 | E46: Runway North | F46: Andrew Sweeney | G46: 8809 E 46TH AVE | H46: DENVER | I46: CO | J46: 80238 | K46: (720) 744-0750 | L46: $15 off all plans 1 mo. | M46: B06 | U46: 2 | AW46: 1500 | BP46: 10 | CH46: 2 | CO46: 10 | CU46: 1 | DB46: 1
A47: CO-Colorado Springs/Pueblo/Denver | B47: 810 | C47: 1349 | D47: 1349 | E47: Constitution | F47: Kelly Duran | G47: 6015 CONSTITUTION AVE | H47: COLORADO SPRINGS | I47: CO | J47: 80915 | K47: (719) 301-3064 | L47: $15 off all plans 1 mo. | M47: B05 | U47: 2 | AV47: 1500 | BO47: 10 | CH47: 2 | CO47: 10 | CU47: 1 | DB47: 1
A48: FL-Cape Coral | B48: 812 | C48: 1801 | D48: 1801 | E48: Del Prado | F48: James Glass | G48: 1009 DEL PRADO BLVD S | H48: CAPE CORAL | I48: FL | J48: 33990 | K48: (239) 772-2277 | L48: All Plans PoR 1 mo. | M48: 10F-201 | AA48: 2 | AP48: 1500 | BI48: 10 | CM48: 2 | CS48: 10 | DA48: 1 | DB48: 1
A49: FL-Cape Coral | B49: 812 | C49: 1805 | D49: 1805 | E49: Santa Barbara Blvd | F49: Santiago Velasquez | G49: 2002 SANTA BARBARA BLVD | H49: CAPE CORAL | I49: FL | J49: 33991 | K49: (239) 791-1707 | L49: All Plans PoR 1 mo. | M49: 10F-201 | AA49: 2 | AP49: 1500 | BI49: 10 | CM49: 2 | CS49: 10 | DA49: 1 | DB49: 1
A50: FL-Cape Coral | B50: 812 | C50: 1807 | D50: 1807 | E50: Ne 16th Place | F50: Deserae Gannelli | G50: 318 NE 16TH PLACE | H50: CAPE CORAL | I50: FL | J50: 33909 | K50: (239) 402-3119 | L50: All Plans PoR 1 mo. | M50: 10F-201 | AA50: 2 | AP50: 1500 | BI50: 10 | CM50: 2 | CS50: 10 | DA50: 1 | DB50: 1
A51: FL-Cape Coral | B51: 832 | C51: 1811 | D51: 1811 | E51: Cody Lee | F51: Ryan Russell | G51: 8851 CODY LEE RD | H51: FORT MYERS | I51: FL | J51: 33912 | K51: (239) 234-1276 | L51: All Plans PoR 1 mo. | M51: 10F-201 | AB51: 2 | AP51: 1500 | BI51: 10 | CM51: 2 | CS51: 10 | DA51: 1 | DB51: 1
A52: FL-Cape Coral | B52: 832 | C52: 1813 | D52: 1813 | E52: Arborwood | F52: Carisa Civiello | G52: 13601 GOLDENWOOD DR | H52: FORT MYERS | I52: FL | J52: 33913 | K52: (239) 241-8294 | L52: All Plans PoR 1 mo. | M52: 10F-201 | AA52: 2 | AP52: 1500 | BI52: 10 | CM52: 2 | CS52: 10 | DA52: 1 | DB52: 1
A53: FL-Cape Coral | B53: 832 | C53: 1814 | D53: 1814 | E53: Metro Pkwy | F53: Ana Castro | G53: 2811 COLONIAL BLVD | H53: FORT MYERS | I53: FL | J53: 33966 | K53: (239) 241-8300 | L53: All Plans PoR 1 mo. | M53: 10F-201 | AA53: 2 | AP53: 1500 | BI53: 10 | CM53: 2 | CS53: 10 | DA53: 1 | DB53: 1
A54: FL-Cape Coral | B54: 832 | C54: 1816 | D54: 1816 | E54: Estero | F54: Rick Marsten | G54: 8030 TYSON EYE WAY | H54: ESTERO | I54: FL | J54: 33967 | K54: (239) 422-5745 | L54: All Plans PoR 1 mo. | M54: 10F-201 | AA54: 2 | AP54: 1500 | BI54: 10 | CM54: 2 | CS54: 10 | DA54: 1 | DB54: 1
A55: FL-Lakeland | B55: 832 | C55: 1906 | D55: 1906 | E55: Florida Ave S | F55: Christina Stivers | G55: 6051 FLORIDA AVE S | H55: LAKELAND | I55: FL | J55: 33813 | K55: (863) 213-0542 | L55: All Plans PoR 1 mo. | M55: 10F-201 | AB55: 2 | AP55: 1500 | BI55: 10 | CM55: 2 | CS55: 10 | DA55: 1 | DB55: 1
A56: FL-Orlando | B56: 812 | C56: 0233 | D56: 233 | E56: Fern Park | F56: Skylar Prescott | G56: 6501 SOUTH US HWY 17 92 | H56: CASSELBERRY | I56: FL | J56: 32730 | K56: (407) 260-0335 | L56: All Plans PoR 1 mo. | M56: 10F-101 | AA56: 1 | AB56: 0 | AN56: 1500 | BG56: 10 | CM56: 2 | CS56: 10 | DA56: 1 | DB56: 1
A57: FL-Orlando | B57: 812 | C57: 0235 | D57: 235 | E57: Colonial | F57: Holly Hutcheson | G57: 12180 E COLONIAL DR | H57: ORLANDO | I57: FL | J57: 32826 | K57: (407) 207-1294 | L57: All Plans PoR 1 mo. | M57: 10F-101 | AN57: 1500 | BG57: 10 | CF57: 1 | CM57: 2 | CS57: 10 | DA57: 1 | DB57: 1
A58: FL-Orlando | B58: 812 | C58: 0236 | D58: 236 | E58: Chickasaw | F58: Celi Cordero | G58: 7958 E COLONIAL DR | H58: ORLANDO | I58: FL | J58: 32807 | K58: (407) 203-0993 | L58: All Plans PoR 1 mo. | M58: 10F-101 | AA58: 2 | AB58: 0 | AN58: 1500 | BG58: 10 | CM58: 2 | CS58: 10 | DA58: 1 | DB58: 1
A59: FL-Orlando | B59: 812 | C59: 0243 | D59: 243 | E59: Silver Star | F59: Brendan Gilreath | G59: 4551 SILVER STAR RD | H59: ORLANDO | I59: FL | J59: 32808 | K59: (407) 553-3430 | L59: All Plans PoR 1 mo. | M59: 10F-101 | AA59: 1 | AB59: 0 | AF59: 0 | AN59: 1500 | BG59: 10 | CM59: 2 | CS59: 10 | DA59: 1 | DB59: 1
A60: FL-Orlando | B60: 812 | C60: 0279 | D60: 279 | E60: Orange Blossom | F60: Cameron Snell | G60: 5275 S ORANGE BLOSSOM TRAIL | H60: ORLANDO | I60: FL | J60: 32839 | K60: (407) 553-3429 | L60: All Plans PoR 1 mo. | M60: 10F-101 | AA60: 1 | AB60: 0 | AF60: 0 | AN60: 1500 | BG60: 10 | CM60: 2 | CS60: 10 | DA60: 1 | DB60: 1
A61: FL-Orlando | B61: 812 | C61: 1205 | D61: 1205 | E61: Commerce Ctr Dr | F61: Tathiana Rivera | G61: 4670 13TH ST | H61: SAINT CLOUD | I61: FL | J61: 34769 | K61: (407) 559-9787 | L61: All Plans PoR 1 mo. | M61: 10F-101 | AA61: 2 | AB61: 0 | AF61: 0 | AN61: 1500 | BG61: 10 | CM61: 2 | CS61: 10 | DA61: 1 | DB61: 1
A62: FL-Orlando | B62: 812 | C62: 1206 | D62: 1206 | E62: Kissimmee | F62: Luz Rodriguez | G62: 4573 W IRLO BRONSON MEMORIAL HWY | H62: KISSIMMEE | I62: FL | J62: 34746 | K62: (407) 390-1400 | L62: All Plans PoR 1 mo. | M62: 10F-101 | AA62: 2 | AB62: 0 | AF62: 0 | AN62: 1500 | BG62: 10 | CM62: 2 | CS62: 10 | DA62: 1 | DB62: 1
A63: FL-Orlando | B63: 812 | C63: 1208 | D63: 1208 | E63: Oaks Blvd | F63: Eric Cuebas | G63: 3170 S JOHN YOUNG PKWY | H63: KISSIMMEE | I63: FL | J63: 34746 | K63: (407) 329-2196 | L63: All Plans PoR 1 mo. | M63: 10F-101 | AA63: 2 | AB63: 0 | AF63: 0 | AN63: 1500 | BG63: 10 | CM63: 2 | CS63: 10 | DA63: 1 | DB63: 1
A64: FL-Orlando | B64: 812 | C64: 1215 | D64: 1215 | E64: Ormond Beach | F64: Andre Swanston | G64: 49 S YONGE ST | H64: ORMOND BEACH | I64: FL | J64: 32174 | K64: (386) 356-5113 | L64: All Plans PoR 1 mo. | M64: 10F-101 | AA64: 1 | AB64: 0 | AF64: 0 | AN64: 1500 | BG64: 10 | CM64: 2 | CS64: 10 | DA64: 1 | DB64: 1
A65: FL-Orlando | B65: 832 | C65: 1236 | D65: 1236 | E65: Poinciana | F65: Dakota Polk | G65: 530 CYPRESS PKWY | H65: POINCIANA | I65: FL | J65: 34759 | K65: (321) 300-7499 | L65: All Plans PoR 1 mo. | M65: 10F-101 | AA65: 2 | AB65: 0 | AF65: 0 | AN65: 1500 | BG65: 10 | CM65: 2 | CS65: 10 | DA65: 1 | DB65: 1
A66: FL-Orlando | B66: 832 | C66: 1242 | D66: 1242 | E66: Semoran | F66: Keegan Wyatt | G66: 1405 S SEMORAN BLVD | H66: ORLANDO | I66: FL | J66: 32807 | K66: (321) 300-3207 | L66: All Plans PoR 1 mo. | M66: 10F-101 | AA66: 2 | AB66: 0 | AF66: 0 | AN66: 1500 | BG66: 10 | CM66: 2 | CS66: 10 | DA66: 1 | DB66: 1
A67: FL-Orlando | B67: 832 | C67: 1245 | D67: 1245 | E67: Clyde Morris Blvd | F67: Robert Roundtree | G67: 3807 CLYDE MORRIS BLVD | H67: PORT ORANGE | I67: FL | J67: 32129 | K67: (386) 309-2621 | L67: All Plans PoR 1 mo. | M67: 10F-101 | N67: 2 | AA67: 0 | AB67: 0 | AF67: 0 | AN67: 1500 | BG67: 10 | CM67: 2 | CS67: 10 | DA67: 1 | DB67: 1
A68: FL-Orlando | B68: 812 | C68: 1249 | D68: 1249 | E68: Irwin | F68: Angel Mora | G68: 1164 W NEW HAVEN AVE | H68: MELBOURNE | I68: FL | J68: 32904 | K68: (321) 265-4007 | L68: All Plans PoR 1 mo. | M68: 10F-101 | N68: 2 | AA68: 0 | AB68: 0 | AF68: 0 | AN68: 1500 | BG68: 10 | CM68: 2 | CS68: 10 | DA68: 1 | DB68: 1
A69: FL-Orlando | B69: 812 | C69: 1254 | D69: 1254 | E69: Millenia | F69: David Gaus | G69: 4588 POWER CENTER LN | H69: ORLANDO | I69: FL | J69: 32839 | K69: (407) 848-1320 | L69: All Plans PoR 1 mo. | M69: 10F-101 | AA69: 2 | AB69: 0 | AF69: 0 | AN69: 1500 | BG69: 10 | CM69: 2 | CS69: 10 | DA69: 1 | DB69: 1
A70: FL-Orlando | B70: 812 | C70: 1856 | D70: 1856 | E70: Belvedere | F70: Kevin Mckinnon | G70: 2505 PARR DR | H70: THE VILLAGES | I70: FL | J70: 32162 | K70: (352) 775-1805 | L70: All Plans PoR 1 mo. | M70: 10F-101 | AA70: 2 | AB70: 0 | AF70: 0 | AN70: 1500 | BG70: 10 | CM70: 2 | CS70: 10 | DA70: 1 | DB70: 1
A71: FL-Southeast Florida | B71: 832 | C71: 1854 | D71: 1854 | E71: Hypoluxo | F71: Karlee Feldner | G71: 1833 HYPOLUXO RD | H71: LANTANA | I71: FL | J71: 33462 | K71: (561) 407-0035 | L71: All Plans PoR 1 mo. | M71: 10F-201 | AA71: 1 | AB71: 0 | AF71: 0 | AP71: 1500 | BI71: 10 | CM71: 2 | CS71: 10 | DA71: 1 | DB71: 1
A72: FL-Southeast Florida | B72: 812 | C72: 1855 | D72: 1855 | E72: Goldenrod | F72: Dylan Sanchez | G72: 3775 NW FEDERAL HWY | H72: JENSEN BEACH | I72: FL | J72: 34957 | K72: (772) 208-3966 | L72: All Plans PoR 1 mo. | M72: 10F-201 | N72: 2 | AA72: 0 | AB72: 0 | AF72: 0 | AP72: 1500 | BI72: 10 | CM72: 2 | CS72: 10 | DA72: 1 | DB72: 1
A73: FL-Tampa | B73: 812 | C73: 0226 | D73: 226 | E73: North Dale Mabry | F73: Dennis Crumlich | G73: 8101 NORTH DALE MABRY | H73: TAMPA | I73: FL | J73: 33614 | K73: (813) 933-6661 | L73: All Plans PoR 1 mo. | M73: 10F-201 | N73: 0 | AA73: 0 | AB73: 0 | AK73: 1 | AP73: 1500 | BI73: 10 | CM73: 2 | CS73: 10 | DA73: 1 | DB73: 1
A74: FL-Tampa | B74: 812 | C74: 0273 | D74: 273 | E74: Hudson | F74: Skiler Woods | G74: 12611 US HIGHWAY 19 | H74: HUDSON | I74: FL | J74: 34667-1955 | K74: (727) 868-7130 | L74: All Plans PoR 1 mo. | M74: 10F-201 | N74: 0 | AA74: 0 | AB74: 0 | AK74: 0 | AP74: 1500 | BI74: 10 | CF74: 1 | CM74: 2 | CS74: 10 | DA74: 1 | DB74: 1
A75: FL-Tampa | B75: 812 | C75: 0274 | D75: 274 | E75: Spring Hill | F75: Taylin McCormick | G75: 4330 COMMERCIAL WAY | H75: SPRING HILL | I75: FL | J75: 34606 | K75: (352) 597-5573 | L75: All Plans PoR 1 mo. | M75: 10F-201 | N75: 0 | AA75: 0 | AB75: 1 | AK75: 1 | AP75: 1500 | BI75: 10 | CM75: 2 | CS75: 10 | DA75: 1 | DB75: 1
A76: FL-Tampa | B76: 812 | C76: 1221 | D76: 1221 | E76: State Route 52 | F76: Taylor Masters | G76: 9215 STATE ROUTE 52 | H76: HUDSON | I76: FL | J76: 34669 | K76: (727) 214-3847 | L76: All Plans PoR 1 mo. | M76: 10F-201 | N76: 0 | AA76: 1 | AB76: 0 | AF76: 0 | AP76: 1500 | BI76: 10 | CM76: 2 | CS76: 10 | DA76: 1 | DB76: 1
A77: FL-Tampa | B77: 812 | C77: 1251 | D77: 1251 | E77: Park Ridge | F77: James Thomas | G77: 6801 PARK BLVD | H77: PINELLAS PARK | I77: FL | J77: 33781 | K77: (727) 620-5085 | L77: All Plans PoR 1 mo. | M77: 10F-201 | N77: 1 | AA77: 0 | AB77: 0 | AF77: 0 | AP77: 1500 | BI77: 10 | CM77: 2 | CS77: 10 | DA77: 1 | DB77: 1
A78: FL-Tampa | B78: 832 | C78: 1901 | D78: 1901 | E78: Hillsborough | F78: David Herster | G78: 12806 W HILLSBOROUGH AVE | H78: TAMPA | I78: FL | J78: 33635 | K78: (656) 444-0758 | L78: All Plans PoR 1 mo. | M78: 10F-201 | N78: 0 | AA78: 0 | AB78: 0 | AF78: 0 | AP78: 1500 | BI78: 10 | CF78: 1 | CM78: 2 | CS78: 10 | DA78: 1 | DB78: 1
A79: FL-Tampa | B79: 832 | C79: 1902 | D79: 1902 | E79: Wesley Chapel | F79: Evan Hinzman | G79: 29891 WESLEY CHAPEL BLVD | H79: WESLEY CHAPEL | I79: FL | J79: 33543 | K79: (656) 202-4586 | L79: All Plans PoR 1 mo. | M79: 10F-201 | N79: 0 | AA79: 2 | AB79: 0 | AF79: 0 | AP79: 1500 | BI79: 10 | CM79: 2 | CS79: 10 | DA79: 1 | DB79: 1
A80: FL-Tampa | B80: 812 | C80: 2501 | D80: 2501 | E80: Zephyrhills | F80: William Sprinkle | G80: 6353 GALL BOULEVARD | H80: ZEPHYRHILLS | I80: FL | J80: 33542 | K80: (813) 670-2213 | L80: All Plans PoR 1 mo. | M80: 10F-201 | N80: 1 | T80: 0 | AB80: 0 | AF80: 0 | AP80: 1500 | BI80: 10 | CM80: 2 | CS80: 10 | DA80: 1 | DB80: 1
A81: GA-Atlanta | B81: 813 | C81: 0264 | D81: 264 | E81: Hiram | F81: Alexis Strozier | G81: 5651 WENDY BAGWELL PKWY | H81: HIRAM | I81: GA | J81: 30141-7806 | K81: (770) 943-5967 | L81: $5, $10, $15 | M81: C01 | N81: 0 | T81: 0 | AB81: 0 | AG81: 1 | AX81: 1500 | BQ81: 10 | CI81: 2 | CP81: 10 | CV81: 1 | DB81: 1
A82: GA-Atlanta | B82: 813 | C82: 0270 | D82: 270 | E82: Peachtree | F82: Robert Feinburg | G82: 930 PEACHTREE PKWY | H82: CUMMING | I82: GA | J82: 30041-6823 | K82: (678) 771-8783 | L82: $5, $10, $15 | M82: C01 | N82: 0 | T82: 0 | AB82: 0 | AG82: 2 | AX82: 1500 | BQ82: 10 | CI82: 2 | CP82: 10 | CV82: 1 | DB82: 1
A83: IA-Cedar Rapids/Davenport | B83: 801 | C83: 1484 | D83: 1484 | E83: Kimberly Rd | F83: Elijah Miller | G83: 707 E KIMBERLY RD | H83: DAVENPORT | I83: IA | J83: 52807 | K83: (563) 265-3110 | L83: $9.99 all plans 1 mo. | M83: 8D-04 | N83: 0 | X83: 2 | AB83: 0 | AF83: 0 | AQ83: 1500 | BJ83: 10 | CJ83: 2 | CQ83: 10 | CW83: 1 | DB83: 1
A84: IA-Cedar Rapids/Davenport | B84: 801 | C84: 1723 | D84: 1723 | E84: Lakeview | F84: Sydney Rosebrough | G84: 4511 E 53RD STREET | H84: DAVENPORT | I84: IA | J84: 52807 | K84: (563) 306-2633 | L84: $9.99 all plans 1 mo. | M84: 8D-04 | N84: 0 | X84: 1 | AB84: 0 | AF84: 0 | AQ84: 1500 | BJ84: 10 | CJ84: 2 | CQ84: 10 | CW84: 1 | DB84: 1
A85: IA-Des Moines | B85: 801 | C85: 0730 | D85: 730 | E85: 14th Street | F85: Thomas Duncan | G85: 3400 SE 14TH ST | H85: DES MOINES | I85: IA | J85: 50320 | K85: (515) 974-5062 | L85: $9.99 all plans 1 mo. | M85: D01 | N85: 0 | W85: 2 | AB85: 0 | AF85: 0 | AZ85: 1500 | BS85: 10 | CJ85: 2 | CQ85: 10 | CX85: 1 | DB85: 1
A86: IA-Des Moines | B86: 801 | C86: 0731 | D86: 731 | E86: North Merle Hay | F86: Marina Song | G86: 4850 MERLE HAY RD | H86: URBANDALE | I86: IA | J86: 50322 | K86: (515) 254-2593 | L86: $9.99 all plans 1 mo. | M86: D01 | N86: 0 | W86: 2 | AB86: 0 | AF86: 0 | AZ86: 1500 | BS86: 10 | CJ86: 2 | CQ86: 10 | CX86: 1 | DB86: 1
A87: IA-Des Moines | B87: 801 | C87: 0733 | D87: 733 | E87: Grimes | F87: Neris Martinez | G87: 1901 SE 11TH ST | H87: GRIMES | I87: IA | J87: 50111 | K87: (515) 325-1712 | L87: $9.99 all plans 1 mo. | M87: D01 | N87: 0 | W87: 0 | AC87: 2 | AF87: 0 | AZ87: 1500 | BS87: 10 | CJ87: 2 | CQ87: 10 | CX87: 1 | DB87: 1
A88: IA-Des Moines | B88: 801 | C88: 0734 | D88: 734 | E88: Ankeny | F88: Bahari Afare | G88: 109 S ANKENY BLVD | H88: ANKENY | I88: IA | J88: 50023 | K88: (515) 325-0478 | L88: $9.99 all plans 1 mo. | M88: D01 | N88: 0 | W88: 2 | AB88: 0 | AF88: 0 | AZ88: 1500 | BS88: 10 | CJ88: 2 | CQ88: 10 | CX88: 1 | DB88: 1
A89: IA-Des Moines | B89: 801 | C89: 1721 | D89: 1721 | E89: 12th Ave | F89: Shoalie Niebauer | G89: 5440 E UNIVERSITY AVE | H89: PLEASANT HILL | I89: IA | J89: 50327 | K89: (515) 957-7218 | L89: $9.99 all plans 1 mo. | M89: D01 | N89: 0 | W89: 1 | AB89: 0 | AF89: 0 | AZ89: 1500 | BS89: 10 | CJ89: 2 | CQ89: 10 | CX89: 1 | DB89: 1
A90: IA-Des Moines | B90: 801 | C90: 1722 | D90: 1722 | E90: Altoona | F90: Tajanae Miller | G90: 3590 PRAIRIE FIRE NW | H90: ALTOONA | I90: IA | J90: 50009 | K90: (515) 978-8988 | L90: $9.99 all plans 1 mo. | M90: D01 | N90: 0 | W90: 2 | AB90: 0 | AF90: 0 | AZ90: 1500 | BS90: 10 | CJ90: 2 | CQ90: 10 | CX90: 1 | DB90: 1
A91: IA-Des Moines | B91: 801 | C91: 1724 | D91: 1724 | E91: Hickman | F91: Savhannah White | G91: 555 E HICKMAN RD | H91: WAUKEE | I91: IA | J91: 50263 | K91: (515) 207-6522 | L91: $9.99 all plans 1 mo. | M91: D01 | N91: 0 | W91: 2 | AB91: 0 | AF91: 0 | AZ91: 1500 | BS91: 10 | CJ91: 2 | CQ91: 10 | CX91: 1 | DB91: 1
A92: ID-Boise | B92: 800 | C92: 0501 | D92: 501 | E92: Fairview | F92: Mikel Hart | G92: 5950 FAIRVIEW AVENUE | H92: BOISE | I92: ID | J92: 83704 | K92: (208) 322-5950 | L92: $9.99 all plans 1 mo. | M92: D03 | N92: 0 | W92: 2 | AB92: 0 | AF92: 0 | BB92: 1500 | BU92: 10 | CJ92: 2 | CQ92: 10 | CX92: 1 | DB92: 1
A93: ID-Boise | B93: 800 | C93: 0506 | D93: 506 | E93: Meridian | F93: Hector Hinojosa | G93: 3296 E PINE AVE | H93: MERIDIAN | I93: ID | J93: 83642 | K93: (208) 895-8077 | L93: $9.99 all plans 1 mo. | M93: D03 | N93: 0 | W93: 1 | AB93: 0 | AF93: 0 | BB93: 1500 | BU93: 10 | CJ93: 2 | CQ93: 10 | CX93: 1 | DB93: 1
A94: ID-Boise | B94: 800 | C94: 1509 | D94: 1509 | E94: Milano | F94: Ashley Marten | G94: 4891 N CORTONA WAY | H94: MERIDIAN | I94: ID | J94: 83646 | K94: (208) 202-5469 | L94: $9.99 all plans 1 mo. | M94: D03 | N94: 0 | W94: 2 | AB94: 0 | AF94: 0 | BB94: 1500 | BU94: 10 | CJ94: 2 | CQ94: 10 | CX94: 1 | DB94: 1
A95: ID-Boise | B95: 800 | C95: 1510 | D95: 1510 | E95: Progress Ave | F95: Shane Ford | G95: 675 S PROGRESS AVE | H95: MERIDIAN | I95: ID | J95: 83642 | K95: (208) 297-3240 | L95: $9.99 all plans 1 mo. | M95: D03 | R95: 1 | T95: 0 | AB95: 0 | AF95: 0 | BB95: 1500 | BU95: 10 | CJ95: 2 | CQ95: 10 | CX95: 1 | DB95: 1
A96: MD-Baltimore | B96: 801 | C96: 0652 | D96: 652 | E96: Severna | F96: Joseph Green | G96: 8562 VETERANS HIGHWAY | H96: MILLERSVILLE | I96: MD | J96: 21108 | K96: (410) 729-9274 | L96: 50% off all plan 1 mo. | M96: E07 | N96: 0 | Y96: 2 | AB96: 0 | AF96: 0 | BF96: 1500 | BY96: 10 | CK96: 2 | CR96: 10 | CX96: 1 | DB96: 1
A97: MI-Detroit | B97: 801 | C97: 1474 | D97: 1474 | E97: Ford Rd | F97: Kaitlin Cole | G97: 2104 HAGGERTY ROAD N | H97: CANTON | I97: MI | J97: 48187 | K97: (734) 238-3088 | L97: All Plans PoR 1 mo. | M97: 10F-104 | N97: 2 | T97: 0 | AB97: 0 | AF97: 0 | AO97: 1500 | BH97: 10 | CM97: 2 | CS97: 10 | DA97: 1 | DB97: 1
A98: MI-Detroit | B98: 810 | C98: 1495 | D98: 1495 | E98: Latson | F98: Travis Adle | G98: 1015 S LATSON RD | H98: HOWELL | I98: MI | J98: 48843 | K98: (517) 225-6675 | L98: All Plans PoR 1 mo. | M98: 10F-101 | N98: 1 | AN98: 1500 | BG98: 10 | CM98: 2 | CS98: 10 | DA98: 1 | DB98: 1
A99: MI-Detroit | B99: 810 | C99: 2537 | D99: 2537 | E99: New Baltimore | F99: Chris Gallup | G99: 29300 23 MILE RD | H99: NEW BALTIMORE | I99: MI | J99: 48047 | K99: (586) 210-6765 | L99: All Plans PoR 1 mo. | M99: 10F-104 | N99: 1 | T99: 0 | AB99: 0 | AF99: 0 | AO99: 1500 | BH99: 10 | CM99: 2 | CS99: 10 | DA99: 1 | DB99: 1
A100: MI-Detroit | B100: 810 | C100: 2538 | D100: 2538 | E100: Clarkston | F100: Sara Kangas | G100: 6440 DIXIE HWY | H100: CLARKSTON | I100: MI | J100: 48346 | K100: (248) 605-0440 | L100: All Plans PoR 1 mo. | M100: 10F-104 | N100: 1 | T100: 0 | AB100: 0 | AF100: 0 | AO100: 1500 | BH100: 10 | CM100: 2 | CS100: 10 | DA100: 1 | DB100: 1
A101: MI-Detroit | B101: 810 | C101: 2554 | D101: 2554 | E101: Waterford | F101: Nicholas Roy | G101: 4187 HIGHLAND RD | H101: WATERFORD TWP | I101: MI | J101: 48328 | K101: (248) 599-1820 | L101: All Plans PoR 1 mo. | M101: 10F-104 | N101: 1 | AO101: 1500 | BH101: 10 | CM101: 2 | CS101: 10 | DA101: 1 | DB101: 1
...

Sheet As Values Modified
N1: 1 | O1: 1 | P1: 1 | Q1: 1 | R1: 1 | S1: 1 | T1: 1 | U1: 1 | V1: 1 | W1: 1 | X1: 1 | Y1: 1 | Z1: 1 | AA1: 1 | AB1: 1 | AC1: 1 | AD1: 1 | AE1: 1 | AF1: 1 | AG1: 1 | AH1: 1 | AI1: 1 | AJ1: 1 | AK1: 1 | AL1: 1 | AM1: 1 | AN1: 2 | AO1: 2 | AP1: 2 | AQ1: 2 | AR1: 2 | AS1: 2 | AT1: 2 | AU1: 2 | AV1: 2 | AW1: 2 | AX1: 2 | AY1: 2 | AZ1: 2 | BA1: 2 | BB1: 2 | BC1: 2 | BD1: 2 | BE1: 2 | BF1: 2 | BG1: 2 | BH1: 2 | BI1: 2 | BJ1: 2 | BK1: 2 | BL1: 2 | BM1: 2 | BN1: 2 | BO1: 2 | BP1: 2 | BQ1: 2 | BR1: 2 | BS1: 2 | BT1: 2 | BU1: 2 | BV1: 2 | BW1: 2 | BX1: 2 | BY1: 2 | BZ1: 3 | CA1: 3 | CB1: 3 | CC1: 3 | CD1: 3 | CE1: 3 | CF1: 3 | CG1: 1 | CH1: 1 | CI1: 1 | CJ1: 1 | CK1: 1 | CL1: 1 | CM1: 1 | CN1: 2 | CO1: 2 | CP1: 2 | CQ1: 2 | CR1: 2 | CS1: 2 | CT1: 2 | CU1: 2 | CV1: 2 | CW1: 2 | CX1: 2 | CY1: 2 | CZ1: 2 | DA1: 2
N2: Mister Kiosk Stickers (KSS) | T2: Gen 2 Peg KSS | AB2: Gen 1 Peg KSS | AE2: DRB KSS | AN2: Awareness Flyers | BG2: Handheld Menus | BZ2: 28x44 Windscreens | CG2: Roadside Banners | CN2: Scancards | CP2: V | CQ2: V | CT2: Collateral Guide | DB2: Box Sticker
A3: NEW BUILD BLITZ WAVE 4 August 2026 | E3: Last updated | F3: 46244 | M3: Filename | N3: NB Blitz 4-UWC-KSS-Mister-V4-10F-101-Print.pdf | O3: NB Blitz 4-UWC-KSS-Mister-V4-8F-304-Print.pdf | P3: NB Blitz 4-UWC-KSS-Mister-V4-A-01-Print.pdf | Q3: NB Blitz 4-UWC-KSS-Mister-V4-B-06-Print.pdf | R3: NB Blitz 4-UWC-KSS-Mister-V4-D-01-Print.pdf | S3: NB Blitz 4-UWC-KSS-Mister-V4-E-01-Print.pdf | T3: 2026 09 Promo-NB Blitz 4-UWC-KSS-Peg2-A-01-Print.pdf | U3: 2026 09 Promo-NB Blitz 4-UWC-KSS-Peg2-B-01-Print.pdf | V3: 2026 09 Promo-NB Blitz 4-UWC-KSS-Peg2-C-01-Print.pdf | W3: 2026 09 Promo-NB Blitz 4-UWC-KSS-Peg2-D-01-Print.pdf | X3: 2026 09 Promo-NB Blitz 4-UWC-KSS-Peg2 8D-04-Print.pdf | Y3: 2026 09 Promo-NB Blitz 4-UWC-KSS-Peg2-E-01-Print.pdf | Z3: 2026 09 Promo-NB Blitz 4-UWC-KSS-Peg2-8F-304-Print.pdf | AA3: 2026 09 Promo-NB Blitz 4-UWC-KSS-Peg2-10F-101-Print.pdf | AB3: 2026 09 Promo-NB Blitz 4-UWC-KSS-Peg1 10F-201-Print.pdf | AC3: 2026 09 Promo-NB Blitz 4-UWC-KSS-Peg1-D-01-Print.pdf | AD3: 2026 09 Promo-NB Blitz 4-UWC-KSS-Peg1-B-01-Print.pdf | AE3: 2026 09 Promo-NB Blitz 4-UWC-KSS-DRB XPT 2012-A-01-Print.pdf | AF3: 2026 09 Promo-NB Blitz 4-UWC-KSS-DRB XPT 2012-B-01-Print.pdf | AG3: 2026 09 Promo-NB Blitz 4-UWC-KSS-DRB XPT 2012-C-01-Print.pdf | AH3: 2026 09 Promo-NB Blitz 4-UWC-KSS-DRB XPT 2012-D-01-Print.pdf | AI3: 2026 09 Promo-NB Blitz 4-UWC-KSS-DRB XPT 2012 8D-05-Print.pdf | AJ3: 2026 09 Promo-NB Blitz 4-UWC-KSS-DRB XPT 2012-E-01-Print.pdf | AK3: 2026 09 Promo-NB Blitz 4-UWC-KSS-DRB XPT 2012-8F-304-Print.pdf | AL3: 2026 09 Promo-NB Blitz 4-UWC-KSS-DRB XPT 2012-10F-101-Print.pdf | AM3: 2026 09 Promo-NB Blitz 4-UWC-KSS-DRB XPT 2012-E-01-Print.pdf | AN3: 2026 09 Promo-NB Blitz 4-POR-1mo-UWC-Awareness-10-10F-101-Print.pdf | AO3: 2026 09 Promo-NB Blitz 4-POR-1mo-UWC-Awareness-10-10F-104-Print.pdf | AP3: 2026 09 Promo-NB Blitz 4-POR-1mo-UWC-Awareness-10-10F-201-Print.pdf | AQ3: 2026 09 Promo-NB Blitz 4-999-1mo-UWC-Awareness-8D-04-Print.pdf | AR3: 2026 09 Promo-NB Blitz 4-999-1mo-UWC-Awareness-8D-05-Print.pdf | AS3: 2026 09 Promo-NB Blitz 4-POR-1mo-UWC-Awareness-8-8F-304-Print.pdf | AT3: 2026 09 Promo-NB Blitz 4-10-3mos-UWC-Awareness-A-01-Print.pdf | AU3: 2026 09 Promo-NB Blitz 4-15 off-1mo-UWC-Awareness-B-01-Print.pdf | AV3: 2026 09 Promo-NB Blitz 4-15 off-1mo-UWC-Awareness-B-05-Print.pdf | AW3: 2026 09 Promo-NB Blitz 4-15 off-1mo-UWC-Awareness-B-06-Print.pdf | AX3: 2026 09 Promo-NB Blitz 4-5 10 15-1mo-UWC-Awareness-V2-C-01-Print.pdf | AY3: 2026 09 Promo-NB Blitz 4-5 10 15-1mo-UWC-Awareness-V2-C-04-Print.pdf | AZ3: 2026 09 Promo-NB Blitz 4-999-1mo-UWC-Awareness-D-01-Print.pdf | BA3: 2026 09 Promo-NB Blitz 4-999-1mo-UWC-Awareness-D-02-Print.pdf | BB3: 2026 09 Promo-NB Blitz 4-999-1mo-UWC-Awareness-D-03-Print.pdf | BC3: 2026 09 Promo-NB Blitz 4-999-1mo-UWC-Awareness-D-06-Print.pdf | BD3: 2026 09 Promo-NB Blitz 4-50 off-1mo-UWC-Awareness-E-01-Print.pdf | BE3: 2026 09 Promo-NB Blitz 4-50 off-1mo-UWC-Awareness-E-03-Print.pdf | BF3: 2026 09 Promo-NB Blitz 4-50 off-1mo-UWC-Awareness-E-07-Print.pdf | BG3: 2026 09 Promo-NB Blitz 4-POR-1mo-HandheldMenu-10-10F-101-Print.pdf | BH3: 2026 09 Promo-NB Blitz 4-POR-1mo-HandheldMenu-10-10F-104-Print.pdf | BI3: 2026 09 Promo-NB Blitz 4-POR-1mo-HandheldMenu-10-10F-201-Print.pdf | BJ3: 2026 09 Promo-NB Blitz 4-999-1mo-HandheldMenu-8D-04-Print.pdf | BK3: 2026 09 Promo-NB Blitz 4-999-1mo-HandheldMenu-8D-05-Print.pdf | BL3: 2026 09 Promo-NB Blitz 4-POR-1mo-HandheldMenu-8-8F-304-Print.pdf | BM3: 2026 09 Promo-NB Blitz 4-10-3mos-HandheldMenu-A-01-Print.pdf | BN3: 2026 09 Promo-NB Blitz 4-15 off-1mo-HandheldMenu-B-01-Print.pdf | BO3: 2026 09 Promo-NB Blitz 4-15 off-1mo-HandheldMenu-B-05-Print.pdf | BP3: 2026 09 Promo-NB Blitz 4-15 off-1mo-HandheldMenu-B-06-Print.pdf | BQ3: 2026 09 Promo-NB Blitz 4-5 10 15-1mo-HandheldMenu-V2-C-01-Print.pdf | BR3: 2026 09 Promo-NB Blitz 4-5 10 15-1mo-HandheldMenu-V2-C-04-Print.pdf | BS3: 2026 09 Promo-NB Blitz 4-999-1mo-HandheldMenu-D-01-Print.pdf | BT3: 2026 09 Promo-NB Blitz 4-999-1mo-HandheldMenu-D-02-Print.pdf | BU3: 2026 09 Promo-NB Blitz 4-999-1mo-HandheldMenu-D-03-Print.pdf | BV3: 2026 09 Promo-NB Blitz 4-999-1mo-HandheldMenu-D-06-Print.pdf | BW3: 2026 09 Promo-NB Blitz 4-50 off-1mo-HandheldMenu-E-01-Print.pdf | BX3: 2026 09 Promo-NB Blitz 4-50 off-1mo-HandheldMenu-E-03-Print.pdf | BY3: 2026 09 Promo-NB Blitz 4-50 off-1mo-HandheldMenu-E-07-Print.pdf | BZ3: 2026 09 Promo-NB Blitz 4-UWC-WS-28x44-A-Print.pdf | CA3: 2026 09 Promo-NB Blitz 4-UWC-WS-28x44-B-Print.pdf | CB3: 2026 09 Promo-NB Blitz 4-UWC-WS-28x44-D-Print.pdf | CC3: 2026 09 Promo-NB Blitz 4-UWC-WS-28x44-8D-Print.pdf | CD3: 2026 09 Promo-NB Blitz 4-UWC-WS-28x44-E-Print.pdf | CE3: 2026 09 Promo-NB Blitz 4-UWC-WS-28x44-8F-Print.pdf | CF3: 2026 09 Promo-NB Blitz 4-UWC-WS-28x44-10F-Print.pdf | CG3: 2026 09 Promo-UWC-96x36 Banner-V4-A-Print.pdf | CH3: 2026 09 Promo-UWC-96x36 Banner-V4-B-Print.pdf | CI3: 2026 09 Promo-UWC-96x36 Banner-V4-C-Print.pdf | CJ3: 2026 09 Promo-UWC-96x36 Banner-V4-D-Print.pdf | CK3: 2026 09 Promo-UWC-96x36 Banner-V4-E-Print.pdf | CL3: 2026 09 Promo-UWC-96x36 Banner-V4-8F-Print.pdf | CM3: 2026 09 Promo-UWC-96x36 Banner-V4-10F-Print.pdf | CN3: 2026 09 Promo 10off 3mos Scan Cards-V2-Print | CO3: 2026 09 Promo-15 Off-1mo-ScanCard-Print | CP3: 2026 09 Promo-5-10-15-1mo-ScanCardSet-Print | CQ3: 2026 09 Promo-999-1mo-ScanCardSet-Print.pdf | CR3: 2026 09 Promo-50off-1mo-ScanCard-Print.pdf | CS3: 2026 09 All Plans PoR 1mo Scan Cards-V2-Print.pdf | CT3: 2026 09 Promo-NB Blitz 4-Collateral Guides-A-Print.pdf | CU3: 2026 09 Promo-NB Blitz 4-Collateral Guides-B-Print.pdf | CV3: 2026 09 Promo-NB Blitz 4-Collateral Guides-C-Print.pdf | CW3: 2026 09 Promo-NB Blitz 4-Collateral Guides-8D-Print.pdf | CX3: 2026 09 Promo-NB Blitz 4-Collateral Guides-D-Print.pdf | CY3: 2026 09 Promo-NB Blitz 4-Collateral Guides-E-Print.pdf | CZ3: 2026 09 Promo-NB Blitz 4-Collateral Guides-8F-Print.pdf | DA3: 2026 09 Promo-NB Blitz 4-Collateral Guides-10F-Print.pdf | DB3: Box Sticker
A4: Region | B4: CC | C4: Store # | D4: Vlookup Store # | E4: Location Name | F4: General Manager | G4: Address | H4: City | I4: State | J4: Zip Code | K4: Phone Number | L4: Promo | M4: Art Code | N4: 10F | O4: 8F | P4: A | Q4: B | R4: D | S4: E | T4: A | U4: B | V4: C | W4: D | X4: 8D | Y4: E | Z4: 8F | AA4: 10F | AB4: 10F | AC4: D | AD4: B | AE4: A | AF4: B | AG4: C | AH4: D | AI4: 8D | AJ4: E | AK4: 8F | AL4: 10F | AM4: E | AN4: 10F-101 | AO4: 10F-104 | AP4: 10F-201 | AQ4: 8D-04 | AR4: 8D-05 | AS4: 8F-304 | AT4: A01 | AU4: B01 | AV4: B05 | AW4: B06 | AX4: C01 | AY4: C04 | AZ4: D01 | BA4: D02 | BB4: D03 | BC4: D06 | BD4: E01 | BE4: E03 | BF4: E07 | BG4: 10F-101 | BH4: 10F-104 | BI4: 10F-201 | BJ4: 8D-04 | BK4: 8D-05 | BL4: 8F-304 | BM4: A01 | BN4: B01 | BO4: B05 | BP4: B06 | BQ4: C01 | BR4: C04 | BS4: D01 | BT4: D02 | BU4: D03 | BV4: D06 | BW4: E01 | BX4: E03 | BY4: E07 | BZ4: A | CA4: B | CB4: D | CC4: 8D | CD4: E | CE4: 8F | CF4: 10F | CG4: A | CH4: B | CI4: C | CJ4: D | CK4: E | CL4: 8F | CM4: 10F | CN4: A5 | CO4: B7 | CP4: C8 | CQ4: D9 | CR4: E12 | CS4: F | CT4: A | CU4: B | CV4: C | CW4: 8D | CX4: D | CY4: E | CZ4: 8F | DA4: 10F
A5: AL-Huntsville | B5: 813 | C5: 0041 | D5: 41 | E5: Hartselle | F5: MaryGrace Gilley | G5: 1206 HIGHWAY 31 NW | H5: HARTSELLE | I5: AL | J5: 35640-4421 | K5: (256) 773-7737 | L5: 50% off all plan 1 mo. | M5: E01 | AJ5: 1 | BD5: 1500 | BW5: 10 | CK5: 2 | CR5: 10 | CX5: 1 | DB5: 1
A6: AL-Huntsville | B6: 813 | C6: 0042 | D6: 42 | E6: Limestone | F6: Jamie Garrie | G6: 1321 US HIGHWAY 72 E | H6: ATHENS | I6: AL | J6: 35611-4405 | K6: (256) 233-2290 | L6: 50% off all plan 1 mo. | M6: E01 | AJ6: 1 | BD6: 1500 | BW6: 10 | CK6: 2 | CR6: 10 | CX6: 1 | DB6: 1
A7: AL-Huntsville | B7: 813 | C7: 0043 | D7: 43 | E7: Madison | F7: Klaryssa Melendrez | G7: 5509 PROMENADE POINT PKWY | H7: MADISON | I7: AL | J7: 35758-6701 | K7: (256) 895-2693 | L7: 50% off all plan 1 mo. | M7: E01 | AJ7: 1 | BD7: 1500 | BW7: 10 | CK7: 2 | CR7: 10 | CX7: 1 | DB7: 1
A8: AL-Huntsville | B8: 813 | C8: 0044 | D8: 44 | E8: Setter | F8: Stevie Wagner | G8: 627 BELTLINE RD SW | H8: DECATUR | I8: AL | J8: 35601 | K8: (256) 867-0108 | L8: 50% off all plan 1 mo. | M8: E01 | AJ8: 1 | BD8: 1500 | BW8: 10 | CK8: 2 | CR8: 10 | CX8: 1 | DB8: 1
A9: AL-Huntsville | B9: 813 | C9: 0045 | D9: 45 | E9: 9th Street | F9: Christian Rider | G9: 2240 BELTLINE RD SW | H9: DECATUR | I9: AL | J9: 35601-7001 | K9: (256) 822-2939 | L9: 50% off all plan 1 mo. | M9: E01 | AJ9: 1 | BD9: 1500 | BW9: 10 | CK9: 2 | CR9: 10 | CX9: 1 | DB9: 1
A10: AL-Huntsville | B10: 813 | C10: 0046 | D10: 46 | E10: Bassett Ave | F10: Josh Lamey | G10: 721 14TH ST SE | H10: DECATUR | I10: AL | J10: 35601-5911 | K10: (256) 822-2029 | L10: 50% off all plan 1 mo. | M10: E01 | AJ10: 1 | BD10: 1500 | BW10: 10 | CK10: 2 | CR10: 10 | CX10: 1 | DB10: 1
A11: AL-Huntsville | B11: 813 | C11: 0047 | D11: 47 | E11: Grace | F11: Justin Williams | G11: 403 US HIGHWAY 72 W | H11: ATHENS | I11: AL | J11: 35611-4207 | K11: (256) 998-5312 | L11: 50% off all plan 1 mo. | M11: E01 | AJ11: 1 | BD11: 1500 | BW11: 10 | CK11: 2 | CR11: 10 | CX11: 1 | DB11: 1
A12: AL-Huntsville | B12: 813 | C12: 0051 | D12: 51 | E12: Azalea | F12: Colby Gray | G12: 271 AZALEA DR | H12: FLORENCE | I12: AL | J12: 35630-1733 | K12: (256) 766-2726 | L12: 50% off all plan 1 mo. | M12: E01 | AJ12: 1 | BD12: 1500 | BW12: 10 | CK12: 2 | CR12: 10 | CX12: 1 | DB12: 1
A13: AL-Huntsville | B13: 813 | C13: 0052 | D13: 52 | E13: Muscle Shoals | F13: Olivia Thomsen | G13: 702 AVALON AVE | H13: MUSCLE SHOALS | I13: AL | J13: 35661-2304 | K13: (256) 389-3890 | L13: 50% off all plan 1 mo. | M13: E01 | BD13: 1500 | BW13: 10 | CD13: 1 | CK13: 2 | CR13: 10 | CX13: 1 | DB13: 1
A14: AL-Huntsville | B14: 813 | C14: 0053 | D14: 53 | E14: Cloverdale | F14: Katherine Huddleston | G14: 2914 CLOVERDALE RD | H14: FLORENCE | I14: AL | J14: 35633 | K14: (256) 712-0183 | L14: 50% off all plan 1 mo. | M14: E01 | AJ14: 1 | BD14: 1500 | BW14: 10 | CK14: 2 | CR14: 10 | CX14: 1 | DB14: 1
A15: AZ-Tucson | B15: 806 | C15: 0326 | D15: 326 | E15: Swan | F15: Sierrah Bainter | G15: 4600 E BROADWAY BLVD | H15: TUCSON | I15: AZ | J15: 85711-3512 | K15: (520) 428-0256 | L15: $9.99 all plans 1 mo. | M15: D01 | AZ15: 1500 | BS15: 10 | CB15: 1 | CJ15: 2 | CQ15: 10 | CX15: 1 | DB15: 1
A16: AZ-Tucson | B16: 806 | C16: 0327 | D16: 327 | E16: South Kolb | F16: Evelyn Conger | G16: 2409 S KOLB RD | H16: TUCSON | I16: AZ | J16: 85710 | K16: (520) 721-9290 | L16: $9.99 all plans 1 mo. | M16: D01 | AZ16: 1500 | BS16: 10 | CB16: 1 | CJ16: 2 | CQ16: 10 | CX16: 1 | DB16: 1
A17: AZ-Tucson | B17: 806 | C17: 0328 | D17: 328 | E17: Euclid | F17: Stefanie Osuna | G17: 730 E BROADWAY BLVD | H17: TUCSON | I17: AZ | J17: 85719 | K17: (520) 623-2923 | L17: $9.99 all plans 1 mo. | M17: D01 | AZ17: 1500 | BS17: 10 | CB17: 1 | CJ17: 2 | CQ17: 10 | CX17: 1 | DB17: 1
A18: AZ-Tucson | B18: 806 | C18: 0335 | D18: 335 | E18: E Grant | F18: 0 | G18: 3150 E GRANT RD | H18: TUCSON | I18: AZ | J18: 85716 | K18: (520) 881-1486 | L18: $9.99 all plans 1 mo. | M18: D01 | AZ18: 1500 | BS18: 10 | CB18: 1 | CJ18: 2 | CQ18: 10 | CX18: 1 | DB18: 1
A19: AZ-Tucson | B19: 806 | C19: 1329 | D19: 1329 | E19: Craycroft | F19: Chandrani Das | G19: 5515 E GRANT RD | H19: TUCSON | I19: AZ | J19: 85712 | K19: (520) 497-1922 | L19: $9.99 all plans 1 mo. | M19: D01 | R19: 2 | AZ19: 1500 | BS19: 10 | CJ19: 2 | CQ19: 10 | CX19: 1 | DB19: 1
A20: AZ-Tucson | B20: 806 | C20: 1331 | D20: 1331 | E20: Twin Peaks | F20: Vanna Valdez | G20: 6520 W MARANA CENTER BL | H20: TUCSON | I20: AZ | J20: 85742 | K20: (520) 335-8707 | L20: $9.99 all plans 1 mo. | M20: D01 | R20: 1 | AZ20: 1500 | BS20: 10 | CJ20: 2 | CQ20: 10 | CX20: 1 | DB20: 1
A21: AZ-Tucson | B21: 806 | C21: 2552 | D21: 2552 | E21: Tucson Mall | F21: Natalie Vazquez Martinez | G21: 4646 N ORACLE | H21: TUCSON | I21: AZ | J21: 85705 | K21: (520) 485-2620 | L21: $9.99 all plans 1 mo. | M21: D01 | R21: 1 | AZ21: 1500 | BS21: 10 | CJ21: 2 | CQ21: 10 | CX21: 1 | DB21: 1
A22: AZ-Tucson | B22: 806 | C22: 2557 | D22: 2557 | E22: Cardinal | F22: Martin Soto | G22: 2850 W VALENCIA ROAD | H22: TUCSON | I22: AZ | J22: 85746 | K22: (520) 497-1992 | L22: $9.99 all plans 1 mo. | M22: D01 | R22: 1 | AZ22: 1500 | BS22: 10 | CJ22: 2 | CQ22: 10 | CX22: 1 | DB22: 1
A23: CA-Bakersfield | B23: 830 | C23: 1016 | D23: 1016 | E23: Rosedale Hwy | F23: Adrian Vargas | G23: 11921 ROSEDALE HIGHWAY | H23: BAKERSFIELD | I23: CA | J23: 93312 | K23: (661) 230-5335 | L23: $9.99 all plans 1 mo. | M23: D01 | W23: 2 | AZ23: 1500 | BS23: 10 | CJ23: 2 | CQ23: 10 | CX23: 1 | DB23: 1
A24: CA-Bakersfield | B24: 830 | C24: 1034 | D24: 1034 | E24: Carmen | F24: Edgar Barron | G24: 1925 S BROADWAY | H24: SANTA MARIA | I24: CA | J24: 93454 | K24: (805) 621-6835 | L24: $9.99 all plans 1 mo. | M24: D01 | R24: 2 | AZ24: 1500 | BS24: 10 | CJ24: 2 | CQ24: 10 | CX24: 1 | DB24: 1
A25: CA-Bakersfield | B25: 830 | C25: 1035 | D25: 1035 | E25: Hosking | F25: Susana Ledina | G25: 1601 HOSKING AVE | H25: BAKERSFIELD | I25: CA | J25: 93307 | K25: (661) 336-9952 | L25: $9.99 all plans 1 mo. | M25: D01 | R25: 1 | AZ25: 1500 | BS25: 10 | CJ25: 2 | CQ25: 10 | CX25: 1 | DB25: 1
A26: CA-Bakersfield | B26: 830 | C26: 1038 | D26: 1038 | E26: Heath | F26: Hailey Divina | G26: 16214 STOCKDALE HWY | H26: BAKERSFIELD | I26: CA | J26: 93314 | K26: (661) 336-9403 | L26: $9.99 all plans 1 mo. | M26: D01 | R26: 2 | AZ26: 1500 | BS26: 10 | CJ26: 2 | CQ26: 10 | CX26: 1 | DB26: 1
A27: CA-Bakersfield | B27: 830 | C27: 1058 | D27: 1058 | E27: Stockdale | F27: Jorge Escobar | G27: 11417 STOCKDALE HWY | H27: BAKERSFIELD | I27: CA | J27: 93311 | K27: (661) 636-6520 | L27: $9.99 all plans 1 mo. | M27: D01 | R27: 2 | AZ27: 1500 | BS27: 10 | CJ27: 2 | CQ27: 10 | CX27: 1 | DB27: 1
A28: CA-Los Angeles | B28: 830 | C28: 1013 | D28: 1013 | E28: Hwy 138 | F28: Kayla Lopez | G28: 1822 E PALMDALE BLVD | H28: PALMDALE | I28: CA | J28: 93550 | K28: (661) 268-6424 | L28: $9.99 all plans 1 mo. | M28: D01 | W28: 2 | AZ28: 1500 | BS28: 10 | CJ28: 2 | CQ28: 10 | CX28: 1 | DB28: 1
A29: CA-Los Angeles | B29: 830 | C29: 1018 | D29: 1018 | E29: Rialto | F29: Olivia Rodriguez | G29: 127 WEST VALLEY BLVD | H29: RIALTO | I29: CA | J29: 92376 | K29: (909) 237-8099 | L29: $9.99 all plans 1 mo. | M29: D01 | R29: 2 | AZ29: 1500 | BS29: 10 | CJ29: 2 | CQ29: 10 | CX29: 1 | DB29: 1
A30: CA-Los Angeles | B30: 830 | C30: 1027 | D30: 1027 | E30: Stoneridge | F30: Zachary Ojeda | G30: 27240 EUCALYPTUS AVE | H30: MORENO VALLEY | I30: CA | J30: 92555 | K30: (951) 221-3009 | L30: $9.99 all plans 1 mo. | M30: D01 | R30: 2 | AZ30: 1500 | BS30: 10 | CJ30: 2 | CQ30: 10 | CX30: 1 | DB30: 1
A31: CA-Los Angeles | B31: 830 | C31: 1037 | D31: 1037 | E31: Varsity | F31: Anthony Fickewirth | G31: 4212 N VARSITY AVE | H31: SAN BERNARDINO | I31: CA | J31: 92407 | K31: (909) 277-6601 | L31: $9.99 all plans 1 mo. | M31: D01 | R31: 2 | AZ31: 1500 | BS31: 10 | CJ31: 2 | CQ31: 10 | CX31: 1 | DB31: 1
A32: CA-Modesto | B32: 831 | C32: 0915 | D32: 915 | E32: Merced | F32: Manuel Toro Garcia | G32: 1800 WEST OLIVE AVE | H32: MERCED | I32: CA | J32: 95348 | K32: (209) 388-9274 | L32: $9.99 all plans 1 mo. | M32: D01 | W32: 1 | AZ32: 1500 | BS32: 10 | CJ32: 2 | CQ32: 10 | CX32: 1 | DB32: 1
A33: CA-Modesto | B33: 830 | C33: 1076 | D33: 1076 | E33: Tuolumne | F33: Elicia Solis | G33: 2530 COUNTRYSIDE DR | H33: TURLOCK | I33: CA | J33: 95380 | K33: (350) 203-2119 | L33: $9.99 all plans 1 mo. | M33: D01 | R33: 2 | AZ33: 1500 | BS33: 10 | CJ33: 2 | CQ33: 10 | CX33: 1 | DB33: 1
A34: CA-San Joaquin Valley | B34: 830 | C34: 1039 | D34: 1039 | E34: Mooney Blvd | F34: Maurice Lacy | G34: 1920 S MOONEY BLVD | H34: VISALIA | I34: CA | J34: 93277 | K34: (559) 372-0454 | L34: All Plans PoR 1 mo. | M34: 10F-101 | N34: 2 | AN34: 1500 | BG34: 10 | CM34: 2 | CS34: 10 | DA34: 1 | DB34: 1
A35: CA-San Joaquin Valley | B35: 830 | C35: 1072 | D35: 1072 | E35: Reedley | F35: Francisco Villatoro | G35: 1595 W MANNING AVE | H35: REEDLEY | I35: CA | J35: 93654 | K35: (559) 554-1641 | L35: All Plans PoR 1 mo. | M35: 10F-101 | N35: 2 | AN35: 1500 | BG35: 10 | CM35: 2 | CS35: 10 | DA35: 1 | DB35: 1
A36: CA-Victor Valley | B36: 830 | C36: 1019 | D36: 1019 | E36: Happy Trails Hwy | F36: Salvador Ramirez | G36: 20440 OUTER HWY 18 | H36: APPLE VALLEY | I36: CA | J36: 92307 | K36: (760) 503-0311 | L36: $9.99 all plans 1 mo. | M36: D01 | R36: 1 | AZ36: 1500 | BS36: 10 | CJ36: 2 | CQ36: 10 | CX36: 1 | DB36: 1
A37: CA-Victor Valley | B37: 830 | C37: 1031 | D37: 1031 | E37: Jellico Ave | F37: Kenyon Mcwhorter | G37: 17112 MAIN STREET | H37: HESPERIA | I37: CA | J37: 92345 | K37: (442) 267-6146 | L37: $9.99 all plans 1 mo. | M37: D01 | R37: 2 | AZ37: 1500 | BS37: 10 | CJ37: 2 | CQ37: 10 | CX37: 1 | DB37: 1
A38: CA-Victor Valley | B38: 830 | C38: 1064 | D38: 1064 | E38: Bear Valley | F38: Natalie Craven | G38: 19389 BEAR VALLEY RD | H38: APPLE VALLEY | I38: CA | J38: 92308 | K38: (442) 855-7229 | L38: $9.99 all plans 1 mo. | M38: D01 | R38: 1 | AZ38: 1500 | BS38: 10 | CJ38: 2 | CQ38: 10 | CX38: 1 | DB38: 1
A39: CO-Colorado Springs/Pueblo/Denver | B39: 810 | C39: 0341 | D39: 341 | E39: Prospect Ave | F39: Davante Jordan | G39: 24273 E PROSPECT AVE | H39: AURORA | I39: CO | J39: 80016 | K39: (303) 928-7520 | L39: $15 off all plans 1 mo. | M39: B06 | AW39: 1500 | BP39: 10 | CA39: 1 | CH39: 2 | CO39: 10 | CU39: 1 | DB39: 1
A40: CO-Colorado Springs/Pueblo/Denver | B40: 810 | C40: 0343 | D40: 343 | E40: Woodmen | F40: Marvin Willis | G40: 5366 NEW CAR DR | H40: COLORADO SPRINGS | I40: CO | J40: 80923-8854 | K40: (719) 266-0169 | L40: $15 off all plans 1 mo. | M40: B05 | Q40: 2 | AV40: 1500 | BO40: 10 | CH40: 2 | CO40: 10 | CU40: 1 | DB40: 1
A41: CO-Colorado Springs/Pueblo/Denver | B41: 810 | C41: 0344 | D41: 344 | E41: Bradley | F41: Michael Dye | G41: 1822 MAIN ST | H41: COLORADO SPRINGS | I41: CO | J41: 80911-1152 | K41: (719) 392-2250 | L41: $15 off all plans 1 mo. | M41: B05 | Q41: 1 | AV41: 1500 | BO41: 10 | CH41: 2 | CO41: 10 | CU41: 1 | DB41: 1
A42: CO-Colorado Springs/Pueblo/Denver | B42: 810 | C42: 0347 | D42: 347 | E42: Fountain | F42: Joshua Benforado | G42: 7980 FOUNTAIN MESA RD | H42: FOUNTAIN | I42: CO | J42: 80817 | K42: (719) 280-0458 | L42: $15 off all plans 1 mo. | M42: B05 | U42: 2 | AV42: 1500 | BO42: 10 | CH42: 2 | CO42: 10 | CU42: 1 | DB42: 1
A43: CO-Colorado Springs/Pueblo/Denver | B43: 810 | C43: 0348 | D43: 348 | E43: Old Ranch Rd | F43: Brandon Sirmans | G43: 3581 BLUE HORIZON VIEW | H43: COLORADO SPRINGS | I43: CO | J43: 80924 | K43: (719) 203-2707 | L43: $15 off all plans 1 mo. | M43: B05 | U43: 1 | AV43: 1500 | BO43: 10 | CH43: 2 | CO43: 10 | CU43: 1 | DB43: 1
A44: CO-Colorado Springs/Pueblo/Denver | B44: 810 | C44: 1341 | D44: 1341 | E44: Academy Blvd | F44: April Jaramillo | G44: 4275 N ACADEMY BLVD | H44: COLORADO SPRINGS | I44: CO | J44: 80918 | K44: (719) 208-4919 | L44: $15 off all plans 1 mo. | M44: B05 | Q44: 2 | AV44: 1500 | BO44: 10 | CH44: 2 | CO44: 10 | CU44: 1 | DB44: 1
A45: CO-Colorado Springs/Pueblo/Denver | B45: 810 | C45: 1343 | D45: 1343 | E45: Monument | F45: Conor Symons | G45: 980 W BAPTIST RD | H45: MONUMENT | I45: CO | J45: 80132 | K45: (719) 203-1873 | L45: $15 off all plans 1 mo. | M45: B05 | Q45: 2 | AV45: 1500 | BO45: 10 | CH45: 2 | CO45: 10 | CU45: 1 | DB45: 1
A46: CO-Colorado Springs/Pueblo/Denver | B46: 810 | C46: 1344 | D46: 1344 | E46: Runway North | F46: Andrew Sweeney | G46: 8809 E 46TH AVE | H46: DENVER | I46: CO | J46: 80238 | K46: (720) 744-0750 | L46: $15 off all plans 1 mo. | M46: B06 | U46: 2 | AW46: 1500 | BP46: 10 | CH46: 2 | CO46: 10 | CU46: 1 | DB46: 1
A47: CO-Colorado Springs/Pueblo/Denver | B47: 810 | C47: 1349 | D47: 1349 | E47: Constitution | F47: Kelly Duran | G47: 6015 CONSTITUTION AVE | H47: COLORADO SPRINGS | I47: CO | J47: 80915 | K47: (719) 301-3064 | L47: $15 off all plans 1 mo. | M47: B05 | U47: 2 | AV47: 1500 | BO47: 10 | CH47: 2 | CO47: 10 | CU47: 1 | DB47: 1
A48: FL-Cape Coral | B48: 812 | C48: 1801 | D48: 1801 | E48: Del Prado | F48: James Glass | G48: 1009 DEL PRADO BLVD S | H48: CAPE CORAL | I48: FL | J48: 33990 | K48: (239) 772-2277 | L48: All Plans PoR 1 mo. | M48: 10F-201 | AA48: 2 | AP48: 1500 | BI48: 10 | CM48: 2 | CS48: 10 | DA48: 1 | DB48: 1
A49: FL-Cape Coral | B49: 812 | C49: 1805 | D49: 1805 | E49: Santa Barbara Blvd | F49: Santiago Velasquez | G49: 2002 SANTA BARBARA BLVD | H49: CAPE CORAL | I49: FL | J49: 33991 | K49: (239) 791-1707 | L49: All Plans PoR 1 mo. | M49: 10F-201 | AA49: 2 | AP49: 1500 | BI49: 10 | CM49: 2 | CS49: 10 | DA49: 1 | DB49: 1
A50: FL-Cape Coral | B50: 812 | C50: 1807 | D50: 1807 | E50: Ne 16th Place | F50: Deserae Gannelli | G50: 318 NE 16TH PLACE | H50: CAPE CORAL | I50: FL | J50: 33909 | K50: (239) 402-3119 | L50: All Plans PoR 1 mo. | M50: 10F-201 | AA50: 2 | AP50: 1500 | BI50: 10 | CM50: 2 | CS50: 10 | DA50: 1 | DB50: 1
A51: FL-Cape Coral | B51: 832 | C51: 1811 | D51: 1811 | E51: Cody Lee | F51: Ryan Russell | G51: 8851 CODY LEE RD | H51: FORT MYERS | I51: FL | J51: 33912 | K51: (239) 234-1276 | L51: All Plans PoR 1 mo. | M51: 10F-201 | AB51: 2 | AP51: 1500 | BI51: 10 | CM51: 2 | CS51: 10 | DA51: 1 | DB51: 1
A52: FL-Cape Coral | B52: 832 | C52: 1813 | D52: 1813 | E52: Arborwood | F52: Carisa Civiello | G52: 13601 GOLDENWOOD DR | H52: FORT MYERS | I52: FL | J52: 33913 | K52: (239) 241-8294 | L52: All Plans PoR 1 mo. | M52: 10F-201 | AA52: 2 | AP52: 1500 | BI52: 10 | CM52: 2 | CS52: 10 | DA52: 1 | DB52: 1
A53: FL-Cape Coral | B53: 832 | C53: 1814 | D53: 1814 | E53: Metro Pkwy | F53: Ana Castro | G53: 2811 COLONIAL BLVD | H53: FORT MYERS | I53: FL | J53: 33966 | K53: (239) 241-8300 | L53: All Plans PoR 1 mo. | M53: 10F-201 | AA53: 2 | AP53: 1500 | BI53: 10 | CM53: 2 | CS53: 10 | DA53: 1 | DB53: 1
A54: FL-Cape Coral | B54: 832 | C54: 1816 | D54: 1816 | E54: Estero | F54: Rick Marsten | G54: 8030 TYSON EYE WAY | H54: ESTERO | I54: FL | J54: 33967 | K54: (239) 422-5745 | L54: All Plans PoR 1 mo. | M54: 10F-201 | AA54: 2 | AP54: 1500 | BI54: 10 | CM54: 2 | CS54: 10 | DA54: 1 | DB54: 1
A55: FL-Lakeland | B55: 832 | C55: 1906 | D55: 1906 | E55: Florida Ave S | F55: Christina Stivers | G55: 6051 FLORIDA AVE S | H55: LAKELAND | I55: FL | J55: 33813 | K55: (863) 213-0542 | L55: All Plans PoR 1 mo. | M55: 10F-201 | AB55: 2 | AP55: 1500 | BI55: 10 | CM55: 2 | CS55: 10 | DA55: 1 | DB55: 1
A56: FL-Orlando | B56: 812 | C56: 0233 | D56: 233 | E56: Fern Park | F56: Skylar Prescott | G56: 6501 SOUTH US HWY 17 92 | H56: CASSELBERRY | I56: FL | J56: 32730 | K56: (407) 260-0335 | L56: All Plans PoR 1 mo. | M56: 10F-101 | AA56: 1 | AB56: 0 | AN56: 1500 | BG56: 10 | CM56: 2 | CS56: 10 | DA56: 1 | DB56: 1
A57: FL-Orlando | B57: 812 | C57: 0235 | D57: 235 | E57: Colonial | F57: Holly Hutcheson | G57: 12180 E COLONIAL DR | H57: ORLANDO | I57: FL | J57: 32826 | K57: (407) 207-1294 | L57: All Plans PoR 1 mo. | M57: 10F-101 | AN57: 1500 | BG57: 10 | CF57: 1 | CM57: 2 | CS57: 10 | DA57: 1 | DB57: 1
A58: FL-Orlando | B58: 812 | C58: 0236 | D58: 236 | E58: Chickasaw | F58: Celi Cordero | G58: 7958 E COLONIAL DR | H58: ORLANDO | I58: FL | J58: 32807 | K58: (407) 203-0993 | L58: All Plans PoR 1 mo. | M58: 10F-101 | AA58: 2 | AB58: 0 | AN58: 1500 | BG58: 10 | CM58: 2 | CS58: 10 | DA58: 1 | DB58: 1
A59: FL-Orlando | B59: 812 | C59: 0243 | D59: 243 | E59: Silver Star | F59: Brendan Gilreath | G59: 4551 SILVER STAR RD | H59: ORLANDO | I59: FL | J59: 32808 | K59: (407) 553-3430 | L59: All Plans PoR 1 mo. | M59: 10F-101 | AA59: 1 | AB59: 0 | AF59: 0 | AN59: 1500 | BG59: 10 | CM59: 2 | CS59: 10 | DA59: 1 | DB59: 1
A60: FL-Orlando | B60: 812 | C60: 0279 | D60: 279 | E60: Orange Blossom | F60: Cameron Snell | G60: 5275 S ORANGE BLOSSOM TRAIL | H60: ORLANDO | I60: FL | J60: 32839 | K60: (407) 553-3429 | L60: All Plans PoR 1 mo. | M60: 10F-101 | AA60: 1 | AB60: 0 | AF60: 0 | AN60: 1500 | BG60: 10 | CM60: 2 | CS60: 10 | DA60: 1 | DB60: 1
A61: FL-Orlando | B61: 812 | C61: 1205 | D61: 1205 | E61: Commerce Ctr Dr | F61: Tathiana Rivera | G61: 4670 13TH ST | H61: SAINT CLOUD | I61: FL | J61: 34769 | K61: (407) 559-9787 | L61: All Plans PoR 1 mo. | M61: 10F-101 | AA61: 2 | AB61: 0 | AF61: 0 | AN61: 1500 | BG61: 10 | CM61: 2 | CS61: 10 | DA61: 1 | DB61: 1
A62: FL-Orlando | B62: 812 | C62: 1206 | D62: 1206 | E62: Kissimmee | F62: Luz Rodriguez | G62: 4573 W IRLO BRONSON MEMORIAL HWY | H62: KISSIMMEE | I62: FL | J62: 34746 | K62: (407) 390-1400 | L62: All Plans PoR 1 mo. | M62: 10F-101 | AA62: 2 | AB62: 0 | AF62: 0 | AN62: 1500 | BG62: 10 | CM62: 2 | CS62: 10 | DA62: 1 | DB62: 1
A63: FL-Orlando | B63: 812 | C63: 1208 | D63: 1208 | E63: Oaks Blvd | F63: Eric Cuebas | G63: 3170 S JOHN YOUNG PKWY | H63: KISSIMMEE | I63: FL | J63: 34746 | K63: (407) 329-2196 | L63: All Plans PoR 1 mo. | M63: 10F-101 | AA63: 2 | AB63: 0 | AF63: 0 | AN63: 1500 | BG63: 10 | CM63: 2 | CS63: 10 | DA63: 1 | DB63: 1
A64: FL-Orlando | B64: 812 | C64: 1215 | D64: 1215 | E64: Ormond Beach | F64: Andre Swanston | G64: 49 S YONGE ST | H64: ORMOND BEACH | I64: FL | J64: 32174 | K64: (386) 356-5113 | L64: All Plans PoR 1 mo. | M64: 10F-101 | AA64: 1 | AB64: 0 | AF64: 0 | AN64: 1500 | BG64: 10 | CM64: 2 | CS64: 10 | DA64: 1 | DB64: 1
A65: FL-Orlando | B65: 832 | C65: 1236 | D65: 1236 | E65: Poinciana | F65: Dakota Polk | G65: 530 CYPRESS PKWY | H65: POINCIANA | I65: FL | J65: 34759 | K65: (321) 300-7499 | L65: All Plans PoR 1 mo. | M65: 10F-101 | AA65: 2 | AB65: 0 | AF65: 0 | AN65: 1500 | BG65: 10 | CM65: 2 | CS65: 10 | DA65: 1 | DB65: 1
A66: FL-Orlando | B66: 832 | C66: 1242 | D66: 1242 | E66: Semoran | F66: Keegan Wyatt | G66: 1405 S SEMORAN BLVD | H66: ORLANDO | I66: FL | J66: 32807 | K66: (321) 300-3207 | L66: All Plans PoR 1 mo. | M66: 10F-101 | AA66: 2 | AB66: 0 | AF66: 0 | AN66: 1500 | BG66: 10 | CM66: 2 | CS66: 10 | DA66: 1 | DB66: 1
A67: FL-Orlando | B67: 832 | C67: 1245 | D67: 1245 | E67: Clyde Morris Blvd | F67: Robert Roundtree | G67: 3807 CLYDE MORRIS BLVD | H67: PORT ORANGE | I67: FL | J67: 32129 | K67: (386) 309-2621 | L67: All Plans PoR 1 mo. | M67: 10F-101 | N67: 2 | AA67: 0 | AB67: 0 | AF67: 0 | AN67: 1500 | BG67: 10 | CM67: 2 | CS67: 10 | DA67: 1 | DB67: 1
A68: FL-Orlando | B68: 812 | C68: 1249 | D68: 1249 | E68: Irwin | F68: Angel Mora | G68: 1164 W NEW HAVEN AVE | H68: MELBOURNE | I68: FL | J68: 32904 | K68: (321) 265-4007 | L68: All Plans PoR 1 mo. | M68: 10F-101 | N68: 2 | AA68: 0 | AB68: 0 | AF68: 0 | AN68: 1500 | BG68: 10 | CM68: 2 | CS68: 10 | DA68: 1 | DB68: 1
A69: FL-Orlando | B69: 812 | C69: 1254 | D69: 1254 | E69: Millenia | F69: David Gaus | G69: 4588 POWER CENTER LN | H69: ORLANDO | I69: FL | J69: 32839 | K69: (407) 848-1320 | L69: All Plans PoR 1 mo. | M69: 10F-101 | AA69: 2 | AB69: 0 | AF69: 0 | AN69: 1500 | BG69: 10 | CM69: 2 | CS69: 10 | DA69: 1 | DB69: 1
A70: FL-Orlando | B70: 812 | C70: 1856 | D70: 1856 | E70: Belvedere | F70: Kevin Mckinnon | G70: 2505 PARR DR | H70: THE VILLAGES | I70: FL | J70: 32162 | K70: (352) 775-1805 | L70: All Plans PoR 1 mo. | M70: 10F-101 | AA70: 2 | AB70: 0 | AF70: 0 | AN70: 1500 | BG70: 10 | CM70: 2 | CS70: 10 | DA70: 1 | DB70: 1
A71: FL-Southeast Florida | B71: 832 | C71: 1854 | D71: 1854 | E71: Hypoluxo | F71: Karlee Feldner | G71: 1833 HYPOLUXO RD | H71: LANTANA | I71: FL | J71: 33462 | K71: (561) 407-0035 | L71: All Plans PoR 1 mo. | M71: 10F-201 | AA71: 1 | AB71: 0 | AF71: 0 | AP71: 1500 | BI71: 10 | CM71: 2 | CS71: 10 | DA71: 1 | DB71: 1
A72: FL-Southeast Florida | B72: 812 | C72: 1855 | D72: 1855 | E72: Goldenrod | F72: Dylan Sanchez | G72: 3775 NW FEDERAL HWY | H72: JENSEN BEACH | I72: FL | J72: 34957 | K72: (772) 208-3966 | L72: All Plans PoR 1 mo. | M72: 10F-201 | N72: 2 | AA72: 0 | AB72: 0 | AF72: 0 | AP72: 1500 | BI72: 10 | CM72: 2 | CS72: 10 | DA72: 1 | DB72: 1
A73: FL-Tampa | B73: 812 | C73: 0226 | D73: 226 | E73: North Dale Mabry | F73: Dennis Crumlich | G73: 8101 NORTH DALE MABRY | H73: TAMPA | I73: FL | J73: 33614 | K73: (813) 933-6661 | L73: All Plans PoR 1 mo. | M73: 10F-201 | N73: 0 | AA73: 0 | AB73: 0 | AK73: 1 | AP73: 1500 | BI73: 10 | CM73: 2 | CS73: 10 | DA73: 1 | DB73: 1
A74: FL-Tampa | B74: 812 | C74: 0273 | D74: 273 | E74: Hudson | F74: Skiler Woods | G74: 12611 US HIGHWAY 19 | H74: HUDSON | I74: FL | J74: 34667-1955 | K74: (727) 868-7130 | L74: All Plans PoR 1 mo. | M74: 10F-201 | N74: 0 | AA74: 0 | AB74: 0 | AK74: 0 | AP74: 1500 | BI74: 10 | CF74: 1 | CM74: 2 | CS74: 10 | DA74: 1 | DB74: 1
A75: FL-Tampa | B75: 812 | C75: 0274 | D75: 274 | E75: Spring Hill | F75: Taylin McCormick | G75: 4330 COMMERCIAL WAY | H75: SPRING HILL | I75: FL | J75: 34606 | K75: (352) 597-5573 | L75: All Plans PoR 1 mo. | M75: 10F-201 | N75: 0 | AA75: 0 | AB75: 1 | AK75: 1 | AP75: 1500 | BI75: 10 | CM75: 2 | CS75: 10 | DA75: 1 | DB75: 1
A76: FL-Tampa | B76: 812 | C76: 1221 | D76: 1221 | E76: State Route 52 | F76: Taylor Masters | G76: 9215 STATE ROUTE 52 | H76: HUDSON | I76: FL | J76: 34669 | K76: (727) 214-3847 | L76: All Plans PoR 1 mo. | M76: 10F-201 | N76: 0 | AA76: 1 | AB76: 0 | AF76: 0 | AP76: 1500 | BI76: 10 | CM76: 2 | CS76: 10 | DA76: 1 | DB76: 1
A77: FL-Tampa | B77: 812 | C77: 1251 | D77: 1251 | E77: Park Ridge | F77: James Thomas | G77: 6801 PARK BLVD | H77: PINELLAS PARK | I77: FL | J77: 33781 | K77: (727) 620-5085 | L77: All Plans PoR 1 mo. | M77: 10F-201 | N77: 1 | AA77: 0 | AB77: 0 | AF77: 0 | AP77: 1500 | BI77: 10 | CM77: 2 | CS77: 10 | DA77: 1 | DB77: 1
A78: FL-Tampa | B78: 832 | C78: 1901 | D78: 1901 | E78: Hillsborough | F78: David Herster | G78: 12806 W HILLSBOROUGH AVE | H78: TAMPA | I78: FL | J78: 33635 | K78: (656) 444-0758 | L78: All Plans PoR 1 mo. | M78: 10F-201 | N78: 0 | AA78: 0 | AB78: 0 | AF78: 0 | AP78: 1500 | BI78: 10 | CF78: 1 | CM78: 2 | CS78: 10 | DA78: 1 | DB78: 1
A79: FL-Tampa | B79: 832 | C79: 1902 | D79: 1902 | E79: Wesley Chapel | F79: Evan Hinzman | G79: 29891 WESLEY CHAPEL BLVD | H79: WESLEY CHAPEL | I79: FL | J79: 33543 | K79: (656) 202-4586 | L79: All Plans PoR 1 mo. | M79: 10F-201 | N79: 0 | AA79: 2 | AB79: 0 | AF79: 0 | AP79: 1500 | BI79: 10 | CM79: 2 | CS79: 10 | DA79: 1 | DB79: 1
A80: FL-Tampa | B80: 812 | C80: 2501 | D80: 2501 | E80: Zephyrhills | F80: William Sprinkle | G80: 6353 GALL BOULEVARD | H80: ZEPHYRHILLS | I80: FL | J80: 33542 | K80: (813) 670-2213 | L80: All Plans PoR 1 mo. | M80: 10F-201 | N80: 1 | T80: 0 | AB80: 0 | AF80: 0 | AP80: 1500 | BI80: 10 | CM80: 2 | CS80: 10 | DA80: 1 | DB80: 1
A81: GA-Atlanta | B81: 813 | C81: 0264 | D81: 264 | E81: Hiram | F81: Alexis Strozier | G81: 5651 WENDY BAGWELL PKWY | H81: HIRAM | I81: GA | J81: 30141-7806 | K81: (770) 943-5967 | L81: $5, $10, $15 | M81: C01 | N81: 0 | T81: 0 | AB81: 0 | AG81: 1 | AX81: 1500 | BQ81: 10 | CI81: 2 | CP81: 10 | CV81: 1 | DB81: 1
A82: GA-Atlanta | B82: 813 | C82: 0270 | D82: 270 | E82: Peachtree | F82: Robert Feinburg | G82: 930 PEACHTREE PKWY | H82: CUMMING | I82: GA | J82: 30041-6823 | K82: (678) 771-8783 | L82: $5, $10, $15 | M82: C01 | N82: 0 | T82: 0 | AB82: 0 | AG82: 2 | AX82: 1500 | BQ82: 10 | CI82: 2 | CP82: 10 | CV82: 1 | DB82: 1
A83: IA-Cedar Rapids/Davenport | B83: 801 | C83: 1484 | D83: 1484 | E83: Kimberly Rd | F83: Elijah Miller | G83: 707 E KIMBERLY RD | H83: DAVENPORT | I83: IA | J83: 52807 | K83: (563) 265-3110 | L83: $9.99 all plans 1 mo. | M83: 8D-04 | N83: 0 | X83: 2 | AB83: 0 | AF83: 0 | AQ83: 1500 | BJ83: 10 | CJ83: 2 | CQ83: 10 | CW83: 1 | DB83: 1
A84: IA-Cedar Rapids/Davenport | B84: 801 | C84: 1723 | D84: 1723 | E84: Lakeview | F84: Sydney Rosebrough | G84: 4511 E 53RD STREET | H84: DAVENPORT | I84: IA | J84: 52807 | K84: (563) 306-2633 | L84: $9.99 all plans 1 mo. | M84: 8D-04 | N84: 0 | X84: 1 | AB84: 0 | AF84: 0 | AQ84: 1500 | BJ84: 10 | CJ84: 2 | CQ84: 10 | CW84: 1 | DB84: 1
A85: IA-Des Moines | B85: 801 | C85: 0730 | D85: 730 | E85: 14th Street | F85: Thomas Duncan | G85: 3400 SE 14TH ST | H85: DES MOINES | I85: IA | J85: 50320 | K85: (515) 974-5062 | L85: $9.99 all plans 1 mo. | M85: D01 | N85: 0 | W85: 2 | AB85: 0 | AF85: 0 | AZ85: 1500 | BS85: 10 | CJ85: 2 | CQ85: 10 | CX85: 1 | DB85: 1
A86: IA-Des Moines | B86: 801 | C86: 0731 | D86: 731 | E86: North Merle Hay | F86: Marina Song | G86: 4850 MERLE HAY RD | H86: URBANDALE | I86: IA | J86: 50322 | K86: (515) 254-2593 | L86: $9.99 all plans 1 mo. | M86: D01 | N86: 0 | W86: 2 | AB86: 0 | AF86: 0 | AZ86: 1500 | BS86: 10 | CJ86: 2 | CQ86: 10 | CX86: 1 | DB86: 1
A87: IA-Des Moines | B87: 801 | C87: 0733 | D87: 733 | E87: Grimes | F87: Neris Martinez | G87: 1901 SE 11TH ST | H87: GRIMES | I87: IA | J87: 50111 | K87: (515) 325-1712 | L87: $9.99 all plans 1 mo. | M87: D01 | N87: 0 | W87: 0 | AC87: 2 | AF87: 0 | AZ87: 1500 | BS87: 10 | CJ87: 2 | CQ87: 10 | CX87: 1 | DB87: 1
A88: IA-Des Moines | B88: 801 | C88: 0734 | D88: 734 | E88: Ankeny | F88: Bahari Afare | G88: 109 S ANKENY BLVD | H88: ANKENY | I88: IA | J88: 50023 | K88: (515) 325-0478 | L88: $9.99 all plans 1 mo. | M88: D01 | N88: 0 | W88: 2 | AB88: 0 | AF88: 0 | AZ88: 1500 | BS88: 10 | CJ88: 2 | CQ88: 10 | CX88: 1 | DB88: 1
A89: IA-Des Moines | B89: 801 | C89: 1721 | D89: 1721 | E89: 12th Ave | F89: Shoalie Niebauer | G89: 5440 E UNIVERSITY AVE | H89: PLEASANT HILL | I89: IA | J89: 50327 | K89: (515) 957-7218 | L89: $9.99 all plans 1 mo. | M89: D01 | N89: 0 | W89: 1 | AB89: 0 | AF89: 0 | AZ89: 1500 | BS89: 10 | CJ89: 2 | CQ89: 10 | CX89: 1 | DB89: 1
A90: IA-Des Moines | B90: 801 | C90: 1722 | D90: 1722 | E90: Altoona | F90: Tajanae Miller | G90: 3590 PRAIRIE FIRE NW | H90: ALTOONA | I90: IA | J90: 50009 | K90: (515) 978-8988 | L90: $9.99 all plans 1 mo. | M90: D01 | N90: 0 | W90: 2 | AB90: 0 | AF90: 0 | AZ90: 1500 | BS90: 10 | CJ90: 2 | CQ90: 10 | CX90: 1 | DB90: 1
A91: IA-Des Moines | B91: 801 | C91: 1724 | D91: 1724 | E91: Hickman | F91: Savhannah White | G91: 555 E HICKMAN RD | H91: WAUKEE | I91: IA | J91: 50263 | K91: (515) 207-6522 | L91: $9.99 all plans 1 mo. | M91: D01 | N91: 0 | W91: 2 | AB91: 0 | AF91: 0 | AZ91: 1500 | BS91: 10 | CJ91: 2 | CQ91: 10 | CX91: 1 | DB91: 1
A92: ID-Boise | B92: 800 | C92: 0501 | D92: 501 | E92: Fairview | F92: Mikel Hart | G92: 5950 FAIRVIEW AVENUE | H92: BOISE | I92: ID | J92: 83704 | K92: (208) 322-5950 | L92: $9.99 all plans 1 mo. | M92: D03 | N92: 0 | W92: 2 | AB92: 0 | AF92: 0 | BB92: 1500 | BU92: 10 | CJ92: 2 | CQ92: 10 | CX92: 1 | DB92: 1
A93: ID-Boise | B93: 800 | C93: 0506 | D93: 506 | E93: Meridian | F93: Hector Hinojosa | G93: 3296 E PINE AVE | H93: MERIDIAN | I93: ID | J93: 83642 | K93: (208) 895-8077 | L93: $9.99 all plans 1 mo. | M93: D03 | N93: 0 | W93: 1 | AB93: 0 | AF93: 0 | BB93: 1500 | BU93: 10 | CJ93: 2 | CQ93: 10 | CX93: 1 | DB93: 1
A94: ID-Boise | B94: 800 | C94: 1509 | D94: 1509 | E94: Milano | F94: Ashley Marten | G94: 4891 N CORTONA WAY | H94: MERIDIAN | I94: ID | J94: 83646 | K94: (208) 202-5469 | L94: $9.99 all plans 1 mo. | M94: D03 | N94: 0 | W94: 2 | AB94: 0 | AF94: 0 | BB94: 1500 | BU94: 10 | CJ94: 2 | CQ94: 10 | CX94: 1 | DB94: 1
A95: ID-Boise | B95: 800 | C95: 1510 | D95: 1510 | E95: Progress Ave | F95: Shane Ford | G95: 675 S PROGRESS AVE | H95: MERIDIAN | I95: ID | J95: 83642 | K95: (208) 297-3240 | L95: $9.99 all plans 1 mo. | M95: D03 | R95: 1 | T95: 0 | AB95: 0 | AF95: 0 | BB95: 1500 | BU95: 10 | CJ95: 2 | CQ95: 10 | CX95: 1 | DB95: 1
A96: MD-Baltimore | B96: 801 | C96: 0652 | D96: 652 | E96: Severna | F96: Joseph Green | G96: 8562 VETERANS HIGHWAY | H96: MILLERSVILLE | I96: MD | J96: 21108 | K96: (410) 729-9274 | L96: 50% off all plan 1 mo. | M96: E07 | N96: 0 | Y96: 2 | AB96: 0 | AF96: 0 | BF96: 1500 | BY96: 10 | CK96: 2 | CR96: 10 | CX96: 1 | DB96: 1
A97: MI-Detroit | B97: 801 | C97: 1474 | D97: 1474 | E97: Ford Rd | F97: Kaitlin Cole | G97: 2104 HAGGERTY ROAD N | H97: CANTON | I97: MI | J97: 48187 | K97: (734) 238-3088 | L97: All Plans PoR 1 mo. | M97: 10F-104 | N97: 2 | T97: 0 | AB97: 0 | AF97: 0 | AO97: 1500 | BH97: 10 | CM97: 2 | CS97: 10 | DA97: 1 | DB97: 1
A98: MI-Detroit | B98: 810 | C98: 1495 | D98: 1495 | E98: Latson | F98: Travis Adle | G98: 1015 S LATSON RD | H98: HOWELL | I98: MI | J98: 48843 | K98: (517) 225-6675 | L98: All Plans PoR 1 mo. | M98: 10F-101 | N98: 1 | AN98: 1500 | BG98: 10 | CM98: 2 | CS98: 10 | DA98: 1 | DB98: 1
A99: MI-Detroit | B99: 810 | C99: 2537 | D99: 2537 | E99: New Baltimore | F99: Chris Gallup | G99: 29300 23 MILE RD | H99: NEW BALTIMORE | I99: MI | J99: 48047 | K99: (586) 210-6765 | L99: All Plans PoR 1 mo. | M99: 10F-104 | N99: 1 | T99: 0 | AB99: 0 | AF99: 0 | AO99: 1500 | BH99: 10 | CM99: 2 | CS99: 10 | DA99: 1 | DB99: 1
A100: MI-Detroit | B100: 810 | C100: 2538 | D100: 2538 | E100: Clarkston | F100: Sara Kangas | G100: 6440 DIXIE HWY | H100: CLARKSTON | I100: MI | J100: 48346 | K100: (248) 605-0440 | L100: All Plans PoR 1 mo. | M100: 10F-104 | N100: 1 | T100: 0 | AB100: 0 | AF100: 0 | AO100: 1500 | BH100: 10 | CM100: 2 | CS100: 10 | DA100: 1 | DB100: 1
...

Sheet As Table
V1: 1500
N2: Awareness Flyers | AG2: Handheld Menus | AZ2: Mister Kiosk Stickers | BF2: Gen 2 Pegasus Kiosk Stickers | BO2: Gen 1 Pegasus Kiosk Stickers | BR2: DRB Kiosk Stickers | CA2: 28x44 Windscreens | CI2: Roadside Banners | CR2: Scancards | CX2: Collateral Guide | DD2: Box Sticker
M3: Filename | CR3: $10 for 3mos | CS3: $15 Off | CT3: $5, $10, $15 | CU3: 9.99 | CV3: 50% Off | CW3: PoR | CX3: $10 for 3mos | CY3: $15 Off | CZ3: $5, $10, $15 | DA3: 9.99 - Base $8 | DB3: 9.99 - Base $10 | DC3: 50% Off | DD3: PoR - Base $8 | DE3: PoR - Base $10
A4: Region | B4: CC | C4: Store # | D4: Vlookup Store # | E4: Location Name | F4: General Manager | G4: Address | H4: City | I4: State | J4: Zip Code | K4: Phone Number | L4: Promo | M4: Art Code | N4: 10F-101 | O4: 10F-104 | P4: 10F-201 | Q4: 8D-04 | R4: 8D-05 | S4: 8F-304 | T4: A01 | U4: B01 | V4: B05 | W4: B06 | X4: C01 | Y4: C04 | Z4: D01 | AA4: D02 | AB4: D03 | AC4: D06 | AD4: E01 | AE4: E03 | AF4: E07 | AG4: 10F-1012 | AH4: 10F-1043 | AI4: 10F-2014 | AJ4: 8D-045 | AK4: 8D-056 | AL4: 8F-3047 | AM4: A018 | AN4: B019 | AO4: B0510 | AP4: B0611 | AQ4: C0112 | AR4: C0413 | AS4: D0114 | AT4: D0215 | AU4: D0316 | AV4: D0617 | AW4: E0118 | AX4: E0319 | AY4: E0720 | AZ4: 10F | BA4: 8F | BB4: A | BC4: B | BD4: D | BE4: E | BF4: A2 | BG4: B3 | BH4: C | BI4: D4 | BJ4: 8D | BK4: E5 | BL4: 8F6 | BM4: 10F7 | BN4: G | BO4: 10F2 | BP4: D2 | BQ4: B2 | BR4: B4 | BS4: C5 | BT4: D6 | BU4: 8D7 | BV4: E8 | BW4: 8F9 | BX4: 10F10 | BY4: E11 | BZ4: G12 | CA4: A3 | CB4: B5 | CC4: D3 | CD4: 8D2 | CE4: E2 | CF4: 8F2 | CG4: 10F3 | CH4: G2 | CI4: A4 | CJ4: B6 | CK4: C7 | CL4: D8 | CM4: 8D9 | CN4: E10 | CO4: 8F11 | CP4: 10F12 | CQ4: G13 | CR4: A5 | CS4: B7 | CT4: C8 | CU4: D9 | CV4: E12 | CW4: F | CX4: A6 | CY4: B8 | CZ4: C9 | DA4: 8D10 | DB4: D11 | DC4: E13 | DD4: 8F14 | DE4: 10F | DF4: SUM | DG4: Item 2 | DH4: Item 3
A5: AL-Huntsville | B5: 813 | C5: 0041 | D5: 41 | E5: Hartselle | F5: MaryGrace Gilley | G5: 1206 HIGHWAY 31 NW | H5: HARTSELLE | I5: AL | J5: 35640-4421 | K5: (256) 773-7737 | L5: 50% off all plan 1 mo. | M5: E01 | AD5: 1500 | AW5: 10 | AZ5: =VLOOKUP(Table7[[#This Row],[Vlookup Store '#]],'Kiosk Stickers'!A$4:$H$538,2,FALSE) -> 0 | BA5: =VLOOKUP(Table7[[#This Row],[Vlookup Store '#]],'Kiosk Stickers'!A$4:$H$538,2,FALSE) -> 0 | BB5: =VLOOKUP(Table7[[#This Row],[General Manager]],'Kiosk Stickers'!C$4:$H$538,2,FALSE) -> #N/A | BC5: =VLOOKUP(Table7[[#This Row],[Address]],'Kiosk Stickers'!D$4:$H$538,2,FALSE) -> #N/A | BD5: =VLOOKUP(Table7[[#This Row],[City]],'Kiosk Stickers'!E$4:$H$538,2,FALSE) -> #N/A | BE5: =VLOOKUP(Table7[[#This Row],[State]],'Kiosk Stickers'!F$4:$H$538,2,FALSE) -> #N/A | BF5: =VLOOKUP(Table7[[#This Row],[Vlookup Store '#]],'Kiosk Stickers'!A$4:$H$538,3,FALSE) -> 0 | BO5: =VLOOKUP(Table7[[#This Row],[Vlookup Store '#]],'Kiosk Stickers'!A$4:$H$538,4,FALSE) -> 0 | BV5: =VLOOKUP(Table7[[#This Row],[Vlookup Store '#]],'Kiosk Stickers'!A$4:$H$538,5,FALSE) -> 1 | CN5: 2 | CV5: 10 | DB5: 1 | DF5: =SUM(CX5:DE5) -> 1
A6: AL-Huntsville | B6: 813 | C6: 0042 | D6: 42 | E6: Limestone | F6: Jamie Garrie | G6: 1321 US HIGHWAY 72 E | H6: ATHENS | I6: AL | J6: 35611-4405 | K6: (256) 233-2290 | L6: 50% off all plan 1 mo. | M6: E01 | AD6: 1500 | AW6: 10 | AZ6: =VLOOKUP(Table7[[#This Row],[Vlookup Store '#]],'Kiosk Stickers'!A$4:$H$538,2,FALSE) -> 0 | BF6: =VLOOKUP(Table7[[#This Row],[Vlookup Store '#]],'Kiosk Stickers'!A$4:$H$538,3,FALSE) -> 0 | BO6: =VLOOKUP(Table7[[#This Row],[Vlookup Store '#]],'Kiosk Stickers'!A$4:$H$538,4,FALSE) -> 0 | BV6: =VLOOKUP(Table7[[#This Row],[Vlookup Store '#]],'Kiosk Stickers'!A$4:$H$538,5,FALSE) -> 1 | CN6: 2 | CV6: 10 | DB6: 1 | DF6: =SUM(CX6:DE6) -> 1
A7: AL-Huntsville | B7: 813 | C7: 0043 | D7: 43 | E7: Madison | F7: Klaryssa Melendrez | G7: 5509 PROMENADE POINT PKWY | H7: MADISON | I7: AL | J7: 35758-6701 | K7: (256) 895-2693 | L7: 50% off all plan 1 mo. | M7: E01 | AD7: 1500 | AW7: 10 | AZ7: =VLOOKUP(Table7[[#This Row],[Vlookup Store '#]],'Kiosk Stickers'!A$4:$H$538,2,FALSE) -> 0 | BF7: =VLOOKUP(Table7[[#This Row],[Vlookup Store '#]],'Kiosk Stickers'!A$4:$H$538,3,FALSE) -> 0 | BO7: =VLOOKUP(Table7[[#This Row],[Vlookup Store '#]],'Kiosk Stickers'!A$4:$H$538,4,FALSE) -> 0 | BV7: =VLOOKUP(Table7[[#This Row],[Vlookup Store '#]],'Kiosk Stickers'!A$4:$H$538,5,FALSE) -> 1 | CN7: 2 | CV7: 10 | DB7: 1 | DF7: =SUM(CX7:DE7) -> 1
A8: AL-Huntsville | B8: 813 | C8: 0044 | D8: 44 | E8: Setter | F8: Stevie Wagner | G8: 627 BELTLINE RD SW | H8: DECATUR | I8: AL | J8: 35601 | K8: (256) 867-0108 | L8: 50% off all plan 1 mo. | M8: E01 | AD8: 1500 | AW8: 10 | AZ8: =VLOOKUP(Table7[[#This Row],[Vlookup Store '#]],'Kiosk Stickers'!A$4:$H$538,2,FALSE) -> 0 | BF8: =VLOOKUP(Table7[[#This Row],[Vlookup Store '#]],'Kiosk Stickers'!A$4:$H$538,3,FALSE) -> 0 | BO8: =VLOOKUP(Table7[[#This Row],[Vlookup Store '#]],'Kiosk Stickers'!A$4:$H$538,4,FALSE) -> 0 | BV8: =VLOOKUP(Table7[[#This Row],[Vlookup Store '#]],'Kiosk Stickers'!A$4:$H$538,5,FALSE) -> 1 | CN8: 2 | CV8: 10 | DB8: 1 | DF8: =SUM(CX8:DE8) -> 1
A9: AL-Huntsville | B9: 813 | C9: 0045 | D9: 45 | E9: 9th Street | F9: Christian Rider | G9: 2240 BELTLINE RD SW | H9: DECATUR | I9: AL | J9: 35601-7001 | K9: (256) 822-2939 | L9: 50% off all plan 1 mo. | M9: E01 | AD9: 1500 | AW9: 10 | AZ9: =VLOOKUP(Table7[[#This Row],[Vlookup Store '#]],'Kiosk Stickers'!A$4:$H$538,2,FALSE) -> 0 | BF9: =VLOOKUP(Table7[[#This Row],[Vlookup Store '#]],'Kiosk Stickers'!A$4:$H$538,3,FALSE) -> 0 | BO9: =VLOOKUP(Table7[[#This Row],[Vlookup Store '#]],'Kiosk Stickers'!A$4:$H$538,4,FALSE) -> 0 | BV9: =VLOOKUP(Table7[[#This Row],[Vlookup Store '#]],'Kiosk Stickers'!A$4:$H$538,5,FALSE) -> 1 | CN9: 2 | CV9: 10 | DB9: 1 | DF9: =SUM(CX9:DE9) -> 1
A10: AL-Huntsville | B10: 813 | C10: 0046 | D10: 46 | E10: Bassett Ave | F10: Josh Lamey | G10: 721 14TH ST SE | H10: DECATUR | I10: AL | J10: 35601-5911 | K10: (256) 822-2029 | L10: 50% off all plan 1 mo. | M10: E01 | AD10: 1500 | AW10: 10 | AZ10: =VLOOKUP(Table7[[#This Row],[Vlookup Store '#]],'Kiosk Stickers'!A$4:$H$538,2,FALSE) -> 0 | BF10: =VLOOKUP(Table7[[#This Row],[Vlookup Store '#]],'Kiosk Stickers'!A$4:$H$538,3,FALSE) -> 0 | BO10: =VLOOKUP(Table7[[#This Row],[Vlookup Store '#]],'Kiosk Stickers'!A$4:$H$538,4,FALSE) -> 0 | BV10: =VLOOKUP(Table7[[#This Row],[Vlookup Store '#]],'Kiosk Stickers'!A$4:$H$538,5,FALSE) -> 1 | CN10: 2 | CV10: 10 | DB10: 1 | DF10: =SUM(CX10:DE10) -> 1
A11: AL-Huntsville | B11: 813 | C11: 0047 | D11: 47 | E11: Grace | F11: Justin Williams | G11: 403 US HIGHWAY 72 W | H11: ATHENS | I11: AL | J11: 35611-4207 | K11: (256) 998-5312 | L11: 50% off all plan 1 mo. | M11: E01 | AD11: 1500 | AW11: 10 | AZ11: =VLOOKUP(Table7[[#This Row],[Vlookup Store '#]],'Kiosk Stickers'!A$4:$H$538,2,FALSE) -> 0 | BF11: =VLOOKUP(Table7[[#This Row],[Vlookup Store '#]],'Kiosk Stickers'!A$4:$H$538,3,FALSE) -> 0 | BO11: =VLOOKUP(Table7[[#This Row],[Vlookup Store '#]],'Kiosk Stickers'!A$4:$H$538,4,FALSE) -> 0 | BV11: =VLOOKUP(Table7[[#This Row],[Vlookup Store '#]],'Kiosk Stickers'!A$4:$H$538,5,FALSE) -> 1 | CN11: 2 | CV11: 10 | DB11: 1 | DF11: =SUM(CX11:DE11) -> 1
A12: AL-Huntsville | B12: 813 | C12: 0051 | D12: 51 | E12: Azalea | F12: Colby Gray | G12: 271 AZALEA DR | H12: FLORENCE | I12: AL | J12: 35630-1733 | K12: (256) 766-2726 | L12: 50% off all plan 1 mo. | M12: E01 | AD12: 1500 | AW12: 10 | AZ12: =VLOOKUP(Table7[[#This Row],[Vlookup Store '#]],'Kiosk Stickers'!A$4:$H$538,2,FALSE) -> 0 | BF12: =VLOOKUP(Table7[[#This Row],[Vlookup Store '#]],'Kiosk Stickers'!A$4:$H$538,3,FALSE) -> 0 | BO12: =VLOOKUP(Table7[[#This Row],[Vlookup Store '#]],'Kiosk Stickers'!A$4:$H$538,4,FALSE) -> 0 | BV12: =VLOOKUP(Table7[[#This Row],[Vlookup Store '#]],'Kiosk Stickers'!A$4:$H$538,5,FALSE) -> 1 | CN12: 2 | CV12: 10 | DB12: 1 | DF12: =SUM(CX12:DE12) -> 1
A13: AL-Huntsville | B13: 813 | C13: 0052 | D13: 52 | E13: Muscle Shoals | F13: Olivia Thomsen | G13: 702 AVALON AVE | H13: MUSCLE SHOALS | I13: AL | J13: 35661-2304 | K13: (256) 389-3890 | L13: 50% off all plan 1 mo. | M13: E01 | AD13: 1500 | AW13: 10 | AZ13: =VLOOKUP(Table7[[#This Row],[Vlookup Store '#]],'Kiosk Stickers'!A$4:$H$538,2,FALSE) -> 0 | BF13: =VLOOKUP(Table7[[#This Row],[Vlookup Store '#]],'Kiosk Stickers'!A$4:$H$538,3,FALSE) -> 0 | BO13: =VLOOKUP(Table7[[#This Row],[Vlookup Store '#]],'Kiosk Stickers'!A$4:$H$538,4,FALSE) -> 0 | BV13: =VLOOKUP(Table7[[#This Row],[Vlookup Store '#]],'Kiosk Stickers'!A$4:$H$538,5,FALSE) -> 0 | CE13: =VLOOKUP(Table7[[#This Row],[Vlookup Store '#]],'Kiosk Stickers'!A$4:$H$538,6,FALSE) -> 1 | CN13: 2 | CV13: 10 | DB13: 1 | DF13: =SUM(CX13:DE13) -> 1
A14: AL-Huntsville | B14: 813 | C14: 0053 | D14: 53 | E14: Cloverdale | F14: Katherine Huddleston | G14: 2914 CLOVERDALE RD | H14: FLORENCE | I14: AL | J14: 35633 | K14: (256) 712-0183 | L14: 50% off all plan 1 mo. | M14: E01 | AD14: 1500 | AW14: 10 | AZ14: =VLOOKUP(Table7[[#This Row],[Vlookup Store '#]],'Kiosk Stickers'!A$4:$H$538,2,FALSE) -> 0 | BF14: =VLOOKUP(Table7[[#This Row],[Vlookup Store '#]],'Kiosk Stickers'!A$4:$H$538,3,FALSE) -> 0 | BO14: =VLOOKUP(Table7[[#This Row],[Vlookup Store '#]],'Kiosk Stickers'!A$4:$H$538,4,FALSE) -> 0 | BV14: =VLOOKUP(Table7[[#This Row],[Vlookup Store '#]],'Kiosk Stickers'!A$4:$H$538,5,FALSE) -> 1 | CN14: 2 | CV14: 10 | DB14: 1 | DF14: =SUM(CX14:DE14) -> 1
A15: AZ-Tucson | B15: 806 | C15: 0326 | D15: 326 | E15: Swan | F15: Sierrah Bainter | G15: 4600 E BROADWAY BLVD | H15: TUCSON | I15: AZ | J15: 85711-3512 | K15: (520) 428-0256 | L15: $9.99 all plans 1 mo. | M15: D01 | Z15: 1500 | AS15: 10 | AZ15: =VLOOKUP(Table7[[#This Row],[Vlookup Store '#]],'Kiosk Stickers'!A$4:$H$538,2,FALSE) -> 0 | BF15: =VLOOKUP(Table7[[#This Row],[Vlookup Store '#]],'Kiosk Stickers'!A$4:$H$538,3,FALSE) -> 0 | BO15: =VLOOKUP(Table7[[#This Row],[Vlookup Store '#]],'Kiosk Stickers'!A$4:$H$538,4,FALSE) -> 0 | BR15: =VLOOKUP(Table7[[#This Row],[Vlookup Store '#]],'Kiosk Stickers'!A$4:$H$538,5,FALSE) -> 0 | CC15: =VLOOKUP(Table7[[#This Row],[Vlookup Store '#]],'Kiosk Stickers'!A$4:$H$538,6,FALSE) -> 1 | CL15: 2 | CU15: 10 | DB15: 1 | DF15: =SUM(CX15:DE15) -> 1
A16: AZ-Tucson | B16: 806 | C16: 0327 | D16: 327 | E16: South Kolb | F16: Evelyn Conger | G16: 2409 S KOLB RD | H16: TUCSON | I16: AZ | J16: 85710 | K16: (520) 721-9290 | L16: $9.99 all plans 1 mo. | M16: D01 | Z16: 1500 | AS16: 10 | AZ16: =VLOOKUP(Table7[[#This Row],[Vlookup Store '#]],'Kiosk Stickers'!A$4:$H$538,2,FALSE) -> 0 | BF16: =VLOOKUP(Table7[[#This Row],[Vlookup Store '#]],'Kiosk Stickers'!A$4:$H$538,3,FALSE) -> 0 | BO16: =VLOOKUP(Table7[[#This Row],[Vlookup Store '#]],'Kiosk Stickers'!A$4:$H$538,4,FALSE) -> 0 | BR16: =VLOOKUP(Table7[[#This Row],[Vlookup Store '#]],'Kiosk Stickers'!A$4:$H$538,5,FALSE) -> 0 | CC16: =VLOOKUP(Table7[[#This Row],[Vlookup Store '#]],'Kiosk Stickers'!A$4:$H$538,6,FALSE) -> 1 | CL16: 2 | CU16: 10 | DB16: 1 | DF16: =SUM(CX16:DE16) -> 1
A17: AZ-Tucson | B17: 806 | C17: 0328 | D17: 328 | E17: Euclid | F17: Stefanie Osuna | G17: 730 E BROADWAY BLVD | H17: TUCSON | I17: AZ | J17: 85719 | K17: (520) 623-2923 | L17: $9.99 all plans 1 mo. | M17: D01 | Z17: 1500 | AS17: 10 | AZ17: =VLOOKUP(Table7[[#This Row],[Vlookup Store '#]],'Kiosk Stickers'!A$4:$H$538,2,FALSE) -> 0 | BF17: =VLOOKUP(Table7[[#This Row],[Vlookup Store '#]],'Kiosk Stickers'!A$4:$H$538,3,FALSE) -> 0 | BO17: =VLOOKUP(Table7[[#This Row],[Vlookup Store '#]],'Kiosk Stickers'!A$4:$H$538,4,FALSE) -> 0 | BR17: =VLOOKUP(Table7[[#This Row],[Vlookup Store '#]],'Kiosk Stickers'!A$4:$H$538,5,FALSE) -> 0 | CC17: =VLOOKUP(Table7[[#This Row],[Vlookup Store '#]],'Kiosk Stickers'!A$4:$H$538,6,FALSE) -> 1 | CL17: 2 | CU17: 10 | DB17: 1 | DF17: =SUM(CX17:DE17) -> 1
A18: AZ-Tucson | B18: 806 | C18: 0335 | D18: 335 | E18: E Grant | F18: 0 | G18: 3150 E GRANT RD | H18: TUCSON | I18: AZ | J18: 85716 | K18: (520) 881-1486 | L18: $9.99 all plans 1 mo. | M18: D01 | Z18: 1500 | AS18: 10 | AZ18: =VLOOKUP(Table7[[#This Row],[Vlookup Store '#]],'Kiosk Stickers'!A$4:$H$538,2,FALSE) -> 0 | BF18: =VLOOKUP(Table7[[#This Row],[Vlookup Store '#]],'Kiosk Stickers'!A$4:$H$538,3,FALSE) -> 0 | BO18: =VLOOKUP(Table7[[#This Row],[Vlookup Store '#]],'Kiosk Stickers'!A$4:$H$538,4,FALSE) -> 0 | BR18: =VLOOKUP(Table7[[#This Row],[Vlookup Store '#]],'Kiosk Stickers'!A$4:$H$538,5,FALSE) -> 0 | CC18: =VLOOKUP(Table7[[#This Row],[Vlookup Store '#]],'Kiosk Stickers'!A$4:$H$538,6,FALSE) -> 1 | CL18: 2 | CU18: 10 | DB18: 1 | DF18: =SUM(CX18:DE18) -> 1
A19: AZ-Tucson | B19: 806 | C19: 1329 | D19: 1329 | E19: Craycroft | F19: Chandrani Das | G19: 5515 E GRANT RD | H19: TUCSON | I19: AZ | J19: 85712 | K19: (520) 497-1922 | L19: $9.99 all plans 1 mo. | M19: D01 | Z19: 1500 | AS19: 10 | BD19: =VLOOKUP(Table7[[#This Row],[Vlookup Store '#]],'Kiosk Stickers'!A$4:$H$538,2,FALSE) -> 2 | BF19: =VLOOKUP(Table7[[#This Row],[Vlookup Store '#]],'Kiosk Stickers'!A$4:$H$538,3,FALSE) -> 0 | BO19: =VLOOKUP(Table7[[#This Row],[Vlookup Store '#]],'Kiosk Stickers'!A$4:$H$538,4,FALSE) -> 0 | BR19: =VLOOKUP(Table7[[#This Row],[Vlookup Store '#]],'Kiosk Stickers'!A$4:$H$538,5,FALSE) -> 0 | CL19: 2 | CU19: 10 | DB19: 1 | DF19: =SUM(CX19:DE19) -> 1
A20: AZ-Tucson | B20: 806 | C20: 1331 | D20: 1331 | E20: Twin Peaks | F20: Vanna Valdez | G20: 6520 W MARANA CENTER BL | H20: TUCSON | I20: AZ | J20: 85742 | K20: (520) 335-8707 | L20: $9.99 all plans 1 mo. | M20: D01 | Z20: 1500 | AS20: 10 | BD20: 1 | CL20: 2 | CU20: 10 | DB20: 1 | DF20: =SUM(CX20:DE20) -> 1
A21: AZ-Tucson | B21: 806 | C21: 2552 | D21: 2552 | E21: Tucson Mall | F21: Natalie Vazquez Martinez | G21: 4646 N ORACLE | H21: TUCSON | I21: AZ | J21: 85705 | K21: (520) 485-2620 | L21: $9.99 all plans 1 mo. | M21: D01 | Z21: 1500 | AS21: 10 | BD21: =VLOOKUP(Table7[[#This Row],[Vlookup Store '#]],'Kiosk Stickers'!A$4:$H$538,2,FALSE) -> 1 | BF21: =VLOOKUP(Table7[[#This Row],[Vlookup Store '#]],'Kiosk Stickers'!A$4:$H$538,3,FALSE) -> 0 | BO21: =VLOOKUP(Table7[[#This Row],[Vlookup Store '#]],'Kiosk Stickers'!A$4:$H$538,4,FALSE) -> 0 | BR21: =VLOOKUP(Table7[[#This Row],[Vlookup Store '#]],'Kiosk Stickers'!A$4:$H$538,5,FALSE) -> 0 | CL21: 2 | CU21: 10 | DB21: 1 | DF21: =SUM(CX21:DE21) -> 1
A22: AZ-Tucson | B22: 806 | C22: 2557 | D22: 2557 | E22: Cardinal | F22: Martin Soto | G22: 2850 W VALENCIA ROAD | H22: TUCSON | I22: AZ | J22: 85746 | K22: (520) 497-1992 | L22: $9.99 all plans 1 mo. | M22: D01 | Z22: 1500 | AS22: 10 | BD22: =VLOOKUP(Table7[[#This Row],[Vlookup Store '#]],'Kiosk Stickers'!A$4:$H$538,2,FALSE) -> 1 | BF22: =VLOOKUP(Table7[[#This Row],[Vlookup Store '#]],'Kiosk Stickers'!A$4:$H$538,3,FALSE) -> 0 | BO22: =VLOOKUP(Table7[[#This Row],[Vlookup Store '#]],'Kiosk Stickers'!A$4:$H$538,4,FALSE) -> 0 | BR22: =VLOOKUP(Table7[[#This Row],[Vlookup Store '#]],'Kiosk Stickers'!A$4:$H$538,5,FALSE) -> 0 | CL22: 2 | CU22: 10 | DB22: 1 | DF22: =SUM(CX22:DE22) -> 1
A23: CA-Bakersfield | B23: 830 | C23: 1016 | D23: 1016 | E23: Rosedale Hwy | F23: Adrian Vargas | G23: 11921 ROSEDALE HIGHWAY | H23: BAKERSFIELD | I23: CA | J23: 93312 | K23: (661) 230-5335 | L23: $9.99 all plans 1 mo. | M23: D01 | Z23: 1500 | AS23: 10 | BD23: =VLOOKUP(Table7[[#This Row],[Vlookup Store '#]],'Kiosk Stickers'!A$4:$H$538,2,FALSE) -> 0 | BI23: =VLOOKUP(Table7[[#This Row],[Vlookup Store '#]],'Kiosk Stickers'!A$4:$H$538,3,FALSE) -> 2 | BO23: =VLOOKUP(Table7[[#This Row],[Vlookup Store '#]],'Kiosk Stickers'!A$4:$H$538,4,FALSE) -> 0 | BR23: =VLOOKUP(Table7[[#This Row],[Vlookup Store '#]],'Kiosk Stickers'!A$4:$H$538,5,FALSE) -> 0 | CL23: 2 | CU23: 10 | DB23: 1 | DF23: =SUM(CX23:DE23) -> 1
A24: CA-Bakersfield | B24: 830 | C24: 1034 | D24: 1034 | E24: Carmen | F24: Edgar Barron | G24: 1925 S BROADWAY | H24: SANTA MARIA | I24: CA | J24: 93454 | K24: (805) 621-6835 | L24: $9.99 all plans 1 mo. | M24: D01 | Z24: 1500 | AS24: 10 | BD24: =VLOOKUP(Table7[[#This Row],[Vlookup Store '#]],'Kiosk Stickers'!A$4:$H$538,2,FALSE) -> 2 | BI24: =VLOOKUP(Table7[[#This Row],[Vlookup Store '#]],'Kiosk Stickers'!A$4:$H$538,3,FALSE) -> 0 | BO24: =VLOOKUP(Table7[[#This Row],[Vlookup Store '#]],'Kiosk Stickers'!A$4:$H$538,4,FALSE) -> 0 | BR24: =VLOOKUP(Table7[[#This Row],[Vlookup Store '#]],'Kiosk Stickers'!A$4:$H$538,5,FALSE) -> 0 | CL24: 2 | CU24: 10 | DB24: 1 | DF24: =SUM(CX24:DE24) -> 1
A25: CA-Bakersfield | B25: 830 | C25: 1035 | D25: 1035 | E25: Hosking | F25: Susana Ledina | G25: 1601 HOSKING AVE | H25: BAKERSFIELD | I25: CA | J25: 93307 | K25: (661) 336-9952 | L25: $9.99 all plans 1 mo. | M25: D01 | Z25: 1500 | AS25: 10 | BD25: 1 | CL25: 2 | CU25: 10 | DB25: 1 | DF25: =SUM(CX25:DE25) -> 1
A26: CA-Bakersfield | B26: 830 | C26: 1038 | D26: 1038 | E26: Heath | F26: Hailey Divina | G26: 16214 STOCKDALE HWY | H26: BAKERSFIELD | I26: CA | J26: 93314 | K26: (661) 336-9403 | L26: $9.99 all plans 1 mo. | M26: D01 | Z26: 1500 | AS26: 10 | BD26: =VLOOKUP(Table7[[#This Row],[Vlookup Store '#]],'Kiosk Stickers'!A$4:$H$538,2,FALSE) -> 2 | BI26: =VLOOKUP(Table7[[#This Row],[Vlookup Store '#]],'Kiosk Stickers'!A$4:$H$538,3,FALSE) -> 0 | BO26: =VLOOKUP(Table7[[#This Row],[Vlookup Store '#]],'Kiosk Stickers'!A$4:$H$538,4,FALSE) -> 0 | BR26: =VLOOKUP(Table7[[#This Row],[Vlookup Store '#]],'Kiosk Stickers'!A$4:$H$538,5,FALSE) -> 0 | CL26: 2 | CU26: 10 | DB26: 1 | DF26: =SUM(CX26:DE26) -> 1
A27: CA-Bakersfield | B27: 830 | C27: 1058 | D27: 1058 | E27: Stockdale | F27: Jorge Escobar | G27: 11417 STOCKDALE HWY | H27: BAKERSFIELD | I27: CA | J27: 93311 | K27: (661) 636-6520 | L27: $9.99 all plans 1 mo. | M27: D01 | Z27: 1500 | AS27: 10 | BD27: =VLOOKUP(Table7[[#This Row],[Vlookup Store '#]],'Kiosk Stickers'!A$4:$H$538,2,FALSE) -> 2 | BI27: =VLOOKUP(Table7[[#This Row],[Vlookup Store '#]],'Kiosk Stickers'!A$4:$H$538,3,FALSE) -> 0 | BO27: =VLOOKUP(Table7[[#This Row],[Vlookup Store '#]],'Kiosk Stickers'!A$4:$H$538,4,FALSE) -> 0 | BR27: =VLOOKUP(Table7[[#This Row],[Vlookup Store '#]],'Kiosk Stickers'!A$4:$H$538,5,FALSE) -> 0 | CL27: 2 | CU27: 10 | DB27: 1 | DF27: =SUM(CX27:DE27) -> 1
A28: CA-Los Angeles | B28: 830 | C28: 1013 | D28: 1013 | E28: Hwy 138 | F28: Kayla Lopez | G28: 1822 E PALMDALE BLVD | H28: PALMDALE | I28: CA | J28: 93550 | K28: (661) 268-6424 | L28: $9.99 all plans 1 mo. | M28: D01 | Z28: 1500 | AS28: 10 | BD28: =VLOOKUP(Table7[[#This Row],[Vlookup Store '#]],'Kiosk Stickers'!A$4:$H$538,2,FALSE) -> 0 | BI28: =VLOOKUP(Table7[[#This Row],[Vlookup Store '#]],'Kiosk Stickers'!A$4:$H$538,3,FALSE) -> 2 | BO28: =VLOOKUP(Table7[[#This Row],[Vlookup Store '#]],'Kiosk Stickers'!A$4:$H$538,4,FALSE) -> 0 | BR28: =VLOOKUP(Table7[[#This Row],[Vlookup Store '#]],'Kiosk Stickers'!A$4:$H$538,5,FALSE) -> 0 | CL28: 2 | CU28: 10 | DB28: 1 | DF28: =SUM(CX28:DE28) -> 1
A29: CA-Los Angeles | B29: 830 | C29: 1018 | D29: 1018 | E29: Rialto | F29: Olivia Rodriguez | G29: 127 WEST VALLEY BLVD | H29: RIALTO | I29: CA | J29: 92376 | K29: (909) 237-8099 | L29: $9.99 all plans 1 mo. | M29: D01 | Z29: 1500 | AS29: 10 | BD29: =VLOOKUP(Table7[[#This Row],[Vlookup Store '#]],'Kiosk Stickers'!A$4:$H$538,2,FALSE) -> 2 | BI29: =VLOOKUP(Table7[[#This Row],[Vlookup Store '#]],'Kiosk Stickers'!A$4:$H$538,3,FALSE) -> 0 | BO29: =VLOOKUP(Table7[[#This Row],[Vlookup Store '#]],'Kiosk Stickers'!A$4:$H$538,4,FALSE) -> 0 | BR29: =VLOOKUP(Table7[[#This Row],[Vlookup Store '#]],'Kiosk Stickers'!A$4:$H$538,5,FALSE) -> 0 | CL29: 2 | CU29: 10 | DB29: 1 | DF29: =SUM(CX29:DE29) -> 1
A30: CA-Los Angeles | B30: 830 | C30: 1027 | D30: 1027 | E30: Stoneridge | F30: Zachary Ojeda | G30: 27240 EUCALYPTUS AVE | H30: MORENO VALLEY | I30: CA | J30: 92555 | K30: (951) 221-3009 | L30: $9.99 all plans 1 mo. | M30: D01 | Z30: 1500 | AS30: 10 | BD30: =VLOOKUP(Table7[[#This Row],[Vlookup Store '#]],'Kiosk Stickers'!A$4:$H$538,2,FALSE) -> 2 | BI30: =VLOOKUP(Table7[[#This Row],[Vlookup Store '#]],'Kiosk Stickers'!A$4:$H$538,3,FALSE) -> 0 | BO30: =VLOOKUP(Table7[[#This Row],[Vlookup Store '#]],'Kiosk Stickers'!A$4:$H$538,4,FALSE) -> 0 | BR30: =VLOOKUP(Table7[[#This Row],[Vlookup Store '#]],'Kiosk Stickers'!A$4:$H$538,5,FALSE) -> 0 | CL30: 2 | CU30: 10 | DB30: 1 | DF30: =SUM(CX30:DE30) -> 1
A31: CA-Los Angeles | B31: 830 | C31: 1037 | D31: 1037 | E31: Varsity | F31: Anthony Fickewirth | G31: 4212 N VARSITY AVE | H31: SAN BERNARDINO | I31: CA | J31: 92407 | K31: (909) 277-6601 | L31: $9.99 all plans 1 mo. | M31: D01 | Z31: 1500 | AS31: 10 | BD31: =VLOOKUP(Table7[[#This Row],[Vlookup Store '#]],'Kiosk Stickers'!A$4:$H$538,2,FALSE) -> 2 | BI31: =VLOOKUP(Table7[[#This Row],[Vlookup Store '#]],'Kiosk Stickers'!A$4:$H$538,3,FALSE) -> 0 | BO31: =VLOOKUP(Table7[[#This Row],[Vlookup Store '#]],'Kiosk Stickers'!A$4:$H$538,4,FALSE) -> 0 | BR31: =VLOOKUP(Table7[[#This Row],[Vlookup Store '#]],'Kiosk Stickers'!A$4:$H$538,5,FALSE) -> 0 | CL31: 2 | CU31: 10 | DB31: 1 | DF31: =SUM(CX31:DE31) -> 1
A32: CA-Modesto | B32: 831 | C32: 0915 | D32: 915 | E32: Merced | F32: Manuel Toro Garcia | G32: 1800 WEST OLIVE AVE | H32: MERCED | I32: CA | J32: 95348 | K32: (209) 388-9274 | L32: $9.99 all plans 1 mo. | M32: D01 | Z32: 1500 | AS32: 10 | BD32: =VLOOKUP(Table7[[#This Row],[Vlookup Store '#]],'Kiosk Stickers'!A$4:$H$538,2,FALSE) -> 0 | BI32: =VLOOKUP(Table7[[#This Row],[Vlookup Store '#]],'Kiosk Stickers'!A$4:$H$538,3,FALSE) -> 1 | BO32: =VLOOKUP(Table7[[#This Row],[Vlookup Store '#]],'Kiosk Stickers'!A$4:$H$538,4,FALSE) -> 0 | BR32: =VLOOKUP(Table7[[#This Row],[Vlookup Store '#]],'Kiosk Stickers'!A$4:$H$538,5,FALSE) -> 0 | CL32: 2 | CU32: 10 | DB32: 1 | DF32: =SUM(CX32:DE32) -> 1
A33: CA-Modesto | B33: 830 | C33: 1076 | D33: 1076 | E33: Tuolumne | F33: Elicia Solis | G33: 2530 COUNTRYSIDE DR | H33: TURLOCK | I33: CA | J33: 95380 | K33: (350) 203-2119 | L33: $9.99 all plans 1 mo. | M33: D01 | Z33: 1500 | AS33: 10 | BD33: =VLOOKUP(Table7[[#This Row],[Vlookup Store '#]],'Kiosk Stickers'!A$4:$H$538,2,FALSE) -> 2 | BF33: =VLOOKUP(Table7[[#This Row],[Vlookup Store '#]],'Kiosk Stickers'!A$4:$H$538,3,FALSE) -> 0 | BO33: =VLOOKUP(Table7[[#This Row],[Vlookup Store '#]],'Kiosk Stickers'!A$4:$H$538,4,FALSE) -> 0 | BR33: =VLOOKUP(Table7[[#This Row],[Vlookup Store '#]],'Kiosk Stickers'!A$4:$H$538,5,FALSE) -> 0 | CL33: 2 | CU33: 10 | DB33: 1 | DF33: =SUM(CX33:DE33) -> 1
A34: CA-San Joaquin Valley | B34: 830 | C34: 1039 | D34: 1039 | E34: Mooney Blvd | F34: Maurice Lacy | G34: 1920 S MOONEY BLVD | H34: VISALIA | I34: CA | J34: 93277 | K34: (559) 372-0454 | L34: All Plans PoR 1 mo. | M34: 10F-101 | N34: 1500 | AG34: 10 | AZ34: =VLOOKUP(Table7[[#This Row],[Vlookup Store '#]],'Kiosk Stickers'!A$4:$H$538,2,FALSE) -> 2 | BF34: =VLOOKUP(Table7[[#This Row],[Vlookup Store '#]],'Kiosk Stickers'!A$4:$H$538,3,FALSE) -> 0 | BO34: =VLOOKUP(Table7[[#This Row],[Vlookup Store '#]],'Kiosk Stickers'!A$4:$H$538,4,FALSE) -> 0 | BR34: =VLOOKUP(Table7[[#This Row],[Vlookup Store '#]],'Kiosk Stickers'!A$4:$H$538,5,FALSE) -> 0 | CP34: 2 | CW34: 10 | DE34: 1 | DF34: =SUM(CX34:DE34) -> 1
A35: CA-San Joaquin Valley | B35: 830 | C35: 1072 | D35: 1072 | E35: Reedley | F35: Francisco Villatoro | G35: 1595 W MANNING AVE | H35: REEDLEY | I35: CA | J35: 93654 | K35: (559) 554-1641 | L35: All Plans PoR 1 mo. | M35: 10F-101 | N35: 1500 | AG35: 10 | AZ35: =VLOOKUP(Table7[[#This Row],[Vlookup Store '#]],'Kiosk Stickers'!A$4:$H$538,2,FALSE) -> 2 | BF35: =VLOOKUP(Table7[[#This Row],[Vlookup Store '#]],'Kiosk Stickers'!A$4:$H$538,3,FALSE) -> 0 | BO35: =VLOOKUP(Table7[[#This Row],[Vlookup Store '#]],'Kiosk Stickers'!A$4:$H$538,4,FALSE) -> 0 | BR35: =VLOOKUP(Table7[[#This Row],[Vlookup Store '#]],'Kiosk Stickers'!A$4:$H$538,5,FALSE) -> 0 | CP35: 2 | CW35: 10 | DE35: 1 | DF35: =SUM(CX35:DE35) -> 1
A36: CA-Victor Valley | B36: 830 | C36: 1019 | D36: 1019 | E36: Happy Trails Hwy | F36: Salvador Ramirez | G36: 20440 OUTER HWY 18 | H36: APPLE VALLEY | I36: CA | J36: 92307 | K36: (760) 503-0311 | L36: $9.99 all plans 1 mo. | M36: D01 | Z36: 1500 | AS36: 10 | BD36: =VLOOKUP(Table7[[#This Row],[Vlookup Store '#]],'Kiosk Stickers'!A$4:$H$538,2,FALSE) -> 1 | BF36: =VLOOKUP(Table7[[#This Row],[Vlookup Store '#]],'Kiosk Stickers'!A$4:$H$538,3,FALSE) -> 0 | BO36: =VLOOKUP(Table7[[#This Row],[Vlookup Store '#]],'Kiosk Stickers'!A$4:$H$538,4,FALSE) -> 0 | BR36: =VLOOKUP(Table7[[#This Row],[Vlookup Store '#]],'Kiosk Stickers'!A$4:$H$538,5,FALSE) -> 0 | CL36: 2 | CU36: 10 | DB36: 1 | DF36: =SUM(CX36:DE36) -> 1
A37: CA-Victor Valley | B37: 830 | C37: 1031 | D37: 1031 | E37: Jellico Ave | F37: Kenyon Mcwhorter | G37: 17112 MAIN STREET | H37: HESPERIA | I37: CA | J37: 92345 | K37: (442) 267-6146 | L37: $9.99 all plans 1 mo. | M37: D01 | Z37: 1500 | AS37: 10 | BD37: =VLOOKUP(Table7[[#This Row],[Vlookup Store '#]],'Kiosk Stickers'!A$4:$H$538,2,FALSE) -> 2 | BF37: =VLOOKUP(Table7[[#This Row],[Vlookup Store '#]],'Kiosk Stickers'!A$4:$H$538,3,FALSE) -> 0 | BO37: =VLOOKUP(Table7[[#This Row],[Vlookup Store '#]],'Kiosk Stickers'!A$4:$H$538,4,FALSE) -> 0 | BR37: =VLOOKUP(Table7[[#This Row],[Vlookup Store '#]],'Kiosk Stickers'!A$4:$H$538,5,FALSE) -> 0 | CL37: 2 | CU37: 10 | DB37: 1 | DF37: =SUM(CX37:DE37) -> 1
A38: CA-Victor Valley | B38: 830 | C38: 1064 | D38: 1064 | E38: Bear Valley | F38: Natalie Craven | G38: 19389 BEAR VALLEY RD | H38: APPLE VALLEY | I38: CA | J38: 92308 | K38: (442) 855-7229 | L38: $9.99 all plans 1 mo. | M38: D01 | Z38: 1500 | AS38: 10 | BD38: =VLOOKUP(Table7[[#This Row],[Vlookup Store '#]],'Kiosk Stickers'!A$4:$H$538,2,FALSE) -> 1 | BF38: =VLOOKUP(Table7[[#This Row],[Vlookup Store '#]],'Kiosk Stickers'!A$4:$H$538,3,FALSE) -> 0 | BO38: =VLOOKUP(Table7[[#This Row],[Vlookup Store '#]],'Kiosk Stickers'!A$4:$H$538,4,FALSE) -> 0 | BR38: =VLOOKUP(Table7[[#This Row],[Vlookup Store '#]],'Kiosk Stickers'!A$4:$H$538,5,FALSE) -> 0 | CL38: 2 | CU38: 10 | DB38: 1 | DF38: =SUM(CX38:DE38) -> 1
A39: CO-Colorado Springs/Pueblo/Denver | B39: 810 | C39: 0341 | D39: 341 | E39: Prospect Ave | F39: Davante Jordan | G39: 24273 E PROSPECT AVE | H39: AURORA | I39: CO | J39: 80016 | K39: (303) 928-7520 | L39: $15 off all plans 1 mo. | M39: B06 | W39: 1500 | AP39: 10 | AZ39: =VLOOKUP(Table7[[#This Row],[Vlookup Store '#]],'Kiosk Stickers'!A$4:$H$538,2,FALSE) -> 0 | BF39: =VLOOKUP(Table7[[#This Row],[Vlookup Store '#]],'Kiosk Stickers'!A$4:$H$538,3,FALSE) -> 0 | BO39: =VLOOKUP(Table7[[#This Row],[Vlookup Store '#]],'Kiosk Stickers'!A$4:$H$538,4,FALSE) -> 0 | BR39: =VLOOKUP(Table7[[#This Row],[Vlookup Store '#]],'Kiosk Stickers'!A$4:$H$538,5,FALSE) -> 0 | CB39: =VLOOKUP(Table7[[#This Row],[Vlookup Store '#]],'Kiosk Stickers'!A$4:$H$538,6,FALSE) -> 1 | CJ39: 2 | CS39: 10 | CY39: 1 | DF39: =SUM(CX39:DE39) -> 1
A40: CO-Colorado Springs/Pueblo/Denver | B40: 810 | C40: 0343 | D40: 343 | E40: Woodmen | F40: Marvin Willis | G40: 5366 NEW CAR DR | H40: COLORADO SPRINGS | I40: CO | J40: 80923-8854 | K40: (719) 266-0169 | L40: $15 off all plans 1 mo. | M40: B05 | V40: 1500 | AO40: 10 | BC40: =VLOOKUP(Table7[[#This Row],[Vlookup Store '#]],'Kiosk Stickers'!A$4:$H$538,2,FALSE) -> 2 | BF40: =VLOOKUP(Table7[[#This Row],[Vlookup Store '#]],'Kiosk Stickers'!A$4:$H$538,3,FALSE) -> 0 | BO40: =VLOOKUP(Table7[[#This Row],[Vlookup Store '#]],'Kiosk Stickers'!A$4:$H$538,4,FALSE) -> 0 | BR40: =VLOOKUP(Table7[[#This Row],[Vlookup Store '#]],'Kiosk Stickers'!A$4:$H$538,5,FALSE) -> 0 | CJ40: 2 | CS40: 10 | CY40: 1 | DF40: =SUM(CX40:DE40) -> 1
A41: CO-Colorado Springs/Pueblo/Denver | B41: 810 | C41: 0344 | D41: 344 | E41: Bradley | F41: Michael Dye | G41: 1822 MAIN ST | H41: COLORADO SPRINGS | I41: CO | J41: 80911-1152 | K41: (719) 392-2250 | L41: $15 off all plans 1 mo. | M41: B05 | V41: 1500 | AO41: 10 | BC41: =VLOOKUP(Table7[[#This Row],[Vlookup Store '#]],'Kiosk Stickers'!A$4:$H$538,2,FALSE) -> 1 | BF41: =VLOOKUP(Table7[[#This Row],[Vlookup Store '#]],'Kiosk Stickers'!A$4:$H$538,3,FALSE) -> 0 | BO41: =VLOOKUP(Table7[[#This Row],[Vlookup Store '#]],'Kiosk Stickers'!A$4:$H$538,4,FALSE) -> 0 | BR41: =VLOOKUP(Table7[[#This Row],[Vlookup Store '#]],'Kiosk Stickers'!A$4:$H$538,5,FALSE) -> 0 | CJ41: 2 | CS41: 10 | CY41: 1 | DF41: =SUM(CX41:DE41) -> 1
A42: CO-Colorado Springs/Pueblo/Denver | B42: 810 | C42: 0347 | D42: 347 | E42: Fountain | F42: Joshua Benforado | G42: 7980 FOUNTAIN MESA RD | H42: FOUNTAIN | I42: CO | J42: 80817 | K42: (719) 280-0458 | L42: $15 off all plans 1 mo. | M42: B05 | V42: 1500 | AO42: 10 | BC42: =VLOOKUP(Table7[[#This Row],[Vlookup Store '#]],'Kiosk Stickers'!A$4:$H$538,2,FALSE) -> 0 | BG42: =VLOOKUP(Table7[[#This Row],[Vlookup Store '#]],'Kiosk Stickers'!A$4:$H$538,3,FALSE) -> 2 | BO42: =VLOOKUP(Table7[[#This Row],[Vlookup Store '#]],'Kiosk Stickers'!A$4:$H$538,4,FALSE) -> 0 | BR42: =VLOOKUP(Table7[[#This Row],[Vlookup Store '#]],'Kiosk Stickers'!A$4:$H$538,5,FALSE) -> 0 | CJ42: 2 | CS42: 10 | CY42: 1 | DF42: =SUM(CX42:DE42) -> 1
A43: CO-Colorado Springs/Pueblo/Denver | B43: 810 | C43: 0348 | D43: 348 | E43: Old Ranch Rd | F43: Brandon Sirmans | G43: 3581 BLUE HORIZON VIEW | H43: COLORADO SPRINGS | I43: CO | J43: 80924 | K43: (719) 203-2707 | L43: $15 off all plans 1 mo. | M43: B05 | V43: 1500 | AO43: 10 | BC43: =VLOOKUP(Table7[[#This Row],[Vlookup Store '#]],'Kiosk Stickers'!A$4:$H$538,2,FALSE) -> 0 | BG43: =VLOOKUP(Table7[[#This Row],[Vlookup Store '#]],'Kiosk Stickers'!A$4:$H$538,3,FALSE) -> 1 | BO43: =VLOOKUP(Table7[[#This Row],[Vlookup Store '#]],'Kiosk Stickers'!A$4:$H$538,4,FALSE) -> 0 | BR43: =VLOOKUP(Table7[[#This Row],[Vlookup Store '#]],'Kiosk Stickers'!A$4:$H$538,5,FALSE) -> 0 | CJ43: 2 | CS43: 10 | CY43: 1 | DF43: =SUM(CX43:DE43) -> 1
A44: CO-Colorado Springs/Pueblo/Denver | B44: 810 | C44: 1341 | D44: 1341 | E44: Academy Blvd | F44: April Jaramillo | G44: 4275 N ACADEMY BLVD | H44: COLORADO SPRINGS | I44: CO | J44: 80918 | K44: (719) 208-4919 | L44: $15 off all plans 1 mo. | M44: B05 | V44: 1500 | AO44: 10 | BC44: =VLOOKUP(Table7[[#This Row],[Vlookup Store '#]],'Kiosk Stickers'!A$4:$H$538,2,FALSE) -> 2 | BG44: =VLOOKUP(Table7[[#This Row],[Vlookup Store '#]],'Kiosk Stickers'!A$4:$H$538,3,FALSE) -> 0 | BO44: =VLOOKUP(Table7[[#This Row],[Vlookup Store '#]],'Kiosk Stickers'!A$4:$H$538,4,FALSE) -> 0 | BR44: =VLOOKUP(Table7[[#This Row],[Vlookup Store '#]],'Kiosk Stickers'!A$4:$H$538,5,FALSE) -> 0 | CJ44: 2 | CS44: 10 | CY44: 1 | DF44: =SUM(CX44:DE44) -> 1
A45: CO-Colorado Springs/Pueblo/Denver | B45: 810 | C45: 1343 | D45: 1343 | E45: Monument | F45: Conor Symons | G45: 980 W BAPTIST RD | H45: MONUMENT | I45: CO | J45: 80132 | K45: (719) 203-1873 | L45: $15 off all plans 1 mo. | M45: B05 | V45: 1500 | AO45: 10 | BC45: =VLOOKUP(Table7[[#This Row],[Vlookup Store '#]],'Kiosk Stickers'!A$4:$H$538,2,FALSE) -> 2 | BG45: =VLOOKUP(Table7[[#This Row],[Vlookup Store '#]],'Kiosk Stickers'!A$4:$H$538,3,FALSE) -> 0 | BO45: =VLOOKUP(Table7[[#This Row],[Vlookup Store '#]],'Kiosk Stickers'!A$4:$H$538,4,FALSE) -> 0 | BR45: =VLOOKUP(Table7[[#This Row],[Vlookup Store '#]],'Kiosk Stickers'!A$4:$H$538,5,FALSE) -> 0 | CJ45: 2 | CS45: 10 | CY45: 1 | DF45: =SUM(CX45:DE45) -> 1
A46: CO-Colorado Springs/Pueblo/Denver | B46: 810 | C46: 1344 | D46: 1344 | E46: Runway North | F46: Andrew Sweeney | G46: 8809 E 46TH AVE | H46: DENVER | I46: CO | J46: 80238 | K46: (720) 744-0750 | L46: $15 off all plans 1 mo. | M46: B06 | W46: 1500 | AP46: 10 | AZ46: =VLOOKUP(Table7[[#This Row],[Vlookup Store '#]],'Kiosk Stickers'!A$4:$H$538,2,FALSE) -> 0 | BG46: =VLOOKUP(Table7[[#This Row],[Vlookup Store '#]],'Kiosk Stickers'!A$4:$H$538,3,FALSE) -> 2 | BO46: =VLOOKUP(Table7[[#This Row],[Vlookup Store '#]],'Kiosk Stickers'!A$4:$H$538,4,FALSE) -> 0 | BR46: =VLOOKUP(Table7[[#This Row],[Vlookup Store '#]],'Kiosk Stickers'!A$4:$H$538,5,FALSE) -> 0 | CJ46: 2 | CS46: 10 | CY46: 1 | DF46: =SUM(CX46:DE46) -> 1
A47: CO-Colorado Springs/Pueblo/Denver | B47: 810 | C47: 1349 | D47: 1349 | E47: Constitution | F47: Kelly Duran | G47: 6015 CONSTITUTION AVE | H47: COLORADO SPRINGS | I47: CO | J47: 80915 | K47: (719) 301-3064 | L47: $15 off all plans 1 mo. | M47: B05 | V47: 1500 | AO47: 10 | AZ47: =VLOOKUP(Table7[[#This Row],[Vlookup Store '#]],'Kiosk Stickers'!A$4:$H$538,2,FALSE) -> 0 | BG47: =VLOOKUP(Table7[[#This Row],[Vlookup Store '#]],'Kiosk Stickers'!A$4:$H$538,3,FALSE) -> 2 | BO47: =VLOOKUP(Table7[[#This Row],[Vlookup Store '#]],'Kiosk Stickers'!A$4:$H$538,4,FALSE) -> 0 | BR47: =VLOOKUP(Table7[[#This Row],[Vlookup Store '#]],'Kiosk Stickers'!A$4:$H$538,5,FALSE) -> 0 | CJ47: 2 | CS47: 10 | CY47: 1 | DF47: =SUM(CX47:DE47) -> 1
A48: FL-Cape Coral | B48: 812 | C48: 1801 | D48: 1801 | E48: Del Prado | F48: James Glass | G48: 1009 DEL PRADO BLVD S | H48: CAPE CORAL | I48: FL | J48: 33990 | K48: (239) 772-2277 | L48: All Plans PoR 1 mo. | M48: 10F-201 | P48: 1500 | AI48: 10 | AZ48: =VLOOKUP(Table7[[#This Row],[Vlookup Store '#]],'Kiosk Stickers'!A$4:$H$538,2,FALSE) -> 0 | BM48: =VLOOKUP(Table7[[#This Row],[Vlookup Store '#]],'Kiosk Stickers'!A$4:$H$538,3,FALSE) -> 2 | BO48: =VLOOKUP(Table7[[#This Row],[Vlookup Store '#]],'Kiosk Stickers'!A$4:$H$538,4,FALSE) -> 0 | BR48: =VLOOKUP(Table7[[#This Row],[Vlookup Store '#]],'Kiosk Stickers'!A$4:$H$538,5,FALSE) -> 0 | CP48: 2 | CW48: 10 | DE48: 1 | DF48: =SUM(CX48:DE48) -> 1
A49: FL-Cape Coral | B49: 812 | C49: 1805 | D49: 1805 | E49: Santa Barbara Blvd | F49: Santiago Velasquez | G49: 2002 SANTA BARBARA BLVD | H49: CAPE CORAL | I49: FL | J49: 33991 | K49: (239) 791-1707 | L49: All Plans PoR 1 mo. | M49: 10F-201 | P49: 1500 | AI49: 10 | AZ49: =VLOOKUP(Table7[[#This Row],[Vlookup Store '#]],'Kiosk Stickers'!A$4:$H$538,2,FALSE) -> 0 | BM49: =VLOOKUP(Table7[[#This Row],[Vlookup Store '#]],'Kiosk Stickers'!A$4:$H$538,3,FALSE) -> 2 | BO49: =VLOOKUP(Table7[[#This Row],[Vlookup Store '#]],'Kiosk Stickers'!A$4:$H$538,4,FALSE) -> 0 | BR49: =VLOOKUP(Table7[[#This Row],[Vlookup Store '#]],'Kiosk Stickers'!A$4:$H$538,5,FALSE) -> 0 | CP49: 2 | CW49: 10 | DE49: 1 | DF49: =SUM(CX49:DE49) -> 1
A50: FL-Cape Coral | B50: 812 | C50: 1807 | D50: 1807 | E50: Ne 16th Place | F50: Deserae Gannelli | G50: 318 NE 16TH PLACE | H50: CAPE CORAL | I50: FL | J50: 33909 | K50: (239) 402-3119 | L50: All Plans PoR 1 mo. | M50: 10F-201 | P50: 1500 | AI50: 10 | AZ50: =VLOOKUP(Table7[[#This Row],[Vlookup Store '#]],'Kiosk Stickers'!A$4:$H$538,2,FALSE) -> 0 | BM50: =VLOOKUP(Table7[[#This Row],[Vlookup Store '#]],'Kiosk Stickers'!A$4:$H$538,3,FALSE) -> 2 | BO50: =VLOOKUP(Table7[[#This Row],[Vlookup Store '#]],'Kiosk Stickers'!A$4:$H$538,4,FALSE) -> 0 | BR50: =VLOOKUP(Table7[[#This Row],[Vlookup Store '#]],'Kiosk Stickers'!A$4:$H$538,5,FALSE) -> 0 | CP50: 2 | CW50: 10 | DE50: 1 | DF50: =SUM(CX50:DE50) -> 1
A51: FL-Cape Coral | B51: 832 | C51: 1811 | D51: 1811 | E51: Cody Lee | F51: Ryan Russell | G51: 8851 CODY LEE RD | H51: FORT MYERS | I51: FL | J51: 33912 | K51: (239) 234-1276 | L51: All Plans PoR 1 mo. | M51: 10F-201 | P51: 1500 | AI51: 10 | AZ51: =VLOOKUP(Table7[[#This Row],[Vlookup Store '#]],'Kiosk Stickers'!A$4:$H$538,2,FALSE) -> 0 | BM51: =VLOOKUP(Table7[[#This Row],[Vlookup Store '#]],'Kiosk Stickers'!A$4:$H$538,3,FALSE) -> 0 | BO51: =VLOOKUP(Table7[[#This Row],[Vlookup Store '#]],'Kiosk Stickers'!A$4:$H$538,4,FALSE) -> 2 | BR51: =VLOOKUP(Table7[[#This Row],[Vlookup Store '#]],'Kiosk Stickers'!A$4:$H$538,5,FALSE) -> 0 | CP51: 2 | CW51: 10 | DE51: 1 | DF51: =SUM(CX51:DE51) -> 1
A52: FL-Cape Coral | B52: 832 | C52: 1813 | D52: 1813 | E52: Arborwood | F52: Carisa Civiello | G52: 13601 GOLDENWOOD DR | H52: FORT MYERS | I52: FL | J52: 33913 | K52: (239) 241-8294 | L52: All Plans PoR 1 mo. | M52: 10F-201 | P52: 1500 | AI52: 10 | AZ52: =VLOOKUP(Table7[[#This Row],[Vlookup Store '#]],'Kiosk Stickers'!A$4:$H$538,2,FALSE) -> 0 | BM52: =VLOOKUP(Table7[[#This Row],[Vlookup Store '#]],'Kiosk Stickers'!A$4:$H$538,3,FALSE) -> 2 | BO52: =VLOOKUP(Table7[[#This Row],[Vlookup Store '#]],'Kiosk Stickers'!A$4:$H$538,4,FALSE) -> 0 | BR52: =VLOOKUP(Table7[[#This Row],[Vlookup Store '#]],'Kiosk Stickers'!A$4:$H$538,5,FALSE) -> 0 | CP52: 2 | CW52: 10 | DE52: 1 | DF52: =SUM(CX52:DE52) -> 1
A53: FL-Cape Coral | B53: 832 | C53: 1814 | D53: 1814 | E53: Metro Pkwy | F53: Ana Castro | G53: 2811 COLONIAL BLVD | H53: FORT MYERS | I53: FL | J53: 33966 | K53: (239) 241-8300 | L53: All Plans PoR 1 mo. | M53: 10F-201 | P53: 1500 | AI53: 10 | AZ53: =VLOOKUP(Table7[[#This Row],[Vlookup Store '#]],'Kiosk Stickers'!A$4:$H$538,2,FALSE) -> 0 | BM53: =VLOOKUP(Table7[[#This Row],[Vlookup Store '#]],'Kiosk Stickers'!A$4:$H$538,3,FALSE) -> 2 | BO53: =VLOOKUP(Table7[[#This Row],[Vlookup Store '#]],'Kiosk Stickers'!A$4:$H$538,4,FALSE) -> 0 | BR53: =VLOOKUP(Table7[[#This Row],[Vlookup Store '#]],'Kiosk Stickers'!A$4:$H$538,5,FALSE) -> 0 | CP53: 2 | CW53: 10 | DE53: 1 | DF53: =SUM(CX53:DE53) -> 1
A54: FL-Cape Coral | B54: 832 | C54: 1816 | D54: 1816 | E54: Estero | F54: Rick Marsten | G54: 8030 TYSON EYE WAY | H54: ESTERO | I54: FL | J54: 33967 | K54: (239) 422-5745 | L54: All Plans PoR 1 mo. | M54: 10F-201 | P54: 1500 | AI54: 10 | AZ54: =VLOOKUP(Table7[[#This Row],[Vlookup Store '#]],'Kiosk Stickers'!A$4:$H$538,2,FALSE) -> 0 | BM54: =VLOOKUP(Table7[[#This Row],[Vlookup Store '#]],'Kiosk Stickers'!A$4:$H$538,3,FALSE) -> 2 | BO54: =VLOOKUP(Table7[[#This Row],[Vlookup Store '#]],'Kiosk Stickers'!A$4:$H$538,4,FALSE) -> 0 | BR54: =VLOOKUP(Table7[[#This Row],[Vlookup Store '#]],'Kiosk Stickers'!A$4:$H$538,5,FALSE) -> 0 | CP54: 2 | CW54: 10 | DE54: 1 | DF54: =SUM(CX54:DE54) -> 1
A55: FL-Lakeland | B55: 832 | C55: 1906 | D55: 1906 | E55: Florida Ave S | F55: Christina Stivers | G55: 6051 FLORIDA AVE S | H55: LAKELAND | I55: FL | J55: 33813 | K55: (863) 213-0542 | L55: All Plans PoR 1 mo. | M55: 10F-201 | P55: 1500 | AI55: 10 | AZ55: =VLOOKUP(Table7[[#This Row],[Vlookup Store '#]],'Kiosk Stickers'!A$4:$H$538,2,FALSE) -> 0 | BM55: =VLOOKUP(Table7[[#This Row],[Vlookup Store '#]],'Kiosk Stickers'!A$4:$H$538,3,FALSE) -> 0 | BO55: =VLOOKUP(Table7[[#This Row],[Vlookup Store '#]],'Kiosk Stickers'!A$4:$H$538,4,FALSE) -> 2 | BR55: =VLOOKUP(Table7[[#This Row],[Vlookup Store '#]],'Kiosk Stickers'!A$4:$H$538,5,FALSE) -> 0 | CP55: 2 | CW55: 10 | DE55: 1 | DF55: =SUM(CX55:DE55) -> 1
A56: FL-Orlando | B56: 812 | C56: 0233 | D56: 233 | E56: Fern Park | F56: Skylar Prescott | G56: 6501 SOUTH US HWY 17 92 | H56: CASSELBERRY | I56: FL | J56: 32730 | K56: (407) 260-0335 | L56: All Plans PoR 1 mo. | M56: 10F-101 | N56: 1500 | AG56: 10 | AZ56: =VLOOKUP(Table7[[#This Row],[Vlookup Store '#]],'Kiosk Stickers'!A$4:$H$538,2,FALSE) -> 0 | BM56: =VLOOKUP(Table7[[#This Row],[Vlookup Store '#]],'Kiosk Stickers'!A$4:$H$538,3,FALSE) -> 1 | BO56: =VLOOKUP(Table7[[#This Row],[Vlookup Store '#]],'Kiosk Stickers'!A$4:$H$538,4,FALSE) -> 0 | BR56: =VLOOKUP(Table7[[#This Row],[Vlookup Store '#]],'Kiosk Stickers'!A$4:$H$538,5,FALSE) -> 0 | CP56: 2 | CW56: 10 | DE56: 1 | DF56: =SUM(CX56:DE56) -> 1
A57: FL-Orlando | B57: 812 | C57: 0235 | D57: 235 | E57: Colonial | F57: Holly Hutcheson | G57: 12180 E COLONIAL DR | H57: ORLANDO | I57: FL | J57: 32826 | K57: (407) 207-1294 | L57: All Plans PoR 1 mo. | M57: 10F-101 | N57: 1500 | AG57: 10 | AZ57: =VLOOKUP(Table7[[#This Row],[Vlookup Store '#]],'Kiosk Stickers'!A$4:$H$538,2,FALSE) -> 0 | BM57: =VLOOKUP(Table7[[#This Row],[Vlookup Store '#]],'Kiosk Stickers'!A$4:$H$538,3,FALSE) -> 0 | BO57: =VLOOKUP(Table7[[#This Row],[Vlookup Store '#]],'Kiosk Stickers'!A$4:$H$538,4,FALSE) -> 0 | BR57: =VLOOKUP(Table7[[#This Row],[Vlookup Store '#]],'Kiosk Stickers'!A$4:$H$538,5,FALSE) -> 0 | CG57: =VLOOKUP(Table7[[#This Row],[Vlookup Store '#]],'Kiosk Stickers'!A$4:$H$538,6,FALSE) -> 1 | CP57: 2 | CW57: 10 | DE57: 1 | DF57: =SUM(CX57:DE57) -> 1
A58: FL-Orlando | B58: 812 | C58: 0236 | D58: 236 | E58: Chickasaw | F58: Celi Cordero | G58: 7958 E COLONIAL DR | H58: ORLANDO | I58: FL | J58: 32807 | K58: (407) 203-0993 | L58: All Plans PoR 1 mo. | M58: 10F-101 | N58: 1500 | AG58: 10 | AZ58: =VLOOKUP(Table7[[#This Row],[Vlookup Store '#]],'Kiosk Stickers'!A$4:$H$538,2,FALSE) -> 0 | BM58: =VLOOKUP(Table7[[#This Row],[Vlookup Store '#]],'Kiosk Stickers'!A$4:$H$538,3,FALSE) -> 2 | BO58: =VLOOKUP(Table7[[#This Row],[Vlookup Store '#]],'Kiosk Stickers'!A$4:$H$538,4,FALSE) -> 0 | BR58: =VLOOKUP(Table7[[#This Row],[Vlookup Store '#]],'Kiosk Stickers'!A$4:$H$538,5,FALSE) -> 0 | CP58: 2 | CW58: 10 | DE58: 1 | DF58: =SUM(CX58:DE58) -> 1
A59: FL-Orlando | B59: 812 | C59: 0243 | D59: 243 | E59: Silver Star | F59: Brendan Gilreath | G59: 4551 SILVER STAR RD | H59: ORLANDO | I59: FL | J59: 32808 | K59: (407) 553-3430 | L59: All Plans PoR 1 mo. | M59: 10F-101 | N59: 1500 | AG59: 10 | AZ59: =VLOOKUP(Table7[[#This Row],[Vlookup Store '#]],'Kiosk Stickers'!A$4:$H$538,2,FALSE) -> 0 | BM59: =VLOOKUP(Table7[[#This Row],[Vlookup Store '#]],'Kiosk Stickers'!A$4:$H$538,3,FALSE) -> 1 | BO59: =VLOOKUP(Table7[[#This Row],[Vlookup Store '#]],'Kiosk Stickers'!A$4:$H$538,4,FALSE) -> 0 | BR59: =VLOOKUP(Table7[[#This Row],[Vlookup Store '#]],'Kiosk Stickers'!A$4:$H$538,5,FALSE) -> 0 | CP59: 2 | CW59: 10 | DE59: 1 | DF59: =SUM(CX59:DE59) -> 1
A60: FL-Orlando | B60: 812 | C60: 0279 | D60: 279 | E60: Orange Blossom | F60: Cameron Snell | G60: 5275 S ORANGE BLOSSOM TRAIL | H60: ORLANDO | I60: FL | J60: 32839 | K60: (407) 553-3429 | L60: All Plans PoR 1 mo. | M60: 10F-101 | N60: 1500 | AG60: 10 | AZ60: =VLOOKUP(Table7[[#This Row],[Vlookup Store '#]],'Kiosk Stickers'!A$4:$H$538,2,FALSE) -> 0 | BM60: =VLOOKUP(Table7[[#This Row],[Vlookup Store '#]],'Kiosk Stickers'!A$4:$H$538,3,FALSE) -> 1 | BO60: =VLOOKUP(Table7[[#This Row],[Vlookup Store '#]],'Kiosk Stickers'!A$4:$H$538,4,FALSE) -> 0 | BR60: =VLOOKUP(Table7[[#This Row],[Vlookup Store '#]],'Kiosk Stickers'!A$4:$H$538,5,FALSE) -> 0 | CP60: 2 | CW60: 10 | DE60: 1 | DF60: =SUM(CX60:DE60) -> 1
A61: FL-Orlando | B61: 812 | C61: 1205 | D61: 1205 | E61: Commerce Ctr Dr | F61: Tathiana Rivera | G61: 4670 13TH ST | H61: SAINT CLOUD | I61: FL | J61: 34769 | K61: (407) 559-9787 | L61: All Plans PoR 1 mo. | M61: 10F-101 | N61: 1500 | AG61: 10 | AZ61: =VLOOKUP(Table7[[#This Row],[Vlookup Store '#]],'Kiosk Stickers'!A$4:$H$538,2,FALSE) -> 0 | BM61: =VLOOKUP(Table7[[#This Row],[Vlookup Store '#]],'Kiosk Stickers'!A$4:$H$538,3,FALSE) -> 2 | BO61: =VLOOKUP(Table7[[#This Row],[Vlookup Store '#]],'Kiosk Stickers'!A$4:$H$538,4,FALSE) -> 0 | BR61: =VLOOKUP(Table7[[#This Row],[Vlookup Store '#]],'Kiosk Stickers'!A$4:$H$538,5,FALSE) -> 0 | CP61: 2 | CW61: 10 | DE61: 1 | DF61: =SUM(CX61:DE61) -> 1
A62: FL-Orlando | B62: 812 | C62: 1206 | D62: 1206 | E62: Kissimmee | F62: Luz Rodriguez | G62: 4573 W IRLO BRONSON MEMORIAL HWY | H62: KISSIMMEE | I62: FL | J62: 34746 | K62: (407) 390-1400 | L62: All Plans PoR 1 mo. | M62: 10F-101 | N62: 1500 | AG62: 10 | AZ62: =VLOOKUP(Table7[[#This Row],[Vlookup Store '#]],'Kiosk Stickers'!A$4:$H$538,2,FALSE) -> 0 | BM62: =VLOOKUP(Table7[[#This Row],[Vlookup Store '#]],'Kiosk Stickers'!A$4:$H$538,3,FALSE) -> 2 | BO62: =VLOOKUP(Table7[[#This Row],[Vlookup Store '#]],'Kiosk Stickers'!A$4:$H$538,4,FALSE) -> 0 | BR62: =VLOOKUP(Table7[[#This Row],[Vlookup Store '#]],'Kiosk Stickers'!A$4:$H$538,5,FALSE) -> 0 | CP62: 2 | CW62: 10 | DE62: 1 | DF62: =SUM(CX62:DE62) -> 1
A63: FL-Orlando | B63: 812 | C63: 1208 | D63: 1208 | E63: Oaks Blvd | F63: Eric Cuebas | G63: 3170 S JOHN YOUNG PKWY | H63: KISSIMMEE | I63: FL | J63: 34746 | K63: (407) 329-2196 | L63: All Plans PoR 1 mo. | M63: 10F-101 | N63: 1500 | AG63: 10 | AZ63: =VLOOKUP(Table7[[#This Row],[Vlookup Store '#]],'Kiosk Stickers'!A$4:$H$538,2,FALSE) -> 0 | BM63: =VLOOKUP(Table7[[#This Row],[Vlookup Store '#]],'Kiosk Stickers'!A$4:$H$538,3,FALSE) -> 2 | BO63: =VLOOKUP(Table7[[#This Row],[Vlookup Store '#]],'Kiosk Stickers'!A$4:$H$538,4,FALSE) -> 0 | BR63: =VLOOKUP(Table7[[#This Row],[Vlookup Store '#]],'Kiosk Stickers'!A$4:$H$538,5,FALSE) -> 0 | CP63: 2 | CW63: 10 | DE63: 1 | DF63: =SUM(CX63:DE63) -> 1
A64: FL-Orlando | B64: 812 | C64: 1215 | D64: 1215 | E64: Ormond Beach | F64: Andre Swanston | G64: 49 S YONGE ST | H64: ORMOND BEACH | I64: FL | J64: 32174 | K64: (386) 356-5113 | L64: All Plans PoR 1 mo. | M64: 10F-101 | N64: 1500 | AG64: 10 | AZ64: =VLOOKUP(Table7[[#This Row],[Vlookup Store '#]],'Kiosk Stickers'!A$4:$H$538,2,FALSE) -> 0 | BM64: =VLOOKUP(Table7[[#This Row],[Vlookup Store '#]],'Kiosk Stickers'!A$4:$H$538,3,FALSE) -> 1 | BO64: =VLOOKUP(Table7[[#This Row],[Vlookup Store '#]],'Kiosk Stickers'!A$4:$H$538,4,FALSE) -> 0 | BR64: =VLOOKUP(Table7[[#This Row],[Vlookup Store '#]],'Kiosk Stickers'!A$4:$H$538,5,FALSE) -> 0 | CP64: 2 | CW64: 10 | DE64: 1 | DF64: =SUM(CX64:DE64) -> 1
A65: FL-Orlando | B65: 832 | C65: 1236 | D65: 1236 | E65: Poinciana | F65: Dakota Polk | G65: 530 CYPRESS PKWY | H65: POINCIANA | I65: FL | J65: 34759 | K65: (321) 300-7499 | L65: All Plans PoR 1 mo. | M65: 10F-101 | N65: 1500 | AG65: 10 | AZ65: =VLOOKUP(Table7[[#This Row],[Vlookup Store '#]],'Kiosk Stickers'!A$4:$H$538,2,FALSE) -> 0 | BM65: =VLOOKUP(Table7[[#This Row],[Vlookup Store '#]],'Kiosk Stickers'!A$4:$H$538,3,FALSE) -> 2 | BO65: =VLOOKUP(Table7[[#This Row],[Vlookup Store '#]],'Kiosk Stickers'!A$4:$H$538,4,FALSE) -> 0 | BR65: =VLOOKUP(Table7[[#This Row],[Vlookup Store '#]],'Kiosk Stickers'!A$4:$H$538,5,FALSE) -> 0 | CP65: 2 | CW65: 10 | DE65: 1 | DF65: =SUM(CX65:DE65) -> 1
A66: FL-Orlando | B66: 832 | C66: 1242 | D66: 1242 | E66: Semoran | F66: Keegan Wyatt | G66: 1405 S SEMORAN BLVD | H66: ORLANDO | I66: FL | J66: 32807 | K66: (321) 300-3207 | L66: All Plans PoR 1 mo. | M66: 10F-101 | N66: 1500 | AG66: 10 | AZ66: =VLOOKUP(Table7[[#This Row],[Vlookup Store '#]],'Kiosk Stickers'!A$4:$H$538,2,FALSE) -> 0 | BM66: =VLOOKUP(Table7[[#This Row],[Vlookup Store '#]],'Kiosk Stickers'!A$4:$H$538,3,FALSE) -> 2 | BO66: =VLOOKUP(Table7[[#This Row],[Vlookup Store '#]],'Kiosk Stickers'!A$4:$H$538,4,FALSE) -> 0 | BR66: =VLOOKUP(Table7[[#This Row],[Vlookup Store '#]],'Kiosk Stickers'!A$4:$H$538,5,FALSE) -> 0 | CP66: 2 | CW66: 10 | DE66: 1 | DF66: =SUM(CX66:DE66) -> 1
A67: FL-Orlando | B67: 832 | C67: 1245 | D67: 1245 | E67: Clyde Morris Blvd | F67: Robert Roundtree | G67: 3807 CLYDE MORRIS BLVD | H67: PORT ORANGE | I67: FL | J67: 32129 | K67: (386) 309-2621 | L67: All Plans PoR 1 mo. | M67: 10F-101 | N67: 1500 | AG67: 10 | AZ67: =VLOOKUP(Table7[[#This Row],[Vlookup Store '#]],'Kiosk Stickers'!A$4:$H$538,2,FALSE) -> 2 | BM67: =VLOOKUP(Table7[[#This Row],[Vlookup Store '#]],'Kiosk Stickers'!A$4:$H$538,3,FALSE) -> 0 | BO67: =VLOOKUP(Table7[[#This Row],[Vlookup Store '#]],'Kiosk Stickers'!A$4:$H$538,4,FALSE) -> 0 | BR67: =VLOOKUP(Table7[[#This Row],[Vlookup Store '#]],'Kiosk Stickers'!A$4:$H$538,5,FALSE) -> 0 | CP67: 2 | CW67: 10 | DE67: 1 | DF67: =SUM(CX67:DE67) -> 1
A68: FL-Orlando | B68: 812 | C68: 1249 | D68: 1249 | E68: Irwin | F68: Angel Mora | G68: 1164 W NEW HAVEN AVE | H68: MELBOURNE | I68: FL | J68: 32904 | K68: (321) 265-4007 | L68: All Plans PoR 1 mo. | M68: 10F-101 | N68: 1500 | AG68: 10 | AZ68: =VLOOKUP(Table7[[#This Row],[Vlookup Store '#]],'Kiosk Stickers'!A$4:$H$538,2,FALSE) -> 2 | BM68: =VLOOKUP(Table7[[#This Row],[Vlookup Store '#]],'Kiosk Stickers'!A$4:$H$538,3,FALSE) -> 0 | BO68: =VLOOKUP(Table7[[#This Row],[Vlookup Store '#]],'Kiosk Stickers'!A$4:$H$538,4,FALSE) -> 0 | BR68: =VLOOKUP(Table7[[#This Row],[Vlookup Store '#]],'Kiosk Stickers'!A$4:$H$538,5,FALSE) -> 0 | CP68: 2 | CW68: 10 | DE68: 1 | DF68: =SUM(CX68:DE68) -> 1
A69: FL-Orlando | B69: 812 | C69: 1254 | D69: 1254 | E69: Millenia | F69: David Gaus | G69: 4588 POWER CENTER LN | H69: ORLANDO | I69: FL | J69: 32839 | K69: (407) 848-1320 | L69: All Plans PoR 1 mo. | M69: 10F-101 | N69: 1500 | AG69: 10 | AZ69: =VLOOKUP(Table7[[#This Row],[Vlookup Store '#]],'Kiosk Stickers'!A$4:$H$538,2,FALSE) -> 0 | BM69: =VLOOKUP(Table7[[#This Row],[Vlookup Store '#]],'Kiosk Stickers'!A$4:$H$538,3,FALSE) -> 2 | BO69: =VLOOKUP(Table7[[#This Row],[Vlookup Store '#]],'Kiosk Stickers'!A$4:$H$538,4,FALSE) -> 0 | BR69: =VLOOKUP(Table7[[#This Row],[Vlookup Store '#]],'Kiosk Stickers'!A$4:$H$538,5,FALSE) -> 0 | CP69: 2 | CW69: 10 | DE69: 1 | DF69: =SUM(CX69:DE69) -> 1
A70: FL-Orlando | B70: 812 | C70: 1856 | D70: 1856 | E70: Belvedere | F70: Kevin Mckinnon | G70: 2505 PARR DR | H70: THE VILLAGES | I70: FL | J70: 32162 | K70: (352) 775-1805 | L70: All Plans PoR 1 mo. | M70: 10F-101 | N70: 1500 | AG70: 10 | AZ70: =VLOOKUP(Table7[[#This Row],[Vlookup Store '#]],'Kiosk Stickers'!A$4:$H$538,2,FALSE) -> 0 | BM70: =VLOOKUP(Table7[[#This Row],[Vlookup Store '#]],'Kiosk Stickers'!A$4:$H$538,3,FALSE) -> 2 | BO70: =VLOOKUP(Table7[[#This Row],[Vlookup Store '#]],'Kiosk Stickers'!A$4:$H$538,4,FALSE) -> 0 | BR70: =VLOOKUP(Table7[[#This Row],[Vlookup Store '#]],'Kiosk Stickers'!A$4:$H$538,5,FALSE) -> 0 | CP70: 2 | CW70: 10 | DE70: 1 | DF70: =SUM(CX70:DE70) -> 1
A71: FL-Southeast Florida | B71: 832 | C71: 1854 | D71: 1854 | E71: Hypoluxo | F71: Karlee Feldner | G71: 1833 HYPOLUXO RD | H71: LANTANA | I71: FL | J71: 33462 | K71: (561) 407-0035 | L71: All Plans PoR 1 mo. | M71: 10F-201 | P71: 1500 | AI71: 10 | AZ71: =VLOOKUP(Table7[[#This Row],[Vlookup Store '#]],'Kiosk Stickers'!A$4:$H$538,2,FALSE) -> 0 | BM71: =VLOOKUP(Table7[[#This Row],[Vlookup Store '#]],'Kiosk Stickers'!A$4:$H$538,3,FALSE) -> 1 | BO71: =VLOOKUP(Table7[[#This Row],[Vlookup Store '#]],'Kiosk Stickers'!A$4:$H$538,4,FALSE) -> 0 | BR71: =VLOOKUP(Table7[[#This Row],[Vlookup Store '#]],'Kiosk Stickers'!A$4:$H$538,5,FALSE) -> 0 | CP71: 2 | CW71: 10 | DE71: 1 | DF71: =SUM(CX71:DE71) -> 1
A72: FL-Southeast Florida | B72: 812 | C72: 1855 | D72: 1855 | E72: Goldenrod | F72: Dylan Sanchez | G72: 3775 NW FEDERAL HWY | H72: JENSEN BEACH | I72: FL | J72: 34957 | K72: (772) 208-3966 | L72: All Plans PoR 1 mo. | M72: 10F-201 | P72: 1500 | AI72: 10 | AZ72: =VLOOKUP(Table7[[#This Row],[Vlookup Store '#]],'Kiosk Stickers'!A$4:$H$538,2,FALSE) -> 2 | BM72: =VLOOKUP(Table7[[#This Row],[Vlookup Store '#]],'Kiosk Stickers'!A$4:$H$538,3,FALSE) -> 0 | BO72: =VLOOKUP(Table7[[#This Row],[Vlookup Store '#]],'Kiosk Stickers'!A$4:$H$538,4,FALSE) -> 0 | BR72: =VLOOKUP(Table7[[#This Row],[Vlookup Store '#]],'Kiosk Stickers'!A$4:$H$538,5,FALSE) -> 0 | CP72: 2 | CW72: 10 | DE72: 1 | DF72: =SUM(CX72:DE72) -> 1
A73: FL-Tampa | B73: 812 | C73: 0226 | D73: 226 | E73: North Dale Mabry | F73: Dennis Crumlich | G73: 8101 NORTH DALE MABRY | H73: TAMPA | I73: FL | J73: 33614 | K73: (813) 933-6661 | L73: All Plans PoR 1 mo. | M73: 10F-201 | P73: 1500 | AI73: 10 | AZ73: =VLOOKUP(Table7[[#This Row],[Vlookup Store '#]],'Kiosk Stickers'!A$4:$H$538,2,FALSE) -> 0 | BM73: =VLOOKUP(Table7[[#This Row],[Vlookup Store '#]],'Kiosk Stickers'!A$4:$H$538,3,FALSE) -> 0 | BO73: =VLOOKUP(Table7[[#This Row],[Vlookup Store '#]],'Kiosk Stickers'!A$4:$H$538,4,FALSE) -> 0 | BW73: =VLOOKUP(Table7[[#This Row],[Vlookup Store '#]],'Kiosk Stickers'!A$4:$H$538,5,FALSE) -> 1 | CP73: 2 | CW73: 10 | DE73: 1 | DF73: =SUM(CX73:DE73) -> 1
A74: FL-Tampa | B74: 812 | C74: 0273 | D74: 273 | E74: Hudson | F74: Skiler Woods | G74: 12611 US HIGHWAY 19 | H74: HUDSON | I74: FL | J74: 34667-1955 | K74: (727) 868-7130 | L74: All Plans PoR 1 mo. | M74: 10F-201 | P74: 1500 | AI74: 10 | AZ74: =VLOOKUP(Table7[[#This Row],[Vlookup Store '#]],'Kiosk Stickers'!A$4:$H$538,2,FALSE) -> 0 | BM74: =VLOOKUP(Table7[[#This Row],[Vlookup Store '#]],'Kiosk Stickers'!A$4:$H$538,3,FALSE) -> 0 | BO74: =VLOOKUP(Table7[[#This Row],[Vlookup Store '#]],'Kiosk Stickers'!A$4:$H$538,4,FALSE) -> 0 | BW74: =VLOOKUP(Table7[[#This Row],[Vlookup Store '#]],'Kiosk Stickers'!A$4:$H$538,5,FALSE) -> 0 | CG74: =VLOOKUP(Table7[[#This Row],[Vlookup Store '#]],'Kiosk Stickers'!A$4:$H$538,6,FALSE) -> 1 | CP74: 2 | CW74: 10 | DE74: 1 | DF74: =SUM(CX74:DE74) -> 1
A75: FL-Tampa | B75: 812 | C75: 0274 | D75: 274 | E75: Spring Hill | F75: Taylin McCormick | G75: 4330 COMMERCIAL WAY | H75: SPRING HILL | I75: FL | J75: 34606 | K75: (352) 597-5573 | L75: All Plans PoR 1 mo. | M75: 10F-201 | P75: 1500 | AI75: 10 | AZ75: =VLOOKUP(Table7[[#This Row],[Vlookup Store '#]],'Kiosk Stickers'!A$4:$H$538,2,FALSE) -> 0 | BM75: =VLOOKUP(Table7[[#This Row],[Vlookup Store '#]],'Kiosk Stickers'!A$4:$H$538,3,FALSE) -> 0 | BO75: =VLOOKUP(Table7[[#This Row],[Vlookup Store '#]],'Kiosk Stickers'!A$4:$H$538,4,FALSE) -> 1 | BW75: =VLOOKUP(Table7[[#This Row],[Vlookup Store '#]],'Kiosk Stickers'!A$4:$H$538,5,FALSE) -> 1 | CP75: 2 | CW75: 10 | DE75: 1 | DF75: =SUM(CX75:DE75) -> 1
A76: FL-Tampa | B76: 812 | C76: 1221 | D76: 1221 | E76: State Route 52 | F76: Taylor Masters | G76: 9215 STATE ROUTE 52 | H76: HUDSON | I76: FL | J76: 34669 | K76: (727) 214-3847 | L76: All Plans PoR 1 mo. | M76: 10F-201 | P76: 1500 | AI76: 10 | AZ76: =VLOOKUP(Table7[[#This Row],[Vlookup Store '#]],'Kiosk Stickers'!A$4:$H$538,2,FALSE) -> 0 | BM76: =VLOOKUP(Table7[[#This Row],[Vlookup Store '#]],'Kiosk Stickers'!A$4:$H$538,3,FALSE) -> 1 | BO76: =VLOOKUP(Table7[[#This Row],[Vlookup Store '#]],'Kiosk Stickers'!A$4:$H$538,4,FALSE) -> 0 | BR76: =VLOOKUP(Table7[[#This Row],[Vlookup Store '#]],'Kiosk Stickers'!A$4:$H$538,5,FALSE) -> 0 | CP76: 2 | CW76: 10 | DE76: 1 | DF76: =SUM(CX76:DE76) -> 1
A77: FL-Tampa | B77: 812 | C77: 1251 | D77: 1251 | E77: Park Ridge | F77: James Thomas | G77: 6801 PARK BLVD | H77: PINELLAS PARK | I77: FL | J77: 33781 | K77: (727) 620-5085 | L77: All Plans PoR 1 mo. | M77: 10F-201 | P77: 1500 | AI77: 10 | AZ77: =VLOOKUP(Table7[[#This Row],[Vlookup Store '#]],'Kiosk Stickers'!A$4:$H$538,2,FALSE) -> 1 | BM77: =VLOOKUP(Table7[[#This Row],[Vlookup Store '#]],'Kiosk Stickers'!A$4:$H$538,3,FALSE) -> 0 | BO77: =VLOOKUP(Table7[[#This Row],[Vlookup Store '#]],'Kiosk Stickers'!A$4:$H$538,4,FALSE) -> 0 | BR77: =VLOOKUP(Table7[[#This Row],[Vlookup Store '#]],'Kiosk Stickers'!A$4:$H$538,5,FALSE) -> 0 | CP77: 2 | CW77: 10 | DE77: 1 | DF77: =SUM(CX77:DE77) -> 1
A78: FL-Tampa | B78: 832 | C78: 1901 | D78: 1901 | E78: Hillsborough | F78: David Herster | G78: 12806 W HILLSBOROUGH AVE | H78: TAMPA | I78: FL | J78: 33635 | K78: (656) 444-0758 | L78: All Plans PoR 1 mo. | M78: 10F-201 | P78: 1500 | AI78: 10 | AZ78: =VLOOKUP(Table7[[#This Row],[Vlookup Store '#]],'Kiosk Stickers'!A$4:$H$538,2,FALSE) -> 0 | BM78: =VLOOKUP(Table7[[#This Row],[Vlookup Store '#]],'Kiosk Stickers'!A$4:$H$538,3,FALSE) -> 0 | BO78: =VLOOKUP(Table7[[#This Row],[Vlookup Store '#]],'Kiosk Stickers'!A$4:$H$538,4,FALSE) -> 0 | BR78: =VLOOKUP(Table7[[#This Row],[Vlookup Store '#]],'Kiosk Stickers'!A$4:$H$538,5,FALSE) -> 0 | CG78: =VLOOKUP(Table7[[#This Row],[Vlookup Store '#]],'Kiosk Stickers'!A$4:$H$538,6,FALSE) -> 1 | CP78: 2 | CW78: 10 | DE78: 1 | DF78: =SUM(CX78:DE78) -> 1
A79: FL-Tampa | B79: 832 | C79: 1902 | D79: 1902 | E79: Wesley Chapel | F79: Evan Hinzman | G79: 29891 WESLEY CHAPEL BLVD | H79: WESLEY CHAPEL | I79: FL | J79: 33543 | K79: (656) 202-4586 | L79: All Plans PoR 1 mo. | M79: 10F-201 | P79: 1500 | AI79: 10 | AZ79: =VLOOKUP(Table7[[#This Row],[Vlookup Store '#]],'Kiosk Stickers'!A$4:$H$538,2,FALSE) -> 0 | BM79: =VLOOKUP(Table7[[#This Row],[Vlookup Store '#]],'Kiosk Stickers'!A$4:$H$538,3,FALSE) -> 2 | BO79: =VLOOKUP(Table7[[#This Row],[Vlookup Store '#]],'Kiosk Stickers'!A$4:$H$538,4,FALSE) -> 0 | BR79: =VLOOKUP(Table7[[#This Row],[Vlookup Store '#]],'Kiosk Stickers'!A$4:$H$538,5,FALSE) -> 0 | CP79: 2 | CW79: 10 | DE79: 1 | DF79: =SUM(CX79:DE79) -> 1
A80: FL-Tampa | B80: 812 | C80: 2501 | D80: 2501 | E80: Zephyrhills | F80: William Sprinkle | G80: 6353 GALL BOULEVARD | H80: ZEPHYRHILLS | I80: FL | J80: 33542 | K80: (813) 670-2213 | L80: All Plans PoR 1 mo. | M80: 10F-201 | P80: 1500 | AI80: 10 | AZ80: =VLOOKUP(Table7[[#This Row],[Vlookup Store '#]],'Kiosk Stickers'!A$4:$H$538,2,FALSE) -> 1 | BF80: =VLOOKUP(Table7[[#This Row],[Vlookup Store '#]],'Kiosk Stickers'!A$4:$H$538,3,FALSE) -> 0 | BO80: =VLOOKUP(Table7[[#This Row],[Vlookup Store '#]],'Kiosk Stickers'!A$4:$H$538,4,FALSE) -> 0 | BR80: =VLOOKUP(Table7[[#This Row],[Vlookup Store '#]],'Kiosk Stickers'!A$4:$H$538,5,FALSE) -> 0 | CP80: 2 | CW80: 10 | DE80: 1 | DF80: =SUM(CX80:DE80) -> 1
A81: GA-Atlanta | B81: 813 | C81: 0264 | D81: 264 | E81: Hiram | F81: Alexis Strozier | G81: 5651 WENDY BAGWELL PKWY | H81: HIRAM | I81: GA | J81: 30141-7806 | K81: (770) 943-5967 | L81: $5, $10, $15 | M81: C01 | X81: 1500 | AQ81: 10 | AZ81: =VLOOKUP(Table7[[#This Row],[Vlookup Store '#]],'Kiosk Stickers'!A$4:$H$538,2,FALSE) -> 0 | BF81: =VLOOKUP(Table7[[#This Row],[Vlookup Store '#]],'Kiosk Stickers'!A$4:$H$538,3,FALSE) -> 0 | BO81: =VLOOKUP(Table7[[#This Row],[Vlookup Store '#]],'Kiosk Stickers'!A$4:$H$538,4,FALSE) -> 0 | BS81: =VLOOKUP(Table7[[#This Row],[Vlookup Store '#]],'Kiosk Stickers'!A$4:$H$538,5,FALSE) -> 1 | CK81: 2 | CT81: 10 | CZ81: 1 | DF81: =SUM(CX81:DE81) -> 1
A82: GA-Atlanta | B82: 813 | C82: 0270 | D82: 270 | E82: Peachtree | F82: Robert Feinburg | G82: 930 PEACHTREE PKWY | H82: CUMMING | I82: GA | J82: 30041-6823 | K82: (678) 771-8783 | L82: $5, $10, $15 | M82: C01 | X82: 1500 | AQ82: 10 | AZ82: =VLOOKUP(Table7[[#This Row],[Vlookup Store '#]],'Kiosk Stickers'!A$4:$H$538,2,FALSE) -> 0 | BF82: =VLOOKUP(Table7[[#This Row],[Vlookup Store '#]],'Kiosk Stickers'!A$4:$H$538,3,FALSE) -> 0 | BO82: =VLOOKUP(Table7[[#This Row],[Vlookup Store '#]],'Kiosk Stickers'!A$4:$H$538,4,FALSE) -> 0 | BS82: =VLOOKUP(Table7[[#This Row],[Vlookup Store '#]],'Kiosk Stickers'!A$4:$H$538,5,FALSE) -> 2 | CK82: 2 | CT82: 10 | CZ82: 1 | DF82: =SUM(CX82:DE82) -> 1
A83: IA-Cedar Rapids/Davenport | B83: 801 | C83: 1484 | D83: 1484 | E83: Kimberly Rd | F83: Elijah Miller | G83: 707 E KIMBERLY RD | H83: DAVENPORT | I83: IA | J83: 52807 | K83: (563) 265-3110 | L83: $9.99 all plans 1 mo. | M83: 8D-04 | Q83: 1500 | AJ83: 10 | AZ83: =VLOOKUP(Table7[[#This Row],[Vlookup Store '#]],'Kiosk Stickers'!A$4:$H$538,2,FALSE) -> 0 | BJ83: =VLOOKUP(Table7[[#This Row],[Vlookup Store '#]],'Kiosk Stickers'!A$4:$H$538,3,FALSE) -> 2 | BO83: =VLOOKUP(Table7[[#This Row],[Vlookup Store '#]],'Kiosk Stickers'!A$4:$H$538,4,FALSE) -> 0 | BR83: =VLOOKUP(Table7[[#This Row],[Vlookup Store '#]],'Kiosk Stickers'!A$4:$H$538,5,FALSE) -> 0 | CM83: 2 | CU83: 10 | DA83: 1 | DF83: =SUM(CX83:DE83) -> 1
A84: IA-Cedar Rapids/Davenport | B84: 801 | C84: 1723 | D84: 1723 | E84: Lakeview | F84: Sydney Rosebrough | G84: 4511 E 53RD STREET | H84: DAVENPORT | I84: IA | J84: 52807 | K84: (563) 306-2633 | L84: $9.99 all plans 1 mo. | M84: 8D-04 | Q84: 1500 | AJ84: 10 | AZ84: =VLOOKUP(Table7[[#This Row],[Vlookup Store '#]],'Kiosk Stickers'!A$4:$H$538,2,FALSE) -> 0 | BJ84: =VLOOKUP(Table7[[#This Row],[Vlookup Store '#]],'Kiosk Stickers'!A$4:$H$538,3,FALSE) -> 1 | BO84: =VLOOKUP(Table7[[#This Row],[Vlookup Store '#]],'Kiosk Stickers'!A$4:$H$538,4,FALSE) -> 0 | BR84: =VLOOKUP(Table7[[#This Row],[Vlookup Store '#]],'Kiosk Stickers'!A$4:$H$538,5,FALSE) -> 0 | CM84: 2 | CU84: 10 | DA84: 1 | DF84: =SUM(CX84:DE84) -> 1
A85: IA-Des Moines | B85: 801 | C85: 0730 | D85: 730 | E85: 14th Street | F85: Thomas Duncan | G85: 3400 SE 14TH ST | H85: DES MOINES | I85: IA | J85: 50320 | K85: (515) 974-5062 | L85: $9.99 all plans 1 mo. | M85: D01 | Z85: 1500 | AS85: 10 | AZ85: =VLOOKUP(Table7[[#This Row],[Vlookup Store '#]],'Kiosk Stickers'!A$4:$H$538,2,FALSE) -> 0 | BI85: =VLOOKUP(Table7[[#This Row],[Vlookup Store '#]],'Kiosk Stickers'!A$4:$H$538,3,FALSE) -> 2 | BO85: =VLOOKUP(Table7[[#This Row],[Vlookup Store '#]],'Kiosk Stickers'!A$4:$H$538,4,FALSE) -> 0 | BR85: =VLOOKUP(Table7[[#This Row],[Vlookup Store '#]],'Kiosk Stickers'!A$4:$H$538,5,FALSE) -> 0 | CL85: 2 | CU85: 10 | DB85: 1 | DF85: =SUM(CX85:DE85) -> 1
A86: IA-Des Moines | B86: 801 | C86: 0731 | D86: 731 | E86: North Merle Hay | F86: Marina Song | G86: 4850 MERLE HAY RD | H86: URBANDALE | I86: IA | J86: 50322 | K86: (515) 254-2593 | L86: $9.99 all plans 1 mo. | M86: D01 | Z86: 1500 | AS86: 10 | AZ86: =VLOOKUP(Table7[[#This Row],[Vlookup Store '#]],'Kiosk Stickers'!A$4:$H$538,2,FALSE) -> 0 | BI86: =VLOOKUP(Table7[[#This Row],[Vlookup Store '#]],'Kiosk Stickers'!A$4:$H$538,3,FALSE) -> 2 | BO86: =VLOOKUP(Table7[[#This Row],[Vlookup Store '#]],'Kiosk Stickers'!A$4:$H$538,4,FALSE) -> 0 | BR86: =VLOOKUP(Table7[[#This Row],[Vlookup Store '#]],'Kiosk Stickers'!A$4:$H$538,5,FALSE) -> 0 | CL86: 2 | CU86: 10 | DB86: 1 | DF86: =SUM(CX86:DE86) -> 1
A87: IA-Des Moines | B87: 801 | C87: 0733 | D87: 733 | E87: Grimes | F87: Neris Martinez | G87: 1901 SE 11TH ST | H87: GRIMES | I87: IA | J87: 50111 | K87: (515) 325-1712 | L87: $9.99 all plans 1 mo. | M87: D01 | Z87: 1500 | AS87: 10 | AZ87: =VLOOKUP(Table7[[#This Row],[Vlookup Store '#]],'Kiosk Stickers'!A$4:$H$538,2,FALSE) -> 0 | BI87: =VLOOKUP(Table7[[#This Row],[Vlookup Store '#]],'Kiosk Stickers'!A$4:$H$538,3,FALSE) -> 0 | BP87: =VLOOKUP(Table7[[#This Row],[Vlookup Store '#]],'Kiosk Stickers'!A$4:$H$538,4,FALSE) -> 2 | BR87: =VLOOKUP(Table7[[#This Row],[Vlookup Store '#]],'Kiosk Stickers'!A$4:$H$538,5,FALSE) -> 0 | CL87: 2 | CU87: 10 | DB87: 1 | DF87: =SUM(CX87:DE87) -> 1
A88: IA-Des Moines | B88: 801 | C88: 0734 | D88: 734 | E88: Ankeny | F88: Bahari Afare | G88: 109 S ANKENY BLVD | H88: ANKENY | I88: IA | J88: 50023 | K88: (515) 325-0478 | L88: $9.99 all plans 1 mo. | M88: D01 | Z88: 1500 | AS88: 10 | AZ88: =VLOOKUP(Table7[[#This Row],[Vlookup Store '#]],'Kiosk Stickers'!A$4:$H$538,2,FALSE) -> 0 | BI88: =VLOOKUP(Table7[[#This Row],[Vlookup Store '#]],'Kiosk Stickers'!A$4:$H$538,3,FALSE) -> 2 | BO88: =VLOOKUP(Table7[[#This Row],[Vlookup Store '#]],'Kiosk Stickers'!A$4:$H$538,4,FALSE) -> 0 | BR88: =VLOOKUP(Table7[[#This Row],[Vlookup Store '#]],'Kiosk Stickers'!A$4:$H$538,5,FALSE) -> 0 | CL88: 2 | CU88: 10 | DB88: 1 | DF88: =SUM(CX88:DE88) -> 1
A89: IA-Des Moines | B89: 801 | C89: 1721 | D89: 1721 | E89: 12th Ave | F89: Shoalie Niebauer | G89: 5440 E UNIVERSITY AVE | H89: PLEASANT HILL | I89: IA | J89: 50327 | K89: (515) 957-7218 | L89: $9.99 all plans 1 mo. | M89: D01 | Z89: 1500 | AS89: 10 | AZ89: =VLOOKUP(Table7[[#This Row],[Vlookup Store '#]],'Kiosk Stickers'!A$4:$H$538,2,FALSE) -> 0 | BI89: =VLOOKUP(Table7[[#This Row],[Vlookup Store '#]],'Kiosk Stickers'!A$4:$H$538,3,FALSE) -> 1 | BO89: =VLOOKUP(Table7[[#This Row],[Vlookup Store '#]],'Kiosk Stickers'!A$4:$H$538,4,FALSE) -> 0 | BR89: =VLOOKUP(Table7[[#This Row],[Vlookup Store '#]],'Kiosk Stickers'!A$4:$H$538,5,FALSE) -> 0 | CL89: 2 | CU89: 10 | DB89: 1 | DF89: =SUM(CX89:DE89) -> 1
A90: IA-Des Moines | B90: 801 | C90: 1722 | D90: 1722 | E90: Altoona | F90: Tajanae Miller | G90: 3590 PRAIRIE FIRE NW | H90: ALTOONA | I90: IA | J90: 50009 | K90: (515) 978-8988 | L90: $9.99 all plans 1 mo. | M90: D01 | Z90: 1500 | AS90: 10 | AZ90: =VLOOKUP(Table7[[#This Row],[Vlookup Store '#]],'Kiosk Stickers'!A$4:$H$538,2,FALSE) -> 0 | BI90: =VLOOKUP(Table7[[#This Row],[Vlookup Store '#]],'Kiosk Stickers'!A$4:$H$538,3,FALSE) -> 2 | BO90: =VLOOKUP(Table7[[#This Row],[Vlookup Store '#]],'Kiosk Stickers'!A$4:$H$538,4,FALSE) -> 0 | BR90: =VLOOKUP(Table7[[#This Row],[Vlookup Store '#]],'Kiosk Stickers'!A$4:$H$538,5,FALSE) -> 0 | CL90: 2 | CU90: 10 | DB90: 1 | DF90: =SUM(CX90:DE90) -> 1
A91: IA-Des Moines | B91: 801 | C91: 1724 | D91: 1724 | E91: Hickman | F91: Savhannah White | G91: 555 E HICKMAN RD | H91: WAUKEE | I91: IA | J91: 50263 | K91: (515) 207-6522 | L91: $9.99 all plans 1 mo. | M91: D01 | Z91: 1500 | AS91: 10 | AZ91: =VLOOKUP(Table7[[#This Row],[Vlookup Store '#]],'Kiosk Stickers'!A$4:$H$538,2,FALSE) -> 0 | BI91: =VLOOKUP(Table7[[#This Row],[Vlookup Store '#]],'Kiosk Stickers'!A$4:$H$538,3,FALSE) -> 2 | BO91: =VLOOKUP(Table7[[#This Row],[Vlookup Store '#]],'Kiosk Stickers'!A$4:$H$538,4,FALSE) -> 0 | BR91: =VLOOKUP(Table7[[#This Row],[Vlookup Store '#]],'Kiosk Stickers'!A$4:$H$538,5,FALSE) -> 0 | CL91: 2 | CU91: 10 | DB91: 1 | DF91: =SUM(CX91:DE91) -> 1
A92: ID-Boise | B92: 800 | C92: 0501 | D92: 501 | E92: Fairview | F92: Mikel Hart | G92: 5950 FAIRVIEW AVENUE | H92: BOISE | I92: ID | J92: 83704 | K92: (208) 322-5950 | L92: $9.99 all plans 1 mo. | M92: D03 | AB92: 1500 | AU92: 10 | AZ92: =VLOOKUP(Table7[[#This Row],[Vlookup Store '#]],'Kiosk Stickers'!A$4:$H$538,2,FALSE) -> 0 | BI92: =VLOOKUP(Table7[[#This Row],[Vlookup Store '#]],'Kiosk Stickers'!A$4:$H$538,3,FALSE) -> 2 | BO92: =VLOOKUP(Table7[[#This Row],[Vlookup Store '#]],'Kiosk Stickers'!A$4:$H$538,4,FALSE) -> 0 | BR92: =VLOOKUP(Table7[[#This Row],[Vlookup Store '#]],'Kiosk Stickers'!A$4:$H$538,5,FALSE) -> 0 | CL92: 2 | CU92: 10 | DB92: 1 | DF92: =SUM(CX92:DE92) -> 1
A93: ID-Boise | B93: 800 | C93: 0506 | D93: 506 | E93: Meridian | F93: Hector Hinojosa | G93: 3296 E PINE AVE | H93: MERIDIAN | I93: ID | J93: 83642 | K93: (208) 895-8077 | L93: $9.99 all plans 1 mo. | M93: D03 | AB93: 1500 | AU93: 10 | AZ93: =VLOOKUP(Table7[[#This Row],[Vlookup Store '#]],'Kiosk Stickers'!A$4:$H$538,2,FALSE) -> 0 | BI93: =VLOOKUP(Table7[[#This Row],[Vlookup Store '#]],'Kiosk Stickers'!A$4:$H$538,3,FALSE) -> 1 | BO93: =VLOOKUP(Table7[[#This Row],[Vlookup Store '#]],'Kiosk Stickers'!A$4:$H$538,4,FALSE) -> 0 | BR93: =VLOOKUP(Table7[[#This Row],[Vlookup Store '#]],'Kiosk Stickers'!A$4:$H$538,5,FALSE) -> 0 | CL93: 2 | CU93: 10 | DB93: 1 | DF93: =SUM(CX93:DE93) -> 1
A94: ID-Boise | B94: 800 | C94: 1509 | D94: 1509 | E94: Milano | F94: Ashley Marten | G94: 4891 N CORTONA WAY | H94: MERIDIAN | I94: ID | J94: 83646 | K94: (208) 202-5469 | L94: $9.99 all plans 1 mo. | M94: D03 | AB94: 1500 | AU94: 10 | AZ94: =VLOOKUP(Table7[[#This Row],[Vlookup Store '#]],'Kiosk Stickers'!A$4:$H$538,2,FALSE) -> 0 | BI94: =VLOOKUP(Table7[[#This Row],[Vlookup Store '#]],'Kiosk Stickers'!A$4:$H$538,3,FALSE) -> 2 | BO94: =VLOOKUP(Table7[[#This Row],[Vlookup Store '#]],'Kiosk Stickers'!A$4:$H$538,4,FALSE) -> 0 | BR94: =VLOOKUP(Table7[[#This Row],[Vlookup Store '#]],'Kiosk Stickers'!A$4:$H$538,5,FALSE) -> 0 | CL94: 2 | CU94: 10 | DB94: 1 | DF94: =SUM(CX94:DE94) -> 1
A95: ID-Boise | B95: 800 | C95: 1510 | D95: 1510 | E95: Progress Ave | F95: Shane Ford | G95: 675 S PROGRESS AVE | H95: MERIDIAN | I95: ID | J95: 83642 | K95: (208) 297-3240 | L95: $9.99 all plans 1 mo. | M95: D03 | AB95: 1500 | AU95: 10 | BD95: =VLOOKUP(Table7[[#This Row],[Vlookup Store '#]],'Kiosk Stickers'!A$4:$H$538,2,FALSE) -> 1 | BF95: =VLOOKUP(Table7[[#This Row],[Vlookup Store '#]],'Kiosk Stickers'!A$4:$H$538,3,FALSE) -> 0 | BO95: =VLOOKUP(Table7[[#This Row],[Vlookup Store '#]],'Kiosk Stickers'!A$4:$H$538,4,FALSE) -> 0 | BR95: =VLOOKUP(Table7[[#This Row],[Vlookup Store '#]],'Kiosk Stickers'!A$4:$H$538,5,FALSE) -> 0 | CL95: 2 | CU95: 10 | DB95: 1 | DF95: =SUM(CX95:DE95) -> 1
A96: MD-Baltimore | B96: 801 | C96: 0652 | D96: 652 | E96: Severna | F96: Joseph Green | G96: 8562 VETERANS HIGHWAY | H96: MILLERSVILLE | I96: MD | J96: 21108 | K96: (410) 729-9274 | L96: 50% off all plan 1 mo. | M96: E07 | AF96: 1500 | AY96: 10 | AZ96: =VLOOKUP(Table7[[#This Row],[Vlookup Store '#]],'Kiosk Stickers'!A$4:$H$538,2,FALSE) -> 0 | BK96: =VLOOKUP(Table7[[#This Row],[Vlookup Store '#]],'Kiosk Stickers'!A$4:$H$538,3,FALSE) -> 2 | BO96: =VLOOKUP(Table7[[#This Row],[Vlookup Store '#]],'Kiosk Stickers'!A$4:$H$538,4,FALSE) -> 0 | BR96: =VLOOKUP(Table7[[#This Row],[Vlookup Store '#]],'Kiosk Stickers'!A$4:$H$538,5,FALSE) -> 0 | CN96: 2 | CV96: 10 | DB96: 1 | DF96: =SUM(CX96:DE96) -> 1
A97: MI-Detroit | B97: 801 | C97: 1474 | D97: 1474 | E97: Ford Rd | F97: Kaitlin Cole | G97: 2104 HAGGERTY ROAD N | H97: CANTON | I97: MI | J97: 48187 | K97: (734) 238-3088 | L97: All Plans PoR 1 mo. | M97: 10F-104 | O97: 1500 | AH97: 10 | AZ97: =VLOOKUP(Table7[[#This Row],[Vlookup Store '#]],'Kiosk Stickers'!A$4:$H$538,2,FALSE) -> 2 | BF97: =VLOOKUP(Table7[[#This Row],[Vlookup Store '#]],'Kiosk Stickers'!A$4:$H$538,3,FALSE) -> 0 | BO97: =VLOOKUP(Table7[[#This Row],[Vlookup Store '#]],'Kiosk Stickers'!A$4:$H$538,4,FALSE) -> 0 | BR97: =VLOOKUP(Table7[[#This Row],[Vlookup Store '#]],'Kiosk Stickers'!A$4:$H$538,5,FALSE) -> 0 | CP97: 2 | CW97: 10 | DE97: 1 | DF97: =SUM(CX97:DE97) -> 1
A98: MI-Detroit | B98: 810 | C98: 1495 | D98: 1495 | E98: Latson | F98: Travis Adle | G98: 1015 S LATSON RD | H98: HOWELL | I98: MI | J98: 48843 | K98: (517) 225-6675 | L98: All Plans PoR 1 mo. | M98: 10F-101 | N98: 1500 | AG98: 10 | AZ98: 1 | CP98: 2 | CW98: 10 | DE98: 1 | DF98: =SUM(CX98:DE98) -> 1
A99: MI-Detroit | B99: 810 | C99: 2537 | D99: 2537 | E99: New Baltimore | F99: Chris Gallup | G99: 29300 23 MILE RD | H99: NEW BALTIMORE | I99: MI | J99: 48047 | K99: (586) 210-6765 | L99: All Plans PoR 1 mo. | M99: 10F-104 | O99: 1500 | AH99: 10 | AZ99: =VLOOKUP(Table7[[#This Row],[Vlookup Store '#]],'Kiosk Stickers'!A$4:$H$538,2,FALSE) -> 1 | BF99: =VLOOKUP(Table7[[#This Row],[Vlookup Store '#]],'Kiosk Stickers'!A$4:$H$538,3,FALSE) -> 0 | BO99: =VLOOKUP(Table7[[#This Row],[Vlookup Store '#]],'Kiosk Stickers'!A$4:$H$538,4,FALSE) -> 0 | BR99: =VLOOKUP(Table7[[#This Row],[Vlookup Store '#]],'Kiosk Stickers'!A$4:$H$538,5,FALSE) -> 0 | CP99: 2 | CW99: 10 | DE99: 1 | DF99: =SUM(CX99:DE99) -> 1
A100: MI-Detroit | B100: 810 | C100: 2538 | D100: 2538 | E100: Clarkston | F100: Sara Kangas | G100: 6440 DIXIE HWY | H100: CLARKSTON | I100: MI | J100: 48346 | K100: (248) 605-0440 | L100: All Plans PoR 1 mo. | M100: 10F-104 | O100: 1500 | AH100: 10 | AZ100: =VLOOKUP(Table7[[#This Row],[Vlookup Store '#]],'Kiosk Stickers'!A$4:$H$538,2,FALSE) -> 1 | BF100: =VLOOKUP(Table7[[#This Row],[Vlookup Store '#]],'Kiosk Stickers'!A$4:$H$538,3,FALSE) -> 0 | BO100: =VLOOKUP(Table7[[#This Row],[Vlookup Store '#]],'Kiosk Stickers'!A$4:$H$538,4,FALSE) -> 0 | BR100: =VLOOKUP(Table7[[#This Row],[Vlookup Store '#]],'Kiosk Stickers'!A$4:$H$538,5,FALSE) -> 0 | CP100: 2 | CW100: 10 | DE100: 1 | DF100: =SUM(CX100:DE100) -> 1
...

Sheet Scratch
B2: {=_xlfn.UNIQUE(A3:A61)} -> D01 | C2: 10F-101 | D2: 10F
A3: D01 | B3: 10F-101 | C3: 10F-104 | D3: 8F | F3: D01 | G3: {=_xlfn.UNIQUE(F3:F88)} -> D01 | H3: 10F-101 | J3: A
A4: D01 | B4: B05 | C4: 10F-201 | D4: A | F4: D01 | G4: B05 | H4: 10F-201 | J4: B
A5: D01 | B5: 10F-201 | C5: 8F-304 | D5: B | F5: D01 | G5: B06 | H5: 8D-04 | J5: C
A6: D01 | B6: D03 | C6: A01 | D6: D | F6: B05 | G6: 10F-201 | H6: 8D-05 | J6: D | L6: E01 | M6: {=_xlfn.UNIQUE(L6:L33)} -> E01 | N6: 10F-101 | O6: B
A7: D01 | B7: 10F-104 | C7: B05 | D7: E | F7: B05 | G7: 10F-101 | H7: 8F-304 | J7: 8D | L7: E01 | M7: 10F-201 | N7: 10F-201 | O7: C | Q7: E01 | R7: {=_xlfn.UNIQUE(Q7:Q27)} -> E01 | S7: 10F-101 | T7: A | V7: A01 | W7: A | Y7: A | Z7: $10 all plans 3 mos.
A8: D01 | B8: A01 | C8: D01 | F8: B06 | G8: 8D-04 | H8: A01 | J8: E | L8: E01 | M8: C01 | N8: 8D-05 | O8: D | Q8: D01 | R8: D01 | S8: 10F-201 | T8: B | V8: G | W8: B | Y8: B | Z8: $15 off all plans 1 mo.
A9: D01 | B9: D02 | C9: D02 | F9: B05 | G9: D03 | H9: B01 | J9: 8F | L9: E01 | M9: D01 | N9: 8F-304 | O9: 8D | Q9: D01 | R9: B06 | S9: 8D-05 | T9: D | V9: B01 | W9: C | Y9: C | Z9: $5, $10, $15
A10: D01 | B10: 8F-304 | C10: D03 | F10: 10F-201 | G10: E07 | H10: B05 | J10: 10F | L10: E01 | M10: 8F-304 | N10: B01 | O10: E | Q10: D01 | R10: 10F-101 | S10: 8F-304 | T10: 8D | V10: B05 | W10: D | Y10: D | Z10: $9.99 all plans 1 mo.
A11: D01 | B11: E01 | C11: D06 | F11: 10F-201 | G11: C01 | H11: B06 | J11: G | L11: E01 | M11: 8D-05 | N11: C01 | O11: 8F | Q11: D01 | R11: 10F-201 | S11: A01 | T11: E | V11: B06 | W11: 8D | Y11: E | Z11: 50% off all plan 1 mo.
A12: D01 | B12: D06 | C12: E01 | F12: 10F-201 | G12: D02 | H12: C01 | L12: E01 | M12: B01 | N12: C04 | O12: 10F | Q12: B06 | R12: D02 | S12: B06 | T12: 8F | V12: C01 | W12: E | Y12: F | Z12: All Plans PoR 1 mo.
A13: D01 | B13: E03 | C13: E03 | F13: 10F-201 | G13: 8F-304 | H13: D01 | L13: E01 | M13: 10F-101 | N13: D01 | O13: E | Q13: 10F-101 | R13: 8F-304 | S13: D01 | T13: 10F | V13: C04 | W13: 8F
A14: D01 | F14: 10F-201 | G14: 8D-05 | H14: D02 | L14: E01 | M14: C04 | N14: E01 | O14: G | Q14: 10F-201 | R14: 8D-05 | S14: D02 | T14: G | V14: D01 | W14: 10F
A15: 10F-101 | F15: 10F-201 | G15: E01 | H15: D03 | L15: 10F-201 | M15: E03 | N15: E03 | Q15: 10F-201 | R15: G | S15: E01 | V15: 8D-04 | W15: G
A16: 10F-101 | F16: 10F-101 | G16: B01 | H16: E01 | L16: 10F-201 | M16: G | N16: G | Q16: D02 | R16: A01 | S16: G | V16: D02
A17: D01 | F17: 10F-101 | G17: E03 | H17: E03 | L17: C01 | Q17: D02 | V17: D06
A18: D01 | F18: 10F-101 | G18: A01 | H18: E07 | L18: C01 | Q18: D02 | V18: 8D-05
A19: D01 | F19: 10F-101 | G19: G | H19: G | L19: D01 | Q19: 8F-304 | V19: D03
A20: B05 | F20: 10F-101 | L20: 8F-304 | Q20: 8F-304 | V20: E01
A21: B05 | F21: 10F-101 | L21: 8F-304 | Q21: 8D-05 | V21: E07
A22: B05 | F22: 10F-101 | L22: 8F-304 | Q22: E01 | V22: E03
A23: B05 | F23: 10F-101 | L23: 8D-05 | Q23: 10F-101 | V23: 10F-101
A24: 10F-101 | F24: 10F-101 | L24: 8D-05 | Q24: 10F-101 | V24: 8F-304
A25: 10F-101 | F25: 10F-101 | L25: E01 | Q25: G | V25: 10F-104
A26: 10F-201 | F26: 10F-101 | L26: E01 | Q26: G | V26: 10F-201
A27: 10F-201 | F27: 10F-101 | L27: B01 | Q27: A01
A28: 10F-201 | F28: 10F-201 | L28: 10F-101
A29: D03 | F29: 10F-201 | L29: D01
A30: 10F-104 | F30: 10F-201 | L30: C04
A31: 10F-101 | F31: 8D-04 | L31: E03
A32: 10F-104 | F32: 8D-04 | L32: E03
A33: 10F-104 | F33: D01 | L33: G
A34: 10F-104 | F34: D01
A35: 10F-104 | F35: D01
A36: A01 | F36: D01
A37: 10F-101 | F37: D01
A38: D02 | F38: D01
A39: D02 | F39: D03
A40: D02 | F40: D03
A41: D02 | F41: D03
A42: 8F-304 | F42: E07
A43: E01 | F43: C01
A44: E01 | F44: C01
A45: E01 | F45: C01
... A61: A01 | F61: B01
F62: 10F-101
F63: 10F-101
F64: 10F-101
F65: 10F-101
F66: 10F-101
F67: 10F-101
F68: 10F-101
F69: 10F-101
F70: D01
F71: E03
F72: E03
F73: E03
... F88: A01

Sheet Kiosk Stickers
A1: KIOSK STICKER SIZES BY STORE | E1: Source: | F1: NBB4 Shipping Key_ Kiosks & Gate Arm Banners - Directions.xlsx
A3: Store Number | B3: Mister Kiosk | C3: Gen 2 Pegasus | D3: Gen 1 Pegasus | E3: DRB | F3: Windscreen | G3: Need windscreen? (0=yes) | H3: Sum of Kiosks | J3: Store Number | K3: Mister Kiosk | L3: Gen 2 Pegasus | M3: Gen 1 Pegasus | N3: DRB | O3: Windscreen | P3: Need windscreen? (0=yes) | Q3: Sum of Kiosks
A4: 1 | B4: 0 | C4: 0 | D4: 0 | E4: 1 | F4: 0 | G4: 1 | H4: 1 | J4: 1 | K4: 0 | L4: 0 | M4: 0 | N4: 1 | O4: 0 | P4: 1 | Q4: 1
A5: 2 | B5: 0 | C5: 2 | D5: 0 | E5: 0 | F5: 0 | G5: 2 | H5: 2 | J5: 2 | K5: 0 | L5: 2 | M5: 0 | N5: 0 | O5: 0 | P5: 2 | Q5: 2
A6: 3 | B6: 0 | C6: 2 | D6: 0 | E6: 0 | F6: 0 | G6: 2 | H6: 2 | J6: 3 | K6: 0 | L6: 2 | M6: 0 | N6: 0 | O6: 0 | P6: 2 | Q6: 2
A7: 4 | B7: 0 | C7: 2 | D7: 0 | E7: 0 | F7: 0 | G7: 2 | H7: 2 | J7: 4 | K7: 0 | L7: 2 | M7: 0 | N7: 0 | O7: 0 | P7: 2 | Q7: 2
A8: 5 | B8: 0 | C8: 1 | D8: 0 | E8: 0 | F8: 0 | G8: 1 | H8: 1 | J8: 5 | K8: 0 | L8: 1 | M8: 0 | N8: 0 | O8: 0 | P8: 1 | Q8: 1
A9: 6 | B9: 0 | C9: 0 | D9: 0 | E9: 1 | F9: 0 | G9: 1 | H9: 1 | J9: 6 | K9: 0 | L9: 0 | M9: 0 | N9: 1 | O9: 0 | P9: 1 | Q9: 1
A10: 7 | B10: 0 | C10: 1 | D10: 0 | E10: 0 | F10: 0 | G10: 1 | H10: 1 | J10: 7 | K10: 0 | L10: 1 | M10: 0 | N10: 0 | O10: 0 | P10: 1 | Q10: 1
A11: 8 | B11: 0 | C11: 0 | D11: 0 | E11: 1 | F11: 0 | G11: 1 | H11: 1 | J11: 8 | K11: 0 | L11: 0 | M11: 0 | N11: 1 | O11: 0 | P11: 1 | Q11: 1
A12: 9 | B12: 0 | C12: 2 | D12: 0 | E12: 0 | F12: 0 | G12: 2 | H12: 2 | J12: 9 | K12: 0 | L12: 2 | M12: 0 | N12: 0 | O12: 0 | P12: 2 | Q12: 2
A13: 10 | B13: 0 | C13: 2 | D13: 0 | E13: 0 | F13: 0 | G13: 2 | H13: 2 | J13: 10 | K13: 0 | L13: 2 | M13: 0 | N13: 0 | O13: 0 | P13: 2 | Q13: 2
A14: 11 | B14: 0 | C14: 2 | D14: 0 | E14: 0 | F14: 0 | G14: 2 | H14: 2 | J14: 11 | K14: 0 | L14: 2 | M14: 0 | N14: 0 | O14: 0 | P14: 2 | Q14: 2
A15: 12 | B15: 0 | C15: 1 | D15: 0 | E15: 0 | F15: 0 | G15: 1 | H15: 1 | J15: 12 | K15: 0 | L15: 1 | M15: 0 | N15: 0 | O15: 0 | P15: 1 | Q15: 1
... A65: 235 | B65: 0 | C65: 0 | D65: 0 | E65: 0 | F65: 1 | G65: 0 | H65: 0 | J65: 235 | K65: 0 | L65: 0 | M65: 0 | N65: 0 | O65: 1 | P65: 0 | Q65: 0
A66: 236 | B66: 0 | C66: 2 | D66: 0 | E66: 0 | F66: 0 | G66: 3 | H66: 2 | J66: 236 | K66: 0 | L66: 2 | M66: 0 | N66: 0 | O66: 0 | P66: 3 | Q66: =SUM(K66:O66) -> 2
A67: 241 | B67: 0 | C67: 2 | D67: 0 | E67: 0 | F67: 0 | G67: 2 | H67: 2 | J67: 241 | K67: 0 | L67: 2 | M67: 0 | N67: 0 | O67: 0 | P67: 2 | Q67: 2
A68: 242 | B68: 0 | C68: 1 | D68: 0 | E68: 0 | F68: 0 | G68: 1 | H68: 1 | J68: 242 | K68: 0 | L68: 1 | M68: 0 | N68: 0 | O68: 0 | P68: 1 | Q68: 1
A69: 243 | B69: 0 | C69: 1 | D69: 0 | E69: 0 | F69: 0 | G69: 1 | H69: 1 | J69: 243 | K69: 0 | L69: 1 | M69: 0 | N69: 0 | O69: 0 | P69: 1 | Q69: 1
A70: 246 | B70: 0 | C70: 2 | D70: 0 | E70: 0 | F70: 0 | G70: 3 | H70: 2 | J70: 246 | K70: 0 | L70: 2 | M70: 0 | N70: 0 | O70: 0 | P70: 3 | Q70: =SUM(K70:O70) -> 2
A71: 247 | B71: 0 | C71: 1 | D71: 0 | E71: 0 | F71: 0 | G71: 1 | H71: 1 | J71: 247 | K71: 0 | L71: 1 | M71: 0 | N71: 0 | O71: 0 | P71: 1 | Q71: 1
A72: 248 | B72: 0 | C72: 0 | D72: 0 | E72: 0 | F72: 1 | G72: 0 | H72: 0 | J72: 248 | K72: 0 | L72: 0 | M72: 0 | N72: 0 | O72: 1 | P72: 0 | Q72: 0
A73: 249 | B73: 0 | C73: 1 | D73: 0 | E73: 0 | F73: 0 | G73: 1 | H73: 1 | J73: 249 | K73: 0 | L73: 1 | M73: 0 | N73: 0 | O73: 0 | P73: 1 | Q73: 1
A74: 252 | B74: 0 | C74: 1 | D74: 0 | E74: 0 | F74: 0 | G74: 1 | H74: 1 | J74: 252 | K74: 0 | L74: 1 | M74: 0 | N74: 0 | O74: 0 | P74: 1 | Q74: 1
A75: 253 | B75: 0 | C75: 2 | D75: 0 | E75: 0 | F75: 0 | G75: 2 | H75: 2 | J75: 253 | K75: 0 | L75: 2 | M75: 0 | N75: 0 | O75: 0 | P75: 2 | Q75: 2
A76: 254 | B76: 0 | C76: 1 | D76: 0 | E76: 0 | F76: 0 | G76: 1 | H76: 1 | J76: 254 | K76: 0 | L76: 1 | M76: 0 | N76: 0 | O76: 0 | P76: 1 | Q76: 1
A77: 255 | B77: 0 | C77: 1 | D77: 0 | E77: 0 | F77: 0 | G77: 1 | H77: 1 | J77: 255 | K77: 0 | L77: 1 | M77: 0 | N77: 0 | O77: 0 | P77: 1 | Q77: 1
A78: 256 | B78: 0 | C78: 0 | D78: 0 | E78: 0 | F78: 1 | G78: 0 | H78: 0 | J78: 256 | K78: 0 | L78: 0 | M78: 0 | N78: 0 | O78: 1 | P78: 0 | Q78: 0
A79: 257 | B79: 0 | C79: 0 | D79: 0 | E79: 0 | F79: 1 | G79: 0 | H79: 0 | J79: 257 | K79: 0 | L79: 0 | M79: 0 | N79: 0 | O79: 1 | P79: 0 | Q79: 0
A80: 258 | B80: 2 | C80: 0 | D80: 0 | E80: 0 | F80: 0 | G80: 4 | H80: 2 | J80: 258 | K80: 2 | L80: 0 | M80: 0 | N80: 0 | O80: 0 | P80: 4 | Q80: =SUM(K80:O80) -> 2
A81: 261 | B81: 0 | C81: 1 | D81: 0 | E81: 1 | F81: 0 | G81: 2 | H81: 2 | J81: 261 | K81: 0 | L81: 1 | M81: 0 | N81: 1 | O81: 0 | P81: 2 | Q81: 2
A82: 262 | B82: 0 | C82: 0 | D82: 0 | E82: 2 | F82: 0 | G82: 2 | H82: 2 | J82: 262 | K82: 0 | L82: 0 | M82: 0 | N82: 2 | O82: 0 | P82: 2 | Q82: 2
A83: 263 | B83: 0 | C83: 0 | D83: 0 | E83: 1 | F83: 0 | G83: 1 | H83: 1 | J83: 263 | K83: 0 | L83: 0 | M83: 0 | N83: 1 | O83: 0 | P83: 1 | Q83: 1
A84: 264 | B84: 0 | C84: 0 | D84: 0 | E84: 1 | F84: 0 | G84: 1 | H84: 1 | J84: 264 | K84: 0 | L84: 0 | M84: 0 | N84: 1 | O84: 0 | P84: 1 | Q84: 1
A85: 265 | B85: 0 | C85: 2 | D85: 0 | E85: 0 | F85: 0 | G85: 3 | H85: 2 | J85: 265 | K85: 0 | L85: 2 | M85: 0 | N85: 0 | O85: 0 | P85: 3 | Q85: =SUM(K85:O85) -> 2
A86: 266 | B86: 0 | C86: 2 | D86: 0 | E86: 0 | F86: 0 | G86: 2 | H86: 2 | J86: 266 | K86: 0 | L86: 2 | M86: 0 | N86: 0 | O86: 0 | P86: 2 | Q86: 2
A87: 267 | B87: 0 | C87: 2 | D87: 0 | E87: 0 | F87: 0 | G87: 2 | H87: 2 | J87: 267 | K87: 0 | L87: 2 | M87: 0 | N87: 0 | O87: 0 | P87: 2 | Q87: 2
A88: 268 | B88: 0 | C88: 1 | D88: 0 | E88: 0 | F88: 0 | G88: 1 | H88: 1 | J88: 268 | K88: 0 | L88: 1 | M88: 0 | N88: 0 | O88: 0 | P88: 1 | Q88: 1
A89: 269 | B89: 0 | C89: 1 | D89: 0 | E89: 0 | F89: 0 | G89: 1 | H89: 1 | J89: 269 | K89: 0 | L89: 1 | M89: 0 | N89: 0 | O89: 0 | P89: 1 | Q89: 1
A90: 270 | B90: 0 | C90: 0 | D90: 0 | E90: 2 | F90: 0 | G90: 3 | H90: 2 | J90: 270 | K90: 0 | L90: 0 | M90: 0 | N90: 2 | O90: 0 | P90: 3 | Q90: =SUM(K90:O90) -> 2
A91: 272 | B91: 0 | C91: 0 | D91: 0 | E91: 0 | F91: 1 | G91: 0 | H91: 0 | J91: 272 | K91: 0 | L91: 0 | M91: 0 | N91: 0 | O91: 1 | P91: 0 | Q91: 0
A92: 273 | B92: 0 | C92: 0 | D92: 0 | E92: 0 | F92: 1 | G92: 0 | H92: 0 | J92: 273 | K92: 0 | L92: 0 | M92: 0 | N92: 0 | O92: 1 | P92: 0 | Q92: 0
A93: 274 | B93: 0 | C93: 0 | D93: 1 | E93: 1 | F93: 0 | G93: 2 | H93: 2 | J93: 274 | K93: 0 | L93: 0 | M93: 1 | N93: 1 | O93: 0 | P93: 2 | Q93: 2
A94: 275 | B94: 0 | C94: 0 | D94: 2 | E94: 0 | F94: 0 | G94: 3 | H94: 2 | J94: 275 | K94: 0 | L94: 0 | M94: 2 | N94: 0 | O94: 0 | P94: 3 | Q94: =SUM(K94:O94) -> 2
A95: 276 | B95: 0 | C95: 0 | D95: 0 | E95: 0 | F95: 1 | G95: 0 | H95: 0 | J95: 276 | K95: 0 | L95: 0 | M95: 0 | N95: 0 | O95: 1 | P95: 0 | Q95: 0
A96: 277 | B96: 0 | C96: 2 | D96: 0 | E96: 0 | F96: 0 | G96: 2 | H96: 2 | J96: 277 | K96: 0 | L96: 2 | M96: 0 | N96: 0 | O96: 0 | P96: 2 | Q96: 2
A97: 278 | B97: 0 | C97: 2 | D97: 0 | E97: 0 | F97: 0 | G97: 2 | H97: 2 | J97: 278 | K97: 0 | L97: 2 | M97: 0 | N97: 0 | O97: 0 | P97: 2 | Q97: 2
A98: 279 | B98: 0 | C98: 1 | D98: 0 | E98: 0 | F98: 0 | G98: 1 | H98: 1 | J98: 279 | K98: 0 | L98: 1 | M98: 0 | N98: 0 | O98: 0 | P98: 1 | Q98: 1
A99: 291 | B99: 0 | C99: 0 | D99: 0 | E99: 1 | F99: 0 | G99: 1 | H99: 1 | J99: 291 | K99: 0 | L99: 0 | M99: 0 | N99: 1 | O99: 0 | P99: 1 | Q99: 1
A100: 292 | B100: 0 | C100: 0 | D100: 0 | E100: 1 | F100: 0 | G100: 1 | H100: 1 | J100: 292 | K100: 0 | L100: 0 | M100: 0 | N100: 1 | O100: 0 | P100: 1 | Q100: 1
A101: 293 | B101: 0 | C101: 0 | D101: 0 | E101: 1 | F101: 0 | G101: 1 | H101: 1 | J101: 293 | K101: 0 | L101: 0 | M101: 0 | N101: 1 | O101: 0 | P101: 1 | Q101: 1
A102: 294 | B102: 0 | C102: 1 | D102: 0 | E102: 0 | F102: 0 | G102: 1 | H102: 1 | J102: 294 | K102: 0 | L102: 1 | M102: 0 | N102: 0 | O102: 0 | P102: 1 | Q102: 1
A103: 296 | B103: 0 | C103: 0 | D103: 0 | E103: 1 | F103: 0 | G103: 1 | H103: 1 | J103: 296 | K103: 0 | L103: 0 | M103: 0 | N103: 1 | O103: 0 | P103: 1 | Q103: 1
A104: 297 | B104: 0 | C104: 0 | D104: 0 | E104: 1 | F104: 0 | G104: 1 | H104: 1 | J104: 297 | K104: 0 | L104: 0 | M104: 0 | N104: 1 | O104: 0 | P104: 1 | Q104: 1
A105: 298 | B105: 0 | C105: 0 | D105: 0 | E105: 1 | F105: 0 | G105: 1 | H105: 1 | J105: 298 | K105: 0 | L105: 0 | M105: 0 | N105: 1 | O105: 0 | P105: 1 | Q105: 1
A106: 299 | B106: 0 | C106: 2 | D106: 0 | E106: 0 | F106: 0 | G106: 3 | H106: 2 | J106: 299 | K106: 0 | L106: 2 | M106: 0 | N106: 0 | O106: 0 | P106: 3 | Q106: =SUM(K106:O106) -> 2
A107: 301 | B107: 0 | C107: 0 | D107: 2 | E107: 0 | F107: 0 | G107: 3 | H107: 2 | J107: 301 | K107: 0 | L107: 0 | M107: 2 | N107: 0 | O107: 0 | P107: 3 | Q107: =SUM(K107:O107) -> 2
A108: 305 | B108: 0 | C108: 0 | D108: 0 | E108: 0 | F108: 1 | G108: 0 | H108: 0 | J108: 305 | K108: 0 | L108: 0 | M108: 0 | N108: 0 | O108: 1 | P108: 0 | Q108: 0
A109: 306 | B109: 0 | C109: 0 | D109: 0 | E109: 1 | F109: 0 | G109: 1 | H109: 1 | J109: 306 | K109: 0 | L109: 0 | M109: 0 | N109: 1 | O109: 0 | P109: 1 | Q109: 1
A110: 308 | B110: 0 | C110: 2 | D110: 0 | E110: 0 | F110: 0 | G110: 3 | H110: 2 | J110: 308 | K110: 0 | L110: 2 | M110: 0 | N110: 0 | O110: 0 | P110: 3 | Q110: =SUM(K110:O110) -> 2
A111: 309 | B111: 0 | C111: 2 | D111: 0 | E111: 0 | F111: 0 | G111: 2 | H111: 2 | J111: 309 | K111: 0 | L111: 2 | M111: 0 | N111: 0 | O111: 0 | P111: 2 | Q111: 2
A112: 311 | B112: 0 | C112: 1 | D112: 0 | E112: 0 | F112: 0 | G112: 1 | H112: 1 | J112: 311 | K112: 0 | L112: 1 | M112: 0 | N112: 0 | O112: 0 | P112: 1 | Q112: 1
A113: 312 | B113: 0 | C113: 1 | D113: 0 | E113: 0 | F113: 0 | G113: 1 | H113: 1 | J113: 312 | K113: 0 | L113: 1 | M113: 0 | N113: 0 | O113: 0 | P113: 1 | Q113: 1
A114: 314 | B114: 1 | C114: 0 | D114: 0 | E114: 0 | F114: 0 | G114: 1 | H114: 1 | J114: 314 | K114: 1 | L114: 0 | M114: 0 | N114: 0 | O114: 0 | P114: 1 | Q114: 1
A115: 315 | B115: 0 | C115: 0 | D115: 1 | E115: 1 | F115: 0 | G115: 2 | H115: 2 | J115: 315 | K115: 0 | L115: 0 | M115: 1 | N115: 1 | O115: 0 | P115: 2 | Q115: 2
A116: 316 | B116: 0 | C116: 1 | D116: 0 | E116: 0 | F116: 0 | G116: 1 | H116: 1 | J116: 316 | K116: 0 | L116: 1 | M116: 0 | N116: 0 | O116: 0 | P116: 1 | Q116: 1
A117: 317 | B117: 0 | C117: 0 | D117: 0 | E117: 2 | F117: 0 | G117: 2 | H117: 2 | J117: 317 | K117: 0 | L117: 0 | M117: 0 | N117: 2 | O117: 0 | P117: 2 | Q117: 2
A118: 318 | B118: 0 | C118: 0 | D118: 2 | E118: 0 | F118: 0 | G118: 3 | H118: 2 | J118: 318 | K118: 0 | L118: 0 | M118: 2 | N118: 0 | O118: 0 | P118: 3 | Q118: =SUM(K118:O118) -> 2
A119: 321 | B119: 0 | C119: 2 | D119: 0 | E119: 0 | F119: 0 | G119: 2 | H119: 2 | J119: 321 | K119: 0 | L119: 2 | M119: 0 | N119: 0 | O119: 0 | P119: 2 | Q119: 2
A120: 322 | B120: 0 | C120: 1 | D120: 0 | E120: 0 | F120: 0 | G120: 1 | H120: 1 | J120: 322 | K120: 0 | L120: 1 | M120: 0 | N120: 0 | O120: 0 | P120: 1 | Q120: 1
A121: 324 | B121: 0 | C121: 0 | D121: 2 | E121: 0 | F121: 0 | G121: 2 | H121: 2 | J121: 324 | K121: 0 | L121: 0 | M121: 2 | N121: 0 | O121: 0 | P121: 2 | Q121: 2
A122: 325 | B122: 0 | C122: 0 | D122: 2 | E122: 0 | F122: 0 | G122: 2 | H122: 2 | J122: 325 | K122: 0 | L122: 0 | M122: 2 | N122: 0 | O122: 0 | P122: 2 | Q122: 2
A123: 326 | B123: 0 | C123: 0 | D123: 0 | E123: 0 | F123: 1 | G123: 0 | H123: 0 | J123: 326 | K123: 0 | L123: 0 | M123: 0 | N123: 0 | O123: 1 | P123: 0 | Q123: 0
A124: 327 | B124: 0 | C124: 0 | D124: 0 | E124: 0 | F124: 1 | G124: 0 | H124: 0 | J124: 327 | K124: 0 | L124: 0 | M124: 0 | N124: 0 | O124: 1 | P124: 0 | Q124: 0
A125: 328 | B125: 0 | C125: 0 | D125: 0 | E125: 0 | F125: 1 | G125: 0 | H125: 0 | J125: 328 | K125: 0 | L125: 0 | M125: 0 | N125: 0 | O125: 1 | P125: 0 | Q125: 0
A126: 329 | B126: 2 | C126: 0 | D126: 0 | E126: 0 | F126: 0 | G126: 2 | H126: 2 | J126: 329 | K126: 2 | L126: 0 | M126: 0 | N126: 0 | O126: 0 | P126: 2 | Q126: 2
A127: 330 | B127: 1 | C127: 0 | D127: 0 | E127: 0 | F127: 0 | G127: 1 | H127: 1 | J127: 330 | K127: 1 | L127: 0 | M127: 0 | N127: 0 | O127: 0 | P127: 1 | Q127: 1
A128: 333 | B128: 1 | C128: 0 | D128: 0 | E128: 0 | F128: 0 | G128: 1 | H128: 1 | J128: 333 | K128: 1 | L128: 0 | M128: 0 | N128: 0 | O128: 0 | P128: 1 | Q128: 1
A129: 335 | B129: 0 | C129: 0 | D129: 0 | E129: 0 | F129: 1 | G129: 0 | H129: 0 | J129: 335 | K129: 0 | L129: 0 | M129: 0 | N129: 0 | O129: 1 | P129: 0 | Q129: 0
A130: 336 | B130: 0 | C130: 0 | D130: 0 | E130: 0 | F130: 1 | G130: 0 | H130: 0 | J130: 336 | K130: 0 | L130: 0 | M130: 0 | N130: 0 | O130: 1 | P130: 0 | Q130: 0
... A156: 375 | B156: 0 | C156: 1 | D156: 0 | E156: 0 | F156: 0 | G156: 1 | H156: 1 | J156: 375 | K156: 0 | L156: 1 | M156: 0 | N156: 0 | O156: 0 | P156: 1 | Q156: 1
A157: 386 | B157: 0 | C157: 0 | D157: 2 | E157: 0 | F157: 0 | G157: 3 | H157: 2 | J157: 386 | K157: 0 | L157: 0 | M157: 2 | N157: 0 | O157: 0 | P157: 3 | Q157: =SUM(K157:O157) -> 2
A158: 387 | B158: 0 | C158: 0 | D158: 2 | E158: 0 | F158: 0 | G158: 2 | H158: 2 | J158: 387 | K158: 0 | L158: 0 | M158: 2 | N158: 0 | O158: 0 | P158: 2 | Q158: 2
A159: 388 | B159: 0 | C159: 0 | D159: 0 | E159: 0 | F159: 1 | G159: 0 | H159: 0 | J159: 388 | K159: 0 | L159: 0 | M159: 0 | N159: 0 | O159: 1 | P159: 0 | Q159: 0
A160: 389 | B160: 0 | C160: 0 | D160: 0 | E160: 1 | F160: 0 | G160: 1 | H160: 1 | J160: 389 | K160: 0 | L160: 0 | M160: 0 | N160: 1 | O160: 0 | P160: 1 | Q160: 1
A161: 391 | B161: 0 | C161: 0 | D161: 0 | E161: 1 | F161: 0 | G161: 1 | H161: 1 | J161: 391 | K161: 0 | L161: 0 | M161: 0 | N161: 1 | O161: 0 | P161: 1 | Q161: 1
A162: 392 | B162: 0 | C162: 1 | D162: 0 | E162: 0 | F162: 0 | G162: 1 | H162: 1 | J162: 392 | K162: 0 | L162: 1 | M162: 0 | N162: 0 | O162: 0 | P162: 1 | Q162: 1
A163: 393 | B163: 0 | C163: 1 | D163: 0 | E163: 0 | F163: 0 | G163: 1 | H163: 1 | J163: 393 | K163: 0 | L163: 1 | M163: 0 | N163: 0 | O163: 0 | P163: 1 | Q163: 1
A164: 394 | B164: 0 | C164: 0 | D164: 0 | E164: 0 | F164: 1 | G164: 0 | H164: 0 | J164: 394 | K164: 0 | L164: 0 | M164: 0 | N164: 0 | O164: 1 | P164: 0 | Q164: 0
A165: 395 | B165: 0 | C165: 0 | D165: 0 | E165: 2 | F165: 0 | G165: 2 | H165: 2 | J165: 395 | K165: 0 | L165: 0 | M165: 0 | N165: 2 | O165: 0 | P165: 2 | Q165: 2
A166: 396 | B166: 0 | C166: 0 | D166: 0 | E166: 1 | F166: 0 | G166: 1 | H166: 1 | J166: 396 | K166: 0 | L166: 0 | M166: 0 | N166: 1 | O166: 0 | P166: 1 | Q166: 1
A167: 397 | B167: 0 | C167: 0 | D167: 0 | E167: 1 | F167: 0 | G167: 1 | H167: 1 | J167: 397 | K167: 0 | L167: 0 | M167: 0 | N167: 1 | O167: 0 | P167: 1 | Q167: 1
A168: 398 | B168: 0 | C168: 0 | D168: 0 | E168: 0 | F168: 1 | G168: 0 | H168: 0 | J168: 398 | K168: 0 | L168: 0 | M168: 0 | N168: 0 | O168: 1 | P168: 0 | Q168: 0
A169: 399 | B169: 0 | C169: 2 | D169: 0 | E169: 0 | F169: 0 | G169: 3 | H169: 2 | J169: 399 | K169: 0 | L169: 2 | M169: 0 | N169: 0 | O169: 0 | P169: 3 | Q169: =SUM(K169:O169) -> 2
A170: 401 | B170: 0 | C170: 2 | D170: 0 | E170: 0 | F170: 0 | G170: 2 | H170: 2 | J170: 401 | K170: 0 | L170: 2 | M170: 0 | N170: 0 | O170: 0 | P170: 2 | Q170: 2
A171: 402 | B171: 0 | C171: 1 | D171: 0 | E171: 0 | F171: 0 | G171: 1 | H171: 1 | J171: 402 | K171: 0 | L171: 1 | M171: 0 | N171: 0 | O171: 0 | P171: 1 | Q171: 1
A172: 430 | B172: 0 | C172: 2 | D172: 0 | E172: 0 | F172: 0 | G172: 2 | H172: 2 | J172: 430 | K172: 0 | L172: 2 | M172: 0 | N172: 0 | O172: 0 | P172: 2 | Q172: 2
A173: 432 | B173: 0 | C173: 2 | D173: 0 | E173: 0 | F173: 0 | G173: 2 | H173: 2 | J173: 432 | K173: 0 | L173: 2 | M173: 0 | N173: 0 | O173: 0 | P173: 2 | Q173: 2
A174: 441 | B174: 0 | C174: 1 | D174: 0 | E174: 0 | F174: 0 | G174: 1 | H174: 1 | J174: 441 | K174: 0 | L174: 1 | M174: 0 | N174: 0 | O174: 0 | P174: 1 | Q174: 1
A175: 451 | B175: 0 | C175: 0 | D175: 0 | E175: 2 | F175: 0 | G175: 2 | H175: 2 | J175: 451 | K175: 0 | L175: 0 | M175: 0 | N175: 2 | O175: 0 | P175: 2 | Q175: 2
...

Sheet Promos
D1: Source: | E1: Wave 4 Proposed.xlsx
O2: Art Code Unique List | P2: Sorted A-Z | Q2: Transposed -> (19 total)
A3: Store # ↓ | B3: Vlookup Store # | C3: Store # & Name ↓ | D3: Region | E3: DO | F3: Category | G3: Wave 4 Promo 9/1 - 11/30 | H3: Note | I3: Combined Code | J3: UWC Code | K3: Art Code | M3: {=_xlfn.UNIQUE(A4:A198)} -> 2552 | O3: {=_xlfn.UNIQUE(K4:K198)} -> D01 | P3: 10F-101 | Q3: 10F-101 | R3: 10F-104 | S3: 10F-201 | T3: 8D-04 | U3: 8D-05 | V3: 8F-304 | W3: A01 | X3: B01 | Y3: B05 | Z3: B06 | AA3: C01 | AB3: C04 | AC3: D01 | AD3: D02 | AE3: D03 | AF3: D06 | AG3: E01 | AH3: E03 | AI3: E07
A4: 2552 | B4: 2552 | C4: AZ-2552 Tucson Mall | D4: AZ - Tucson | E4: Alen Keshishian | F4: NBB | G4: $9.99 all plans 1 mo. | I4: 201 | J4: 01 | K4: D01 | M4: 1329 | O4: 10F-101 | P4: 10F-104
A5: 1329 | B5: 1329 | C5: AZ-1329 Craycroft | D5: AZ - Tucson | E5: Alen Keshishian | F5: NBB | G5: $9.99 all plans 1 mo. | I5: 201 | J5: 01 | K5: D01 | M5: 1331 | O5: E01 | P5: 10F-201
A6: 1331 | B6: 1331 | C6: AZ-1331 Twin Peaks | D6: AZ - Tucson | E6: Alen Keshishian | F6: NBB | G6: $9.99 all plans 1 mo. | I6: 201 | J6: 01 | K6: D01 | M6: 2557 | O6: 8D-04 | P6: 8D-04
A7: 2557 | B7: 2557 | C7: AZ-2557 Cardinal | D7: AZ - Tucson | E7: Alen Keshishian | F7: NBB | G7: $9.99 all plans 1 mo. | I7: 201 | J7: 01 | K7: D01 | M7: 0327 | O7: D02 | P7: 8D-05
A8: 0327 | B8: 327 | C8: AZ-0327 South Kolb | D8: AZ - Tucson | E8: Alen Keshishian | F8: Sub3k | G8: $9.99 all plans 1 mo. | I8: 201 | J8: 01 | K8: D01 | M8: 0326 | O8: 8F-304 | P8: 8F-304
A9: 0326 | B9: 326 | C9: AZ-0326 Swan | D9: AZ - Tucson | E9: Alen Keshishian | F9: Sub3k | G9: $9.99 all plans 1 mo. | I9: 201 | J9: 01 | K9: D01 | M9: 0328 | O9: E07 | P9: A01
A10: 0328 | B10: 328 | C10: AZ-0328 Euclid | D10: AZ - Tucson | E10: Alen Keshishian | F10: Sub3k | G10: $9.99 all plans 1 mo. | I10: 201 | J10: 01 | K10: D01 | M10: 1035 | O10: 10F-104 | P10: B01
A11: 1035 | B11: 1035 | C11: CA-1035 Hosking | D11: CA - Bakersfield | E11: Alen Keshishian | F11: NBB | G11: $9.99 all plans 1 mo. | I11: 101 | J11: 01 | K11: D01 | M11: 1038 | O11: A01 | P11: B05 | S11: {=_xlfn.UNIQUE(G4:G198)} -> $9.99 all plans 1 mo.
A12: 1038 | B12: 1038 | C12: CA-1038 Heath | D12: CA - Bakersfield | E12: Alen Keshishian | F12: NBB | G12: $9.99 all plans 1 mo. | I12: 101 | J12: 01 | K12: D01 | M12: 1058 | O12: C01 | P12: B06 | S12: All Plans PoR 1 mo.
A13: 1058 | B13: 1058 | C13: CA-1058 Stockdale | D13: CA - Bakersfield | E13: Alen Keshishian | F13: NBB | G13: $9.99 all plans 1 mo. | I13: 101 | J13: 01 | K13: D01 | M13: 1016 | O13: D06 | P13: C01 | S13: 50% off all plan 1 mo.
A14: 1016 | B14: 1016 | C14: CA-1016 Rosedale Hwy | D14: CA - Bakersfield | E14: Alen Keshishian | F14: NBB | G14: $9.99 all plans 1 mo. | I14: 101 | J14: 01 | K14: D01 | M14: 1034 | O14: G | P14: C04 | S14: $10 all plans 3 mos.
A15: 1034 | B15: 1034 | C15: CA-1034 Carmen | D15: CA - Bakersfield | E15: Alen Keshishian | F15: NBB | G15: $9.99 all plans 1 mo. | I15: 101 | J15: 01 | K15: D01 | M15: 1013 | O15: 10F-201 | P15: D01 | S15: $5, $10, $15
A16: 1013 | B16: 1013 | C16: CA-1013 Hwy 138 | D16: CA - Los Angeles | E16: Bob Bartholomew | F16: NBB | G16: $9.99 all plans 1 mo. | I16: 101 | J16: 01 | K16: D01 | M16: 1018 | O16: 8D-05 | P16: D02 | S16: $15 off all plans 1 mo.
A17: 1018 | B17: 1018 | C17: CA-1018 Rialto | D17: CA - Los Angeles | E17: Bob Bartholomew | F17: NBB | G17: $9.99 all plans 1 mo. | I17: 101 | J17: 01 | K17: D01 | M17: 1027 | O17: B01 | P17: D03 | S17: $9.99 all plans 1 mo.
A18: 1027 | B18: 1027 | C18: CA-1027 Stoneridge | D18: CA - Los Angeles | E18: Bob Bartholomew | F18: NBB | G18: $9.99 all plans 1 mo. | I18: 101 | J18: 01 | K18: D01 | M18: 1037 | O18: C04 | P18: D06
A19: 1037 | B19: 1037 | C19: CA-1037 Varsity | D19: CA - Los Angeles | E19: Bob Bartholomew | F19: NBB | G19: $9.99 all plans 1 mo. | I19: 101 | J19: 01 | K19: D01 | M19: 0915 | O19: B05 | P19: E01
A20: 0915 | B20: 915 | C20: CA-0915 Merced | D20: CA - Modesto | E20: Bob Bartholomew | F20: Underperforming | G20: $9.99 all plans 1 mo. | I20: 101 | J20: 01 | K20: D01 | M20: 1076 | O20: B06 | P20: E03
A21: 1076 | B21: 1076 | C21: CA-1076 Tuolumne | D21: CA - Modesto | E21: Bob Bartholomew | F21: NBB | G21: $9.99 all plans 1 mo. | H21: Start promo earlier (8/6), keeping it on after FWW | I21: 101 | J21: 01 | K21: D01 | M21: 1039 | O21: D03 | P21: E07
A22: 1039 | B22: 1039 | C22: CA-1039 Mooney Blvd | D22: CA - San Joaquin Valley | E22: Bob Bartholomew | F22: Underperforming | G22: All Plans PoR 1 mo. | I22: 101 | J22: 01 | K22: 10F-101 | M22: 1072 | O22: E03
A23: 1072 | B23: 1072 | C23: CA-1072 Reedley | D23: CA - San Joaquin Valley | E23: Bob Bartholomew | F23: NBB | G23: All Plans PoR 1 mo. | I23: 101 | J23: 01 | K23: 10F-101 | M23: 1031
A24: 1031 | B24: 1031 | C24: CA-1031 Jellico Ave | D24: CA - Victor Valley | E24: Bob Bartholomew | F24: NBB | G24: $9.99 all plans 1 mo. | I24: 201 | J24: 01 | K24: D01 | M24: 1064
A25: 1064 | B25: 1064 | C25: CA-1064 Bear Valley | D25: CA - Victor Valley | E25: Bob Bartholomew | F25: NBB | G25: $9.99 all plans 1 mo. | I25: 201 | J25: 01 | K25: D01 | M25: 1019
A26: 1019 | B26: 1019 | C26: CA-1019 Happy Trails Hwy | D26: CA - Victor Valley | E26: Bob Bartholomew | F26: NBB | G26: $9.99 all plans 1 mo. | I26: 201 | J26: 01 | K26: D01 | M26: 0041
A27: 0041 | B27: 41 | C27: AL-0041 Hartselle | D27: AL - Huntsville | E27: Dean Ngo | F27: Underperforming | G27: 50% off all plan 1 mo. | I27: 101 | J27: 01 | K27: E01 | M27: 0042
A28: 0042 | B28: 42 | C28: AL-0042 Limestone | D28: AL - Huntsville | E28: Dean Ngo | F28: Underperforming | G28: 50% off all plan 1 mo. | I28: 101 | J28: 01 | K28: E01 | M28: 0043
A29: 0043 | B29: 43 | C29: AL-0043 Madison | D29: AL - Huntsville | E29: Dean Ngo | F29: Underperforming | G29: 50% off all plan 1 mo. | I29: 101 | J29: 01 | K29: E01 | M29: 0044
A30: 0044 | B30: 44 | C30: AL-0042 Limestone | D30: AL - Huntsville | E30: Dean Ngo | F30: Underperforming | G30: 50% off all plan 1 mo. | I30: 101 | J30: 01 | K30: E01 | M30: 0045
A31: 0045 | B31: 45 | C31: AL-0045 9th Street | D31: AL - Huntsville | E31: Dean Ngo | F31: Underperforming | G31: 50% off all plan 1 mo. | I31: 101 | J31: 01 | K31: E01 | M31: 0046
A32: 0046 | B32: 46 | C32: AL-0046 Bassett Ave | D32: AL - Huntsville | E32: Dean Ngo | F32: Underperforming | G32: 50% off all plan 1 mo. | I32: 101 | J32: 01 | K32: E01 | M32: 0047
A33: 0047 | B33: 47 | C33: AL-0047 Grace | D33: AL - Huntsville | E33: Dean Ngo | F33: Underperforming | G33: 50% off all plan 1 mo. | I33: 101 | J33: 01 | K33: E01 | M33: 0051
A34: 0051 | B34: 51 | C34: AL-0051 Azalea | D34: AL - Huntsville | E34: Dean Ngo | F34: Underperforming | G34: 50% off all plan 1 mo. | I34: 101 | J34: 01 | K34: E01 | M34: 0052
... A73: 2570 | B73: 2570 | C73: MI-2570 Argyle | D73: MI - Detroit | E73: Jack Larson | F73: NBB | G73: All Plans PoR 1 mo. | I73: 101 | J73: 01 | K73: 10F-101 | M73: 1473
A74: 1473 | B74: 1473 | C74: MI-1473 Holland | D74: MI - Grand Rapids | E74: Jack Larson | F74: NBB | G74: $10 all plans 3 mos. | H74: Version A ($10 3 Mo) | I74: 101 | J74: 01 | K74: A01 | M74: 1474
A75: 1474 | B75: 1474 | C75: MI-1474 Ford Rd | D75: MI - Grand Rapids | E75: Jack Larson | F75: NBB | G75: All Plans PoR 1 mo. | I75: 104 | J75: 04 | K75: 10F-104 | M75: 2554
A76: 2554 | B76: 2554 | C76: MI-2554 Waterford | D76: MI - Grand Rapids | E76: Jack Larson | F76: NBB | G76: All Plans PoR 1 mo. | I76: 104 | J76: 04 | K76: 10F-104 | M76: 1464
A77: 1464 | B77: 1464 | C77: MI-1464 Saginaw | D77: MI - Saginaw | E77: Jack Larson | F77: Underperforming | G77: $5, $10, $15 | I77: 201 | J77: 01 | K77: C01 | M77: 1468
A78: 1468 | B78: 1468 | C78: MI-1468 Lawndale | D78: MI - Saginaw | E78: Jack Larson | F78: Underperforming | G78: $5, $10, $15 | I78: 201 | J78: 01 | K78: C01 | M78: 1467
A79: 1467 | B79: 1467 | C79: MI-1467 Bay Road | D79: MI - Saginaw | E79: Jack Larson | F79: Underperforming | G79: $5, $10, $15 | I79: 201 | J79: 01 | K79: C01 | M79: 1686
A80: 1686 | B80: 1686 | C80: PA-1686 Lincoln Hwy | D80: PA - Lancaster/Reading | E80: Jack Larson | F80: NBB | G80: $9.99 all plans 1 mo. | I80: 106 | J80: 06 | K80: D06 | M80: 1687
A81: 1687 | B81: 1687 | C81: PA-1687 Jonestown | D81: PA - Lancaster/Reading | E81: Jack Larson | F81: NBB | G81: $9.99 all plans 1 mo. | I81: 106 | J81: 06 | K81: D06 | M81: 0834
A82: 0834 | B82: 834 | C82: TN-0834 Columbia Tn | D82: TN - Nashville | E82: Jack Larson | F82: Underperforming | G82: 50% off all plan 1 mo. | I82: 101 | J82: 01 | K82: E01 | M82: 0847
A83: 0847 | B83: 847 | C83: TN-0847 Carver Lane | D83: TN - Nashville | E83: Jack Larson | F83: NBB | G83: 50% off all plan 1 mo. | I83: 101 | J83: 01 | K83: E01 | M83: 0832
A84: 0832 | B84: 832 | C84: TN-0832 Hermitage | D84: TN - Nashville | E84: Jack Larson | F84: Sub3k | G84: 50% off all plan 1 mo. | I84: 101 | J84: 01 | K84: E01 | M84: 0835
A85: 0835 | B85: 835 | C85: TN-0835 Lavergne | D85: TN - Nashville | E85: Jack Larson | F85: Sub3k | G85: 50% off all plan 1 mo. | I85: 101 | J85: 01 | K85: E01 | M85: 0846
A86: 0846 | B86: 846 | C86: TN-0846 Dover Crossing | D86: TN - Nashville | E86: Jack Larson | F86: Sub3k | G86: 50% off all plan 1 mo. | I86: 101 | J86: 01 | K86: E01 | M86: 0844
... A88: 0837 | B88: 837 | C88: TN-0837 Highway 96 | D88: TN - Nashville | E88: Jack Larson | F88: Sub3k | G88: 50% off all plan 1 mo. | I88: 101 | J88: 01 | K88: E01 | M88: 0481
A89: 0481 | B89: 481 | C89: WI-0481 University Ave | D89: WI - Madison/IL | E89: Jack Larson | F89: Underperforming | G89: $10 all plans 3 mos. | H89: Version B (90 Days for $30) | I89: 101 | J89: 01 | K89: G | M89: 0482
A90: 0482 | B90: 482 | C90: WI-0482 Washington | D90: WI - Madison/IL | E90: Jack Larson | F90: Underperforming | G90: $10 all plans 3 mos. | H90: Version B (90 Days for $30) | I90: 101 | J90: 01 | K90: G | M90: 1458
A91: 1458 | B91: 1458 | C91: IL-1458 Loves Park | D91: WI - Madison/IL | E91: Jack Larson | F91: NBB | G91: $10 all plans 3 mos. | H91: Version A ($10 3 Mo) | I91: 201 | J91: 01 | K91: A01 | M91: 1453
A92: 1453 | B92: 1453 | C92: IL-1453 Kimber | D92: WI - Madison/IL | E92: Jack Larson | F92: NBB | G92: $10 all plans 3 mos. | H92: Version A ($10 3 Mo) | I92: 201 | J92: 01 | K92: A01 | M92: 0492
A93: 0492 | B93: 492 | C93: IL-0492 State St | D93: WI - Madison/IL | E93: Jack Larson | F93: Sub3k | G93: $10 all plans 3 mos. | H93: Version A ($10 3 Mo) | I93: 201 | J93: 01 | K93: A01 | M93: 0495
A94: 0495 | B94: 495 | C94: WI-0495 Howell | D94: WI - Milwaukee | E94: Jack Larson | F94: Underperforming | G94: $10 all plans 3 mos. | H94: Version A ($10 3 Mo) | I94: 101 | J94: 01 | K94: A01 | M94: 0493
A95: 0493 | B95: 493 | C95: WI-0493 Brookfield | D95: WI - Milwaukee | E95: Jack Larson | F95: Underperforming | G95: $10 all plans 3 mos. | H95: Version A ($10 3 Mo) | I95: 101 | J95: 01 | K95: A01 | M95: 1480
A96: 1480 | B96: 1480 | C96: WI-1480 Castle Manor | D96: WI - Milwaukee | E96: Jack Larson | F96: NBB | G96: $10 all plans 3 mos. | H96: Version A ($10 3 Mo) | I96: 101 | J96: 01 | K96: A01 | M96: 1481
A97: 1481 | B97: 1481 | C97: WI-1481 Market Lane | D97: WI - Milwaukee | E97: Jack Larson | F97: NBB | G97: $10 all plans 3 mos. | H97: Version A ($10 3 Mo) | I97: 101 | J97: 01 | K97: A01 | M97: 1494
A98: 1494 | B98: 1494 | C98: WI-1494 Kenosha | D98: WI - Milwaukee | E98: Jack Larson | F98: NBB | G98: $10 all plans 3 mos. | H98: Version A ($10 3 Mo) | I98: 101 | J98: 01 | K98: A01 | M98: 0494
A99: 0494 | B99: 494 | C99: WI-0494 Good Hope | D99: WI - Milwaukee | E99: Jack Larson | F99: Sub3k | G99: $10 all plans 3 mos. | H99: Version A ($10 3 Mo) | I99: 101 | J99: 01 | K99: A01 | M99: 1805
A100: 1805 | B100: 1805 | C100: FL-1805 Santa Barbara Blvd | D100: FL - Cape Coral | E100: Jeff Burr | F100: Underperforming | G100: All Plans PoR 1 mo. | I100: 201 | J100: 01 | K100: 10F-201 | M100: 1814
A101: 1814 | B101: 1814 | C101: FL-1814 Metro Pkwy | D101: FL - Cape Coral | E101: Jeff Burr | F101: Underperforming | G101: All Plans PoR 1 mo. | I101: 201 | J101: 01 | K101: 10F-201 | M101: 1807
A102: 1807 | B102: 1807 | C102: FL-1807 Ne 16th Place | D102: FL - Cape Coral | E102: Jeff Burr | F102: NBB | G102: All Plans PoR 1 mo. | I102: 201 | J102: 01 | K102: 10F-201 | M102: 1813
A103: 1813 | B103: 1813 | C103: FL-1813 Arborwood | D103: FL - Cape Coral | E103: Jeff Burr | F103: NBB | G103: All Plans PoR 1 mo. | I103: 201 | J103: 01 | K103: 10F-201 | M103: 1816
A104: 1816 | B104: 1816 | C104: FL-1816 Estero | D104: FL - Cape Coral | E104: Jeff Burr | F104: NBB | G104: All Plans PoR 1 mo. | I104: 201 | J104: 01 | K104: 10F-201 | M104: 1811
A105: 1811 | B105: 1811 | C105: FL-1811 Cody Lee | D105: FL - Cape Coral | E105: Jeff Burr | F105: Sub3k | G105: All Plans PoR 1 mo. | I105: 201 | J105: 01 | K105: 10F-201 | M105: 1801
A106: 1801 | B106: 1801 | C106: FL-1801 Del Prado | D106: FL - Cape Coral | E106: Jeff Burr | F106: Sub3k | G106: All Plans PoR 1 mo. | I106: 201 | J106: 01 | K106: 10F-201 | M106: 1906
A107: 1906 | B107: 1906 | C107: FL-1906 Florida Ave S | D107: FL - Lakeland | E107: Jeff Burr | F107: Underperforming | G107: All Plans PoR 1 mo. | I107: 201 | J107: 01 | K107: 10F-201 | M107: 0243
A108: 0243 | B108: 243 | C108: FL-0243 Silver Star | D108: FL - Orlando | E108: Jeff Burr | F108: Underperforming | G108: All Plans PoR 1 mo. | I108: 101 | J108: 01 | K108: 10F-101 | M108: 0236
A109: 0236 | B109: 236 | C109: FL-0236 Chickasaw | D109: FL - Orlando | E109: Jeff Burr | F109: Underperforming | G109: All Plans PoR 1 mo. | I109: 101 | J109: 01 | K109: 10F-101 | M109: 1242
A110: 1242 | B110: 1242 | C110: FL-1242 Semoran | D110: FL - Orlando | E110: Jeff Burr | F110: Underperforming | G110: All Plans PoR 1 mo. | I110: 101 | J110: 01 | K110: 10F-101 | M110: 1206
A111: 1206 | B111: 1206 | C111: FL-1206 Kissimmee | D111: FL - Orlando | E111: Jeff Burr | F111: Underperforming | G111: All Plans PoR 1 mo. | I111: 101 | J111: 01 | K111: 10F-101 | M111: 0235
... A197: 1114 | B197: 1114 | C197: TX-1114 Pearland | D197: TX - Houston | E197: Kevin Brack | F197: NBB | G197: All Plans PoR 1 mo. | I197: 101 | J197: 01 | K197: 10F-101 | M197: 0335
A198: 0335 | B198: 335 | C198: AZ-0335 Grant | D198: AZ - Tucson | E198: Alen Keshishian | F198: Underperforming | G198: $9.99 all plans 1 mo. | I198: 201 | J198: 01 | K198: D01

Sheet Pivot Check

Sheet Region Shipments
A1: PLEASE DOWNLOAD A COPY OF THE SHIPPING KEY TO WORK ON - don't edit this document | G1: Domo card to get data: | H1: MKTG Shipping Key - Preferred Regional Ship-To Addresses
A2: Shipping Key - Preferred Regional Shipping Addresses | G2: Source dataset: | H2: PROD_LocationDirectory_MoreData_VW
A5: Region Name | B5: CompanyCode | C5: Store # | D5: Location Name | E5: Street Address | F5: City | G5: State | H5: Zip Code | I5: Phone
A6: TX-Houston | B6: 804 | C6: 0002 | D6: Gessner | E6: 1038 GESSNER DRIVE | F6: HOUSTON | G6: TX | H6: 77055 | I6: (713) 461-0541
A7: NM-Farmington | B7: 807 | C7: 0031 | D7: E 20th | E7: 2609 E 20TH STREET | F7: FARMINGTON | G7: NM | H7: 87401 | I7: (505) 325-1347
A8: AL-Huntsville | B8: 813 | C8: 0042 | D8: Limestone | E8: 1321 US HIGHWAY 72 E | F8: ATHENS | G8: AL | H8: 35611-4405 | I8: (256) 233-2290
A9: FL-Orlando | B9: 812 | C9: 0227 | D9: Sanford Wash | E9: 1851 RINEHART RD | F9: SANFORD | G9: FL | H9: 32771 | I9: (321) 333-4296
A10: AL-Birmingham | B10: 813 | C10: 0242 | D10: Vestavia Wash | E10: 611 MONTGOMERY HWY | F10: VESTAVIA HILLS | G10: AL | H10: 35216 | I10: (205) 979-0968
A11: FL-Tampa | B11: 812 | C11: 0272 | D11: Adamo | E11: 9995 E ADAMO DR | F11: BRANDON | G11: FL | H11: 33619 | I11: (813) 627-8913
A12: FL-Lakeland | B12: 812 | C12: 0275 | D12: Miriam | E12: 5031 S FLORIDA AVE | F12: LAKELAND | G12: FL | H12: 33813-2511 | I12: (863) 644-1456
A13: TX-Abilene | B13: 818 | C13: 0293 | D13: S 27th St | E13: 2350 SOUTH 27TH ST | F13: ABILENE | G13: TX | H13: 79605-6132 | I13: (325) 690-0077
A14: TX-Lubbock | B14: 818 | C14: 0299 | D14: Quaker | E14: 7027 QUAKER AVE | F14: LUBBOCK | G14: TX | H14: 79424 | I14: (806) 791-2222
A15: TX-Austin | B15: 806 | C15: 0306 | D15: Round Rock | E15: 2720 S INTERSTATE 35 | F15: ROUND ROCK | G15: TX | H15: 78681 | I15: (512) 218-4000
A16: TX-Killeen/Mesquite | B16: 807 | C16: 0314 | D16: Temple | E16: 5284 W ADAMS AVE | F16: TEMPLE | G16: TX | H16: 76502 | I16: (254) 774-9883
A17: AZ-Tucson | B17: 806 | C17: 0328 | D17: Euclid | E17: 730 E BROADWAY BLVD | F17: TUCSON | G17: AZ | H17: 85719 | I17: (520) 623-2923
A18: CO-Colorado Springs/Pueblo/Denver | B18: 810 | C18: 0346 | D18: Glenroyal | E18: 1711 S PUEBLO BLVD | F18: PUEBLO | G18: CO | H18: 81005 | I18: (520) 367-3192
A19: TX-El Paso | B19: 806 | C19: 0361 | D19: Vista Del Sol | E19: 11184 VISTA DEL SOL | F19: EL PASO | G19: TX | H19: 79935 | I19: (915) 629-0622
A20: NM-Albuquerque | B20: 806 | C20: 0396 | D20: Highway 528 | E20: 3625 HWY 528 N W | F20: ALBUQUERQUE | G20: NM | H20: 87114 | I20: (505) 890-1064
A21: WA-Spokane | B21: 810 | C21: 0441 | D21: Five Mile | E21: 1615 W FIVE MILE ROAD | F21: SPOKANE | G21: WA | H21: 99208 | I21: (509) 570-0440
A22: MI-Grand Rapids | B22: 810 | C22: 0461 | D22: Wyoming | E22: 1259 28TH ST SW | F22: WYOMING | G22: MI | H22: 49509 | I22: (616) 538-6520
A23: WI-Madison/IL | C23: 0480 | D23: Madison Wi Warehouse | E23: 1039 E WASHINGTON AVE | F23: MADISON | G23: WI | H23: 53703 | I23: (111) 111-1111
A24: WI-Milwaukee | B24: 810 | C24: 0489 | D24: Greenfield | E24: 10685 W LAYTON AVE | F24: MILWAUKEE | G24: WI | H24: 53228-3248 | I24: (414) 269-2425
A25: ID-Boise | B25: 800 | C25: 0505 | D25: Front Street | E25: 1300 W FRONT STREET | F25: BOISE | G25: ID | H25: 83702 | I25: (208) 343-5298
A26: UT-Salt Lake City | B26: 800 | C26: 0530 | D26: Draper | E26: 387 E 12300 S | F26: DRAPER | G26: UT | H26: 84020 | I26: (801) 495-3040
A27: WA-Tri-Cities | B27: 800 | C27: 0580 | D27: Fruitland | E27: 520 W COLUMBIA DRIVE | F27: KENNEWICK | G27: WA | H27: 99336 | I27: (509) 265-8011
A28: MN-Minneapolis/Rochester | B28: 801 | C28: 0600 | D28: Minnesota Warehouse | E28: 3650 ANNAPOLIS LANE STE 190 | F28: PLYMOUTH | G28: MN | H28: 55447 | I28: (612) 209-4803
A29: IA-Cedar Rapids/Davenport | B29: 801 | C29: 0728 | D29: Williams Blvd | E29: 3405 WILLIAMS BLVD SW | F29: CEDAR RAPIDS | G29: IA | H29: 52404 | I29: (319) 284-9374
A30: IA-Des Moines | B30: 801 | C30: 0730 | D30: 14th Street | E30: 3400 SE 14TH ST | F30: DES MOINES | G30: IA | H30: 50320 | I30: (515) 974-5062
A31: MO-Springfield | B31: 801 | C31: 0752 | D31: Sunshine | E31: 2323 E SUNSHINE ST | F31: SPRINGFIELD | G31: MO | H31: 65804 | I31: (417) 883-4999
A32: TN-Nashville/Clarksville | B32: 816 | C32: 0843 | D32: Northside | E32: 2239 GALLATIN PIKE N | F32: MADISON | G32: TN | H32: 37115-2018 | I32: (615) 859-6700
A33: MS-Jackson | B33: 815 | C33: 0865 | D33: Lakeland | E33: 3510 LAKELAND DR | F33: FLOWOOD | G33: MS | H33: 39232 | I33: (769) 230-4099
A34: CA-Modesto | B34: 831 | C34: 0924 | D34: South Mchenry | E34: 448 MCHENRY AVENUE | F34: MODESTO | G34: CA | H34: 95354 | I34: (209) 522-9274
A35: CA-Bakersfield | B35: 830 | C35: 1009 | D35: Panama | E35: 3201 PANAMA LANE | F35: BAKERSFIELD | G35: CA | H35: 93313 | I35: (661) 831-7857
A36: CA-Los Angeles | B36: 830 | C36: 1037 | D36: Varsity | E36: 4212 N VARSITY AVE | F36: SAN BERNARDINO | G36: CA | H36: 92407 | I36: (909) 277-6601
A37: CA-San Joaquin Valley | B37: 830 | C37: 1039 | D37: Mooney Blvd | E37: 1920 S MOONEY BLVD | F37: VISALIA | G37: CA | H37: 93277 | I37: (559) 372-0454
A38: GA-Atlanta | B38: 813 | C38: 1248 | D38: Pleasant Hill Rd | E38: 2350 PLEASANT HILL RD | F38: DULUTH | G38: GA | H38: 30096 | I38: (678) 473-4744
A39: NM-Las Cruces | B39: 806 | C39: 1390 | D39: Rinconada | E39: 3501 NORTHRISE DR | F39: LAS CRUCES | G39: NM | H39: 88011 | I39: (575) 233-7109
A40: MI-Saginaw | B40: 810 | C40: 1467 | D40: Bay Road | E40: 3475 BAY ROAD | F40: SAGINAW | G40: MI | H40: 48603 | I40: (989) 497-0000
A41: PA-Lancaster/Reading | B41: 801 | C41: 1686 | D41: Lincoln Hwy | E41: 2175 LINCOLN HWY | F41: LANCASTER | G41: PA | H41: 17602 | I41: (717) 553-0443
A42: FL-Cape Coral | B42: 832 | C42: 1813 | D42: Arborwood | E42: 13601 GOLDENWOOD DR | F42: FORT MYERS | G42: FL | H42: 33913 | I42: (239) 241-8294
A43: FL-Southeast Florida | B43: 832 | C43: 1854 | D43: Hypoluxo | E43: 1833 HYPOLUXO RD | F43: LANTANA | G43: FL | H43: 33462 | I43: (561) 407-0035
A44: CA-Victor Valley | B44: 830 | C44: 2302 | D44: Mcart | E44: 15200 PALMDALE ROAD | F44: VICTORVILLE | G44: CA | H44: 92392 | I44: (760) 821-0091
I45: Shipped | J45: =SUM(J6:J44) -> 0 | K45: =SUM(K6:K44) -> 0 | L45: =SUM(L6:L44) -> 0

Sheet Warehouses
A1: PLEASE DOWNLOAD A COPY OF THE SHIPPING KEY TO WORK ON - don't edit this document | E1: Domo card to get data: | F1: MKTG Shipping Key - Warehouses
A2: Shipping Key - Warehouses | E2: Source dataset: | F2: PROD_LocationDirectory_MoreData_VW
A5: Region | B5: Store # | C5: Location Name | D5: Address | E5: City | F5: State | G5: Zip Code | H5: Phone Number
A6: AL-Huntsville | B6: 0040 | C6: Hunstville Warehouse | D6: 20518 NUCLEAR PLANT RD | E6: TANNER | F6: AL | G6: 35671 | H6: (256) 233-2290
A7: TX-Houston | B7: 0099 | C7: Houston Regional Admin | D7: 1034 GESSNER DR | E7: HOUSTON | F7: TX | G7: 77055 | H7: (713) 467-1400
A8: FL-Orlando | B8: 0200 | C8: Orlando Warehouse | D8: 1851 RINEHART RD | E8: SANFORD | F8: FL | G8: 32771 | H8: (111) 111-1111
A9: FL-Tampa | B9: 0220 | C9: Tampa Warehouse | D9: 4582 EAGLE FALLS PLACE | E9: TAMPA | F9: FL | G9: 33619 | H9: (111) 111-1111
A10: AL-Birmingham | B10: 0240 | C10: Alabama Warehouse | D10: 4621 HWY 280 SOUTH | E10: BIRMINGHAM | F10: AL | G10: 35242 | H10: (205) 991-7335
A11: GA-Atlanta | B11: 0250 | C11: Georgia Warehouse | D11: 4155 SHACKLEFORD ROAD SUITE 240 | E11: NORCROSS | F11: GA | G11: 30093 | H11: (407) 347-7997
A12: TX-Abilene | B12: 0289 | C12: Abilene Warehouse | D12: 2303 IMPACT DR | E12: ABILENE | F12: TX | G12: 79603 | H12: (111) 111-1111
A13: TX-Lubbock | B13: 0290 | C13: Lubbock Warehouse | D13: 7027 QUAKER AVE | E13: LUBBOCK | F13: TX | G13: 79424 | H13: (806) 791-2222
A14: TX-Austin | B14: 0300 | C14: Austin Warehouse | D14: 8421 RESEARCH BLVD UNIT A | E14: AUSTIN | F14: TX | G14: 78758 | H14: (512) 248-1900
A15: TX-Killeen/Mesquite | B15: 0310 | C15: Killeen Warehouse | D15: 1701 E VETERANS MEMORIAL BLVD | E15: KILLEEN | F15: TX | G15: 76541 | H15: (254) 554-3124
A16: AZ-Tucson | B16: 0320 | C16: Tucson Warehouse | D16: 2301 N FORBES BLVD STE 105 | E16: TUCSON | F16: AZ | G16: 85745-1431 | H16: (520) 615-4000
A17: CO-Colorado Springs/Pueblo/Denver | B17: 0340 | C17: Colorado Warehouse | D17: 1711 S PUEBLO BLVD | E17: PUEBLO | F17: CO | G17: 81005 | H17: (111) 111-1111
A18: TX-El Paso | B18: 0350 | C18: El Paso Warehouse | D18: 6800 GATEWAY BOULEVARD EAST BUILDING 5 | E18: EL PASO | F18: TX | G18: 79915 | H18: (915) 781-4359
A19: NM-Albuquerque | B19: 0390 | C19: New Mexico Warehouse | D19: 4320 PASEO DEL NORTE NE SUITE B | E19: ALBUQUERQUE | F19: NM | G19: 87113 | H19: (505) 322-2937
A20: WA-Tri-Cities | B20: 0450 | C20: Tri-Cities Regional Warehouse | D20: 458 STEVENS DR | E20: RICHLAND | F20: WA | G20: 99352 | H20: (111) 111-1111
A21: MI-Grand Rapids | B21: 0460 | C21: Grand Rapids Michigan Warehouse | D21: 2719 HAGUE AVE SW | E21: WYOMING | F21: MI | G21: 49519-2332 | H21: (616) 538-6715
A22: WI-Madison/IL | B22: 0480 | C22: Madison Wi Warehouse | D22: 1039 E WASHINGTON AVE | E22: MADISON | F22: WI | G22: 53703 | H22: (111) 111-1111
A23: IL-Rockford | B23: 0490 | C23: Illinois Warehouse | D23: MISTER CAR WASH #490 | E23: ROCKFORD | F23: IL | G23: 61108
A24: WI-Milwaukee | B24: 0499 | C24: Milwaukee Wi Warehouse | D24: 10685 W LAYTON AVE | E24: GREENFIELD | F24: WI | G24: 53228 | H24: (111) 111-1111
A25: ID-Boise | B25: 0500 | C25: Warehouse Boise | D25: 377 N FIVE MILE | E25: BOISE | F25: ID | G25: 83704 | H25: (208) 322-5950
A26: UT-Salt Lake City | B26: 0510 | C26: Utah Warehouse | D26: 2020 W 2200 S | E26: WEST VALLEY CITY | F26: UT | G26: 84119-1324 | H26: (111) 111-1111
A27: WA-Spokane | B27: 0570 | C27: Spokane Warehouse | D27: 17207 E DALTON AVE | E27: SPOKANE VALLEY | F27: WA | G27: 99216 | H27: (111) 111-1111
A28: MN-Minneapolis/Rochester | B28: 0600 | C28: Minnesota Warehouse | D28: 3650 ANNAPOLIS LANE STE 190 | E28: PLYMOUTH | F28: MN | G28: 55447 | H28: (612) 209-4803
A29: MD-Baltimore | B29: 0650 | C29: Maryland Corporate Cost Center | D29: 2473 SOLOMONS ISLAND RD | E29: EDGEWATER | F29: MD | G29: 21037
A30: PA-Lancaster/Reading | B30: 0685 | C30: Pennsylvania Warehouse | D30: 1897 COMMERCE PARK EAST | E30: LANCASTER | F30: PA | G30: 17601 | H30: (111) 111-1111
A31: IA-Des Moines | B31: 0700 | C31: Iowa Warehouse | D31: 4705 NW 59TH AVE #102 | E31: JOHNSTON | F31: IA | G31: 50131 | H31: (520) 622-2624
A32: IA-Cedar Rapids/Davenport | B32: 0710 | C32: Cedar Rapids Warehouse | D32: 3321 J STREET | E32: CEDAR RAPIDS | F32: IA | G32: 52404 | H32: (111) 111-1111
A33: MO-Springfield | B33: 0750 | C33: Springfield Warehouse | D33: 2325 E BENNETT SUITE A | E33: SPRINGFIELD | F33: MO | G33: 65804 | H33: (111) 111-1111
A34: TN-Nashville/Clarksville | B34: 0830 | C34: Tennessee Warehouse | D34: 5211 LINBAR DR SUITE 515 | E34: NASHVILLE | F34: TN | G34: 37211 | H34: (111) 111-1111
A35: MS-Jackson | B35: 0860 | C35: Jackson Ms Warehouse | D35: 185 COUNTRY PLACE PARKWAY SUITE 780 | E35: PEARL | F35: MS | G35: 39208 | H35: (111) 111-1111
A36: CA-Modesto | B36: 0900 | C36: Modesto Warehouse | D36: 701 15TH ST | E36: MODESTO | F36: CA | G36: 95354 | H36: (111) 111-1111
A37: CA-Bakersfield | B37: 1000 | C37: Bakersfield Ca Warehouse | D37: 8501 PACHECO RD | E37: BAKERSFIELD | F37: CA | G37: 93311-8602 | H37: (661) 837-9472
A38: CA-San Joaquin Valley | B38: 1050 | C38: Tulare County Regional Admin | D38: 1620 HILLMAN ST | E38: TULARE | F38: CA | G38: 93274
A39: FL-Lakeland | B39: 1220 | C39: Lakeland Regional Admin | D39: 4582 EAGLE FALLS PLACE | E39: TAMPA | F39: FL | G39: 33619 | H39: (111) 111-1111
A40: MI-Saginaw | B40: 1460 | C40: Saginaw Regional Admin | D40: 3995 FASHION SQUARE BLVD SUITE 7 | E40: SAGINAW | F40: MI | G40: 48604 | H40: (989) 439-5594
A41: FL-Cape Coral | B41: 1810 | C41: Cape Coral Regional Admin | D41: 10105 AMBERWOOD RD ST3-4 | E41: FORT MYERS | F41: FL | G41: 33913 | H41: (111) 111-1111
A42: FL-Southeast Florida | B42: 1850 | C42: South East Florida Regional Admin | D42: MISTER CAR WASH #1850 | E42: PORT SAINT LUCIE | F42: FL | G42: 34984
A43: CA-Victor Valley | B43: 2300 | C43: Victor Valley Regional Admin | D43: MISTER CAR WASH #2300 | E43: VICTORVILLE | F43: CA | G43: 92392
A44: CA-Los Angeles | B44: 2320 | C44: Los Angeles Regional Admin | D44: 7310 ADAMS ST UNIT A | E44: PARAMOUNT | F44: CA | G44: 90723 | H44: (111) 111-1111
H45: Shipped | I45: =SUM(I5:I44) -> 0 | J45: =SUM(J5:J44) -> 0 | K45: =SUM(K5:K44) -> 0

Sheet Upcoming New Builds
A1: PLEASE DOWNLOAD A COPY OF THE SHIPPING KEY TO WORK ON - don't edit this document | H1: Domo card to get data: | I1: MKTG Shipping Key - Upcoming New Builds (Under Construction)
A2: Shipping Key - Upcoming New Builds | H2: Source dataset: | I2: PROD_LocationDirectory_MoreData_VW
M4: Item 1 | N4: Item 2 | O4: Item 3
A5: Region | B5: CC | C5: Store # | D5: Type | E5: Status | F5: Location Name | G5: General Manager | H5: Address | I5: City | J5: State | K5: Zip Code | L5: Phone
A6: TX-El Paso | B6: 806 | C6: 2546 | D6: Express | E6: Under Construction | F6: Justice | H6: 12253 MONTANA AVE | I6: EL PASO | J6: TX | K6: 79938 | L6: (111) 111-1111
L7: Shipped | M7: =SUM(M6) -> 0 | N7: =SUM(N6) -> 0 | O7: =SUM(O6) -> 0

Sheet Open Stores Data
A1: Domo card to get data: | B1: MKTG Shipping Key - Open Stores | E1: Source dataset: | F1: PROD_LocationDirectory_MoreData_VW
A3: Region | B3: CompanyCode | C3: StoreNumber | D3: StoreType | E3: StoreStatus | F3: StoreName | G3: GeneralManager | H3: StreetAddress | I3: City | J3: State | K3: PostalCode | L3: BusinessPhone
A4: TX-Houston | B4: 804 | C4: 0001 | D4: Interior Clean | E4: Operating | F4: Crosstimbers | G4: Brandon Van Laningham | H4: 640 WEST CROSSTIMBERS | I4: HOUSTON | J4: TX | K4: 77018 | L4: (713) 691-4636
A5: TX-Houston | B5: 804 | C5: 0002 | D5: Interior Clean | E5: Operating | F5: Gessner | G5: Tyrone Coleman | H5: 1038 GESSNER DRIVE | I5: HOUSTON | J5: TX | K5: 77055 | L5: (713) 461-0541
A6: TX-Houston | B6: 804 | C6: 0003 | D6: Interior Clean | E6: Operating | F6: Voss | G6: Guadalupe Marcos | H6: 2251 SOUTH VOSS ROAD | I6: HOUSTON | J6: TX | K6: 77057 | L6: (713) 783-5780
A7: TX-Houston | B7: 804 | C7: 0004 | D7: Interior Clean | E7: Operating | F7: 1960 East | G7: Mason Monaghan | H7: 210 FM 1960 ROAD EAST | I7: HOUSTON | J7: TX | K7: 77073 | L7: (281) 821-0476
A8: TX-Houston | B8: 804 | C8: 0005 | D8: Interior Clean | E8: Operating | F8: Westheimer | G8: Jorge Guzman | H8: 10760 WESTHEIMER | I8: HOUSTON | J8: TX | K8: 77042 | L8: (713) 789-6935
A9: TX-Houston | B9: 804 | C9: 0006 | D9: Interior Clean | E9: Operating | F9: Champions | G9: Pedro De La Cruz | H9: 6612 FM 1960 ROAD WEST | I9: HOUSTON | J9: TX | K9: 77069 | L9: (281) 537-8049
A10: TX-Houston | B10: 804 | C10: 0007 | D10: Express | E10: Operating | F10: Hillcroft | G10: Samuel Brenes | H10: 6107 HILLCROFT STREET | I10: HOUSTON | J10: TX | K10: 77081 | L10: (713) 777-9019
A11: TX-Houston | B11: 804 | C11: 0008 | D11: Interior Clean | E11: Operating | F11: Uvalde | G11: Dominick Tyler | H11: 380 UVALDE ROAD | I11: HOUSTON | J11: TX | K11: 77015 | L11: (713) 455-6651
A12: TX-Houston | B12: 804 | C12: 0009 | D12: Interior Clean | E12: Operating | F12: Humble | G12: Cj Nunn | H12: 9637 FM 1960 BY PASS WEST | I12: HUMBLE | J12: TX | K12: 77338 | L12: (281) 540-2988
A13: TX-Houston | B13: 804 | C13: 0010 | D13: Interior Clean | E13: Operating | F13: Kirby | G13: Armando Villegas | H13: 3150 KIRBY DRIVE | I13: HOUSTON | J13: TX | K13: 77098 | L13: (346) 395-5233
A14: TX-Houston | B14: 804 | C14: 0011 | D14: Interior Clean | E14: Operating | F14: Sugarland | G14: Charlie Saenz | H14: 2530 HIGHWAY 6 | I14: SUGAR LAND | J14: TX | K14: 77478 | L14: (346) 395-5219
A15: TX-Houston | B15: 804 | C15: 0012 | D15: Express | E15: Operating | F15: Galleria | G15: Samantha Hemsell | H15: 5735 WESTHEIMER RD | I15: HOUSTON | J15: TX | K15: 77057 | L15: (832) 678-3010
... A63: FL-Orlando | B63: 812 | C63: 0233 | D63: Express | E63: Operating | F63: Fern Park | G63: Skylar Prescott | H63: 6501 SOUTH US HWY 17 92 | I63: CASSELBERRY | J63: FL | K63: 32730 | L63: (407) 260-0335
A64: FL-Orlando | B64: 812 | C64: 0234 | D64: Express | E64: Operating | F64: French Ave | H64: 2418 S FRENCH AVE | I64: SANFORD | J64: FL | K64: 32771 | L64: (407) 322-6284
A65: FL-Orlando | B65: 812 | C65: 0235 | D65: Express | E65: Operating | F65: Colonial | G65: Holly Hutcheson | H65: 12180 E COLONIAL DR | I65: ORLANDO | J65: FL | K65: 32826 | L65: (407) 207-1294
A66: FL-Orlando | B66: 812 | C66: 0236 | D66: Express | E66: Operating | F66: Chickasaw | G66: Celi Cordero | H66: 7958 E COLONIAL DR | I66: ORLANDO | J66: FL | K66: 32807 | L66: (407) 203-0993
A67: AL-Birmingham | B67: 813 | C67: 0241 | D67: Interior Clean | E67: Operating | F67: Highway 280 Cw | G67: Jace Dailey | H67: 4621 HWY 280 SOUTH | I67: BIRMINGHAM | J67: AL | K67: 35242 | L67: (205) 991-7335
A68: AL-Birmingham | B68: 813 | C68: 0242 | D68: Express | E68: Operating | F68: Vestavia Wash | G68: Ken Duke | H68: 611 MONTGOMERY HWY | I68: VESTAVIA HILLS | J68: AL | K68: 35216 | L68: (205) 979-0968
A69: FL-Orlando | B69: 812 | C69: 0243 | D69: Express | E69: Operating | F69: Silver Star | G69: Brendan Gilreath | H69: 4551 SILVER STAR RD | I69: ORLANDO | J69: FL | K69: 32808 | L69: (407) 553-3430
A70: GA-Atlanta | B70: 813 | C70: 0246 | D70: Express | E70: Operating | F70: Dawsonville Hwy | G70: Adam Taylor | H70: 550 DAWSONVILLE HWY | I70: GAINESVILLE | J70: GA | K70: 30501 | L70: (770) 535-2588
A71: GA-Atlanta | B71: 813 | C71: 0247 | D71: Express | E71: Operating | F71: Oxford | G71: Joel Garrett | H71: 65 PLAZA LANE | I71: OXFORD | J71: AL | K71: 36203 | L71: (256) 835-1053
A72: GA-Atlanta | B72: 813 | C72: 0248 | D72: Express | E72: Operating | F72: Athens | G72: Tyler Trujillo | H72: 1035 PARKWAY BLVD | I72: ATHENS | J72: GA | K72: 30606-6171 | L72: (706) 521-5889
A73: GA-Atlanta | B73: 813 | C73: 0249 | D73: Express | E73: Operating | F73: Monroe | G73: John Zuber | H73: 170 MARTIN LUTHER KING JR BLVD | I73: MONROE | J73: GA | K73: 30655-5620 | L73: (770) 207-1900
A74: GA-Atlanta | B74: 813 | C74: 0252 | D74: Express | E74: Operating | F74: Griffin | G74: Elijah Marlyne | H74: 557 N EXPRESSWAY | I74: GRIFFIN | J74: GA | K74: 30223 | L74: (770) 228-8001
A75: GA-Atlanta | B75: 813 | C75: 0253 | D75: Express | E75: Operating | F75: Lovejoy | G75: Matthew Flowers | H75: 11303 TARA BLVD | I75: HAMPTON | J75: GA | K75: 30228 | L75: (770) 471-0019
A76: GA-Atlanta | B76: 813 | C76: 0254 | D76: Express | E76: Operating | F76: Stone Mountain | G76: Manny Ortiz | H76: 4850 STONE MOUNTAIN HWY | I76: LILBURN | J76: GA | K76: 30047 | L76: (706) 661-7058
... A114: TX-Killeen/Mesquite | B114: 807 | C114: 0314 | D114: Express | E114: Operating | F114: Temple | G114: William Wilkinson | H114: 5284 W ADAMS AVE | I114: TEMPLE | J114: TX | K114: 76502 | L114: (254) 774-9883
A115: TX-Killeen/Mesquite | B115: 807 | C115: 0315 | D115: Express | E115: Operating | F115: Ft Hood | H115: BLDG #50014 CLEAR CREEK RD | I115: FORT CAVAZOS | J115: TX | K115: 76544 | L115: (254) 432-6331
A116: TX-Austin | B116: 807 | C116: 0316 | D116: Express | E116: Operating | F116: Pflugerville | G116: Michael Chappell | H116: 15400 FM-1825 | I116: PFLUGERVILLE | J116: TX | K116: 78660 | L116: (512) 243-6372
A117: TX-Killeen/Mesquite | B117: 807 | C117: 0317 | D117: Express | E117: Operating | F117: Stan Schlueter Loop | G117: Jazmine Oden | H117: 3402 W STAN SCHLUETER LOOP | I117: KILLEEN | J117: TX | K117: 76549 | L117: (254) 232-0837
A118: TX-Austin | B118: 806 | C118: 0318 | D118: Express | E118: Operating | F118: Oakwood Blvd | G118: David Lesley | H118: 2000 ROUND ROCK AVE | I118: ROUND ROCK | J118: TX | K118: 78681 | L118: (512) 428-5855
A119: AZ-Tucson | B119: 806 | C119: 0321 | D119: Interior Clean - Flex | E119: Operating | F119: Tanque Verde | G119: Angel Plaza | H119: 6345 E TANQUE VERDE RD | I119: TUCSON | J119: AZ | K119: 85715 | L119: (520) 886-9573
A120: AZ-Tucson | B120: 806 | C120: 0322 | D120: Interior Clean - Flex | E120: Operating | F120: Oro Valley | G120: Adrian Plaza | H120: 8175 N ORACLE RD | I120: TUCSON | J120: AZ | K120: 85704 | L120: (520) 326-1755
A121: AZ-Tucson | B121: 806 | C121: 0324 | D121: Interior Clean - Flex | E121: Operating | F121: Cortaro | G121: Nsengiyumva Ndayambaje | H121: 8215 N COURTNEY PAGE WAY | I121: TUCSON | J121: AZ | K121: 85743 | L121: (520) 682-4312
A122: AZ-Tucson | B122: 806 | C122: 0325 | D122: Interior Clean | E122: Operating | F122: North Oracle | G122: Leondre Anderson | H122: 4941 N ORACLE RD | I122: TUCSON | J122: AZ | K122: 85704 | L122: (520) 888-6858
A123: AZ-Tucson | B123: 806 | C123: 0326 | D123: Express | E123: Operating | F123: Swan | G123: Sierrah Bainter | H123: 4600 E BROADWAY BLVD | I123: TUCSON | J123: AZ | K123: 85711-3512 | L123: (520) 428-0256
A124: AZ-Tucson | B124: 806 | C124: 0327 | D124: Interior Clean | E124: Operating | F124: South Kolb | G124: Evelyn Conger | H124: 2409 S KOLB RD | I124: TUCSON | J124: AZ | K124: 85710 | L124: (520) 721-9290
A125: AZ-Tucson | B125: 806 | C125: 0328 | D125: Express | E125: Operating | F125: Euclid | G125: Stefanie Osuna | H125: 730 E BROADWAY BLVD | I125: TUCSON | J125: AZ | K125: 85719 | L125: (520) 623-2923
A126: AZ-Tucson | B126: 806 | C126: 0329 | D126: Express | E126: Operating | F126: Speedway | G126: Colton Smith | H126: 3101 E SPEEDWAY BLVD | I126: TUCSON | J126: AZ | K126: 85716 | L126: (520) 327-5656
A127: AZ-Tucson | B127: 806 | C127: 0330 | D127: Express | E127: Operating | F127: Kino | G127: Alexander Zoechbauer | H127: 2975 S KINO PARKWAY | I127: TUCSON | J127: AZ | K127: 85713 | L127: (520) 338-8640
